Workbook

Sheet Filmes
A1: ID | B1: Mostra | C1: Letterboxd | D1: Filme | E1: Título no catálogo | F1: Fonte | G1: País / território (programação) | H1: Formato (programação) | I1: Duração programada (min) | J1: Ano | K1: País | L1: Gênero (ficha) | M1: Selecionado para Festival A? | N1: Festival A | O1: Mostra / Seção | P1: Direção | Q1: Roteiro | R1: Produtora | S1: Produção | T1: Fotografia | U1: Montagem | V1: Música | W1: Elenco / participações | X1: Sinopse | Y1: Ficha técnica padronizada | Z1: Nº de sessões | AA1: Ano | AB1: Gênero padronizado
A2: 001 | B2: Panorama Mundial | C2: https://boxd.it/Rw9k | D2: A Grande Estreia | E2: Debut, The | F2: Catálogo | G2: Estados Unidos | H2: Ficção | I2: 105 | J2: 2026 | K2: Estados Unidos | L2: Ficção | P2: Jesse Eisenberg | Q2: Jesse Eisenberg | R2: Topic Studios, Fruit Tree | S2: Ali Herting, Dave Mccary, Emma Stone | T2: Drew Daniels | U2: Robert Nassau | V2: Emile Mosseri | W2: Julianne Moore, Paul Giamatti, Halle Bailey, Jesse Eisenberg, Cara Buono, Craig Bierko, Eldar Isgandarov, Bernadette Peters | X2: Quando Mona Friedman, uma dona de casa tímida e discreta, consegue um pequeno papel em um teatro comunitário, mergulha no método e se torna obcecada em defender a integridade artística de sua participação quase insignificante. Disposta a tudo, ela entra em guerra com o autoritário diretor do espetáculo. Estrelada por Julianne Moore e Paul Giamatti, esta comédia musical satiriza o ego, a ambição e os delírios da criação. Seleção do Festival de Toronto e competição oficial do Festival de San Sebastián 2026. | Y2: Direção: Jesse Eisenberg | Roteiro: Jesse Eisenberg | Produtora: Topic Studios, Fruit Tree | Produção: Ali Herting, Dave Mccary, Emma Stone | Fotografia: Drew Daniels | Montagem: Robert Nassau | Música: Emile Mosseri | Elenco: Julianne Moore, Paul Giamatti, Halle Bailey, Jesse Eisenberg, Cara Buono, Craig Bierko, Eldar Isgandarov, Bernadette Peters | Z2: 3 | AA2: 2026 | AB2: Ficção
A3: 002 | B3: Panorama Mundial | C3: https://boxd.it/Zo9i | D3: A Noiva Difícil | E3: Difficult Bride, The | F3: Catálogo | G3: França + 4 países | H3: Ficção | I3: 87 | J3: 2026 | K3: França, Portugal, Bangladesh, Noruega, Alemanha | L3: Ficção | P3: Rubaiyat Hossain | Q3: Rubaiyat Hossain | R3: Les Films de L’après-Midi | S3: François D’artemare | T3: Leonor Teles | U3: Raphaëlle Martin-Hölger | V3: Jim Williams | W3: Zaineen Chowdhury Karim, Saberi Alam Motaher, Reekita Nondine Shimu, Azmeri Haque, Sunerah Binte Kamal, Shatabdi Wadud, Dameer Khan, Mohammed Bari | X3: Em Daca, Zaineen se prepara para o próprio casamento, entre rituais de beleza e expectativas familiares. Mas seu corpo começa a reagir de maneiras inesperadas. Enquanto remédios caseiros, pressões sociais e visões perturbadoras se acumulam, o caminho até o altar se transforma em uma luta física e psicológica contra os papéis impostos às mulheres. Entre o real e o sobrenatural, ela busca a liberdade de existir para além da feminilidade prescrita. Seleção da mostra Orizzonti do Festival de Veneza 2026. | Y3: Direção: Rubaiyat Hossain | Roteiro: Rubaiyat Hossain | Produtora: Les Films de L’après-Midi | Produção: François D’artemare | Fotografia: Leonor Teles | Montagem: Raphaëlle Martin-Hölger | Música: Jim Williams | Elenco: Zaineen Chowdhury Karim, Saberi Alam Motaher, Reekita Nondine Shimu, Azmeri Haque, Sunerah Binte Kamal, Shatabdi Wadud, Dameer Khan, Mohammed Bari | Z3: 3 | AA3: 2026 | AB3: Ficção
A4: 003 | B4: Panorama Mundial | C4: https://boxd.it/W19e | D4: A Terceira Noite | E4: Troisième nuit, La | F4: Catálogo | G4: França | H4: Ficção | I4: 90 | J4: 2026 | K4: França | L4: Ficção | M4: Sim | N4: Cannes | O4: Cannes Première | P4: Daniel Auteuil | Q4: Daniel Auteuil, Camille Lugan | R4: Palatio Films, Les Films Velvet | S4: Frédéric Jouve, Adrien Nussembaum, Nelly Auteuil | T4: Jean-François Hensgens | U4: Valérie Deseine | V4: Oliver Goinard | W4: Antonie Reinartz, Daniel Auteuil, Luàna Bjarami, Grégory Gadebois, Grégoire Colin, Yannick Choirat, Jean- Paul Muel | X4: Em agosto de 1942, na França ocupada, o governo de Vichy organiza a deportação em massa de judeus estrangeiros. Um jovem funcionário público encarregado da triagem e um padre humanitário unem forças secretas para desafiar a burocracia do Estado. Juntos, arriscam tudo em uma missão desesperada para salvar mais de cem crianças judias de um campo perto de Lyon. | Y4: Direção: Daniel Auteuil | Roteiro: Daniel Auteuil, Camille Lugan | Produtora: Palatio Films, Les Films Velvet | Produção: Frédéric Jouve, Adrien Nussembaum, Nelly Auteuil | Fotografia: Jean-François Hensgens | Montagem: Valérie Deseine | Música: Oliver Goinard | Elenco: Antonie Reinartz, Daniel Auteuil, Luàna Bjarami, Grégory Gadebois, Grégoire Colin, Yannick Choirat, Jean- Paul Muel | Z4: 3 | AA4: 2026 | AB4: Ficção
A5: 004 | B5: Panorama Mundial | C5: https://boxd.it/VBPy | D5: Amazomania | F5: Complementar / catálogo parcial | G5: Suécia + 2 países | H5: Documentário | I5: 95 | J5: 2026 | K5: Dinamarca, França, Suécia | L5: Documentário | P5: Nathan Grossman | R5: B-Reel Films | S5: Cecilia Nessen | T5: Nathan Grossman, Erling Söderström, Diego Lajst | U5: Jordana Berg, Nathan Grossman | V5: Nicole Hogstrand, Thora Kidon Jæger | W5: Barbara Arisi, Binan Tuku, Comunidade Korubo, Erling Söderström, Malevo, Seatvo, Sydney Possuelo, Takvan, Takvan Vakwë, Xikxuvo | X5: Em 1996, um servidor público brasileiro e um jornalista sueco entraram na Amazônia para documentar o primeiro contato com o povo Korubo, até então completamente isolado. Quase três décadas depois, as imagens ressurgem sob uma perspectiva inquietante. Ao refazer sua jornada e voltar ao Brasil após décadas, o jornalista encontra os Korubo exigindo reparação e o direito de contar a própria história. O resultado confronta o olhar colonial, os mal-entendidos culturais, o empoderamento dos povos indígenas e a própria ética do documentário. Prêmio FIPRESCI no CPH:DOX 2026. | Y5: Direção: Nathan Grossman | Produtora: B-Reel Films | Produção: Cecilia Nessen | Fotografia: Nathan Grossman, Erling Söderström, Diego Lajst | Montagem: Jordana Berg, Nathan Grossman | Música: Nicole Hogstrand, Thora Kidon Jæger | Elenco: Barbara Arisi, Binan Tuku, Comunidade Korubo, Erling Söderström, Malevo, Seatvo, Sydney Possuelo, Takvan, Takvan Vakwë, Xikxuvo | Z5: 2 | AA5: 2026 | AB5: Documentário
A6: 005 | B6: Panorama Mundial | C6: https://boxd.it/MK5w | D6: As Crianças Estão Bem | E6: Enfants Vont Bien, Les | F6: Catálogo | G6: França | H6: Ficção | I6: 111 | J6: 2025 | K6: França | L6: Ficção | P6: Nathan Ambrosioni | Q6: Nathan Ambrosioni | R6: Chi-Fou-Mi Productions | S6: Nicolas Dumont, Hugo Selignac | T6: Victor Seguin - Afc | U6: Nathan Ambrosioni, Alexandre Hecker, Laure-Anne Darras, Olivier Guillaume | V6: Alexandre de la Baume | W6: Camille Cottin, Monia Chokri, Juliette Armanet, Manoã Varvat, Nina Birman, Guillaume Gouix, Myriem Akheddiou, Franckie Wallach, Tania Dessources, Camille Lethuillier, Maxime Tshibangu, Féodor Atkine | X6: Numa noite de verão, Suzanne visita a irmã Jeanne e deixa com ela os dois filhos pequenos. Na manhã seguinte, Suzanne desaparece sem deixar rastros, exceto por uma carta pedindo que não a procurem. Jeanne vê-se subitamente forçada a assumir o papel de mãe biológica e a cuidar dos sobrinhos diante de um abandono voluntário. Enquanto a família tenta digerir o trauma e a ausência enigmática da mãe, o drama foca na perda da inocência e na resiliência das crianças. Em competição no Festival de Cannes 2026. | Y6: Direção: Nathan Ambrosioni | Roteiro: Nathan Ambrosioni | Produtora: Chi-Fou-Mi Productions | Produção: Nicolas Dumont, Hugo Selignac | Fotografia: Victor Seguin - Afc | Montagem: Nathan Ambrosioni, Alexandre Hecker, Laure-Anne Darras, Olivier Guillaume | Música: Alexandre de la Baume | Elenco: Camille Cottin, Monia Chokri, Juliette Armanet, Manoã Varvat, Nina Birman, Guillaume Gouix, Myriem Akheddiou, Franckie Wallach, Tania Dessources, Camille Lethuillier, Maxime Tshibangu, Féodor Atkine | Z6: 5 | AA6: 2025 | AB6: Ficção
A7: 006 | B7: Panorama Mundial | C7: https://boxd.it/ST8Q | D7: Bucking Fastard | F7: Complementar / catálogo parcial | G7: Estados Unidos | H7: Ficção | I7: 109 | J7: 2026 | K7: Estados Unidos | L7: Ficção | M7: Sim | N7: Veneza | O7: Venezia 83 – Competição | P7: Werner Herzog | Q7: Werner Herzog | R7: Gateway To Orkney, Providence Road Entertainment | S7: Clara Wu Tsai, Werner Herzog, Ariel Leon Isacovitch | T7: Peter Zeitlinger | U7: Marco Capalbo | V7: Ernst Reijseger | W7: Kate Mara, Rooney Mara, Orlando Bloom, Domhnall Gleeson | X7: Jean e Joan Holbrooke são irmãs tão inseparáveis que falam em uníssono, compartilham os mesmos sonhos e amam o mesmo homem. Em busca de uma terra imaginária onde o amor verdadeiro seja possível, decidem escavar um túnel através de uma cadeia de montanhas. Livremente inspirado nas gêmeas britânicas Freda e Greta Chaplin, Werner Herzog transforma sua obstinação numa fábula sobre amor, marginalidade e sonhos impossíveis. Com Kate e Rooney Mara. Selecionado para a competição do Festival de Veneza de 2026. | Y7: Direção: Werner Herzog | Roteiro: Werner Herzog | Produtora: Gateway To Orkney, Providence Road Entertainment | Produção: Clara Wu Tsai, Werner Herzog, Ariel Leon Isacovitch | Fotografia: Peter Zeitlinger | Montagem: Marco Capalbo | Música: Ernst Reijseger | Elenco: Kate Mara, Rooney Mara, Orlando Bloom, Domhnall Gleeson | Z7: 3 | AA7: 2026 | AB7: Ficção
A8: 007 | B8: Panorama Mundial | C8: https://boxd.it/Odiw | D8: Cartas Amarelas | E8: Gelbe Briefe | F8: Catálogo | G8: Alemanha + 2 países | H8: Ficção | I8: 127 | J8: 2026 | K8: França, Alemanha, Turquia | L8: Ficção | M8: Sim | N8: Berlinale | O8: Competição Oficial | P8: Ilker Çatak | Q8: Ayda Meryem Çatak, Enis Köstepen | R8: Liman Film, If... Productions, Haut Et Court | S8: Ingo Fliess | T8: Judith Kaufmann | U8: Gesa Jäger | V8: Marvin Miller | W8: Yusuf Akgün, Aydin Işik, Aziz Çapkurt, Elit İşcan, Emine Meyrem, Emre Bakar, Ipek Seyalioglu, Jale Arikan, Leyla Smyrna Cabas, Seda Türkmen, Sultan Ulutaş, Tansu Biçer, Uygar Tamer, Yusuf Özhan Tali, Özgü Namal, İpek Bilgin | X8: Em Ancara, Derya e Aziz formam um respeitado casal de artistas: ela é atriz, ele é dramaturgo e professor. Durante a estreia de uma nova peça, um gesto de desobediência os coloca sob investigação do Estado. Em poucos dias, perdem o trabalho e a casa e precisam se mudar com a filha adolescente para Istambul. À medida que o dinheiro escasseia e a pressão autoritária invade a vida doméstica, suas convicções, o casamento e o futuro da família são postos à prova. Urso de Ouro no Festival de Berlim 2026. | Y8: Direção: Ilker Çatak | Roteiro: Ayda Meryem Çatak, Enis Köstepen | Produtora: Liman Film, If... Productions, Haut Et Court | Produção: Ingo Fliess | Fotografia: Judith Kaufmann | Montagem: Gesa Jäger | Música: Marvin Miller | Elenco: Yusuf Akgün, Aydin Işik, Aziz Çapkurt, Elit İşcan, Emine Meyrem, Emre Bakar, Ipek Seyalioglu, Jale Arikan, Leyla Smyrna Cabas, Seda Türkmen, Sultan Ulutaş, Tansu Biçer, Uygar Tamer, Yusuf Özhan Tali, Özgü Namal, İpek Bilgin | Z8: 3 | AA8: 2026 | AB8: Ficção
A9: 008 | B9: Panorama Mundial | C9: https://boxd.it/xG0M | D9: Cavalo Selvagem Nove | E9: Wild Horse Nine | F9: Catálogo | G9: Reino Unido + 1 país | H9: Ficção | I9: 116 | J9: 2026 | K9: Estados Unidos, Reino Unido | L9: Ficção | M9: Sim | N9: Veneza | O9: Venezia 83 – Competição | P9: Martin Mcdonagh | Q9: Martin Mcdonagh | R9: Searchlight Pictures, Blueprint Pictures, Film4 | S9: Graham Broadbent, Pete Czernin, Martin Mcdonagh, Anita Overland | T9: Ben Davis, Bsc | U9: Mikkel e G Nielsen, Ace | V9: Carter Burwell | W9: John Malkovich, Sam Rockwell, Steve Buscemi, Mariana di Girolamo, Ailín Salas, Tom Waits, Parker Posey | X9: Pouco antes do golpe de Estado no Chile em 1973, dois agentes da CIA são enviados de Santiago para a Ilha de Páscoa em uma missão de teste de confiança. Entre as famosas estátuas que são o marco da ilha, conhecidas como muais, eles enfrentam passados sombrios e conspirações, enquanto o envolvimento de um dos agentes com estudantes rebeldes ameaça arruinar a viagem. Uma afiada combinação de thriller político, drama existencial e comédia sombria. | Y9: Direção: Martin Mcdonagh | Roteiro: Martin Mcdonagh | Produtora: Searchlight Pictures, Blueprint Pictures, Film4 | Produção: Graham Broadbent, Pete Czernin, Martin Mcdonagh, Anita Overland | Fotografia: Ben Davis, Bsc | Montagem: Mikkel e G Nielsen, Ace | Música: Carter Burwell | Elenco: John Malkovich, Sam Rockwell, Steve Buscemi, Mariana di Girolamo, Ailín Salas, Tom Waits, Parker Posey | Z9: 5 | AA9: 2026 | AB9: Ficção
A10: 009 | B10: Panorama Mundial | C10: https://boxd.it/15fbc | D10: Cidadão Osama | E10: Al mowaten Osama | F10: Catálogo | G10: Palestina + 2 países | H10: Documentário | I10: 69 | J10: 2026 | K10: Palestina, França, Catar | L10: Documentário | P10: Ahmed Hassouna | R10: Filcam Media For Media Production, Masharawi Fund For Films & Filmmakers, Coorigines Production | S10: Laura Nikolov, Rashid Masharawi, Ahmed Hassouna | T10: Ahmed Hassouna | U10: DENIS LE PAVEN Edição de Som e Mixagem /Sound Editing and Mixing: HATEM SALMI | V10: Rasmus Steen, Sarah Fasseur-Leroux | W10: Osama Al-Ashi | X10: No norte da Faixa de Gaza sob cerco, Osama, ex-fotógrafo artístico que se tornou documentarista de guerra, tenta proteger a esposa e o filho recém-nascido enquanto registra a devastação ao seu redor. Entre bombardeios, fome e perdas, divide-se entre o dever de testemunhar e as urgências da paternidade. Filmado em meio à guerra, o documentário acompanha um homem que mostra a tragédia ao mundo enquanto também a vive. Estreia mundial no Venice Open do Festival de Veneza de 2026. | Y10: Direção: Ahmed Hassouna | Produtora: Filcam Media For Media Production, Masharawi Fund For Films & Filmmakers, Coorigines Production | Produção: Laura Nikolov, Rashid Masharawi, Ahmed Hassouna | Fotografia: Ahmed Hassouna | Montagem: DENIS LE PAVEN Edição de Som e Mixagem /Sound Editing and Mixing: HATEM SALMI | Música: Rasmus Steen, Sarah Fasseur-Leroux | Elenco: Osama Al-Ashi | Z10: 3 | AA10: 2026 | AB10: Documentário
A11: 010 | B11: Panorama Mundial | C11: https://boxd.it/HOdk | D11: Contos Paralelos | E11: Histoires parallèles | F11: Catálogo | G11: França | H11: Ficção | I11: 141 | J11: 2026 | K11: França | L11: Ficção | M11: Sim | N11: Cannes | O11: Competição Oficial | P11: Asghar Farhadi | Q11: Asghar Farhadi, Saeed Farhadi, Krzysztof Kieslowski | R11: Anonymous Content, Memento Production | S11: Alexandre Mallet-Guy, Asghar Farhadi, David Levine | T11: Guillaume Deffontaines | U11: Hayedeh Safiyari | V11: Zbigniew Preisner | W11: Isabelle Huppert, Virginie Efira, Vincent Cassel, Adam Bessa, Pierre Niney, India Hair, Catherine Deneuve | X11: Em busca de inspiração para o seu novo romance, Sylvie, uma famosa escritora reclusa em Paris, passa os dias a espionar a vida dos vizinhos do prédio da frente com uma luneta. Decidida a movimentar a rotina, ela contrata o enigmático jovem Adam como seu assistente de escrita. Ela só não imaginava que a presença dele viraria o seu mundo e o seu trabalho de cabeça para baixo, até chegar ao ponto em que a ficção imaginada por ela passa a superar a própria realidade de todos. O filme foi exibido na mostra competitiva do Festival de Cannes 2026. | Y11: Direção: Asghar Farhadi | Roteiro: Asghar Farhadi, Saeed Farhadi, Krzysztof Kieslowski | Produtora: Anonymous Content, Memento Production | Produção: Alexandre Mallet-Guy, Asghar Farhadi, David Levine | Fotografia: Guillaume Deffontaines | Montagem: Hayedeh Safiyari | Música: Zbigniew Preisner | Elenco: Isabelle Huppert, Virginie Efira, Vincent Cassel, Adam Bessa, Pierre Niney, India Hair, Catherine Deneuve | Z11: 4 | AA11: 2026 | AB11: Ficção
A12: 011 | B12: Panorama Mundial | C12: https://boxd.it/15fds | D12: Conversa com o Mar | E12: Hiwar ma’ albahr | F12: Catálogo | G12: Catar + 1 país | H12: Ficção | I12: 110 | J12: 2026 | K12: Catar, Palestina | L12: Ficção | P12: Muayad Alayan | Q12: Rami Alayan | R12: Palcine Productions | S12: Muayad Alayan, Rami Alayan | T12: Lorenzo Casadio Vannucci | U12: Matteo Faccenda | V12: Fabienne van Eck | W12: Kamel El Basha, Amer Hlehel , Bahira Ablassi, Maria Zreik, Ebla Mari, Rebecca Esmeralda Telhami | X12: Em Jerusalém, Kamal, um palestino de 60 anos, recebe uma ordem judicial israelense para pagar uma dívida previdenciária em nome do filho Wael, que teria morrido afogado no Mar Vermelho duas décadas antes. Quando descobre que não há registro oficial de sua morte, Kamal parte em busca da verdade sobre o destino do filho, confrontando uma ferida do passado que jamais cicatrizou. | Y12: Direção: Muayad Alayan | Roteiro: Rami Alayan | Produtora: Palcine Productions | Produção: Muayad Alayan, Rami Alayan | Fotografia: Lorenzo Casadio Vannucci | Montagem: Matteo Faccenda | Música: Fabienne van Eck | Elenco: Kamel El Basha, Amer Hlehel , Bahira Ablassi, Maria Zreik, Ebla Mari, Rebecca Esmeralda Telhami | Z12: 3 | AA12: 2026 | AB12: Ficção
A13: 012 | B13: Panorama Mundial | C13: https://boxd.it/TcSy | D13: Covarde | E13: Coward | F13: Catálogo | G13: Bélgica + 2 países | H13: Ficção | I13: 100 | J13: 2026 | K13: Bélgica, França, Países Baixos | L13: Ficção | M13: Sim | N13: Cannes | O13: Competição Oficial | P13: Lukas Dhont | Q13: Lucas Dhont, Angelo Tijssens | R13: The Reunion, Versus Productions, Lumen, Topkapi Films | S13: Michiel Dhont | T13: Frank van Den Eeden | U13: Alain Dessauvage | V13: Valentin Hadjadj | W13: Emannuel Macchia, Valentin Campagne, Jef Jacobs, Willen de Schryver, Liam Jacqmin, Mistral Guigot, Jonas Wertz | X13: Em 1916, em plena Primeira Guerra Mundial, o jovem soldado belga Pierre é enviado para o brutal fronte de batalha das trincheiras. Para tentar manter a sanidade, ele decide juntar-se a uma trupe de teatro improvisada nos bastidores da linha inimiga. Lá, Pierre conhece Francis, o líder criativo do grupo, e os dois acabam desenvolvendo uma intensa e secreta história de amor. Prêmio de Melhor Ator em Cannes 2026, dividido ex aequo entre os dois protagonistas, Emmanuel Macchia e Valentin Campagne. | Y13: Direção: Lukas Dhont | Roteiro: Lucas Dhont, Angelo Tijssens | Produtora: The Reunion, Versus Productions, Lumen, Topkapi Films | Produção: Michiel Dhont | Fotografia: Frank van Den Eeden | Montagem: Alain Dessauvage | Música: Valentin Hadjadj | Elenco: Emannuel Macchia, Valentin Campagne, Jef Jacobs, Willen de Schryver, Liam Jacqmin, Mistral Guigot, Jonas Wertz | Z13: 3 | AA13: 2026 | AB13: Ficção
A14: 013 | B14: Panorama Mundial | C14: https://boxd.it/13fZW | D14: Crianças Invisíveis | E14: Watashi no Shiranai Kodomotachi | F14: Catálogo | G14: Japão | H14: Ficção | I14: 150 | J14: 2026 | K14: Japão | L14: Ficção | P14: Miwa Nishikawa | Q14: Miwa Nishikawa | R14: K2 Pictures, Aoi Pro. | S14: Daiju Koide, Taichi Ito | T14: Norimichi Kasamatsu | U14: Tomomi Kikuchi | V14: Marihiko Hara | W14: Ami Koyae, Fumi Nikaido, Yutaka Takenouchi, Kaito Sakurai | X14: Nos dias finais da Segunda Guerra em Tóquio, uma órfã de 12 anos, filha de músicos, disfarça-se de menino para sobreviver ao submundo. Enquanto isso, sua antiga professora, tomada pela culpa e pela própria luta pela sobrevivência, refaz seus passos em uma busca desesperada. Um drama histórico tocante sobre as marcas invisíveis do conflito. Baseado em fatos reais, o filme abriu a mostra Platform no Festival de Toronto 2026. | Y14: Direção: Miwa Nishikawa | Roteiro: Miwa Nishikawa | Produtora: K2 Pictures, Aoi Pro. | Produção: Daiju Koide, Taichi Ito | Fotografia: Norimichi Kasamatsu | Montagem: Tomomi Kikuchi | Música: Marihiko Hara | Elenco: Ami Koyae, Fumi Nikaido, Yutaka Takenouchi, Kaito Sakurai | Z14: 3 | AA14: 2026 | AB14: Ficção
A15: 014 | B15: Panorama Mundial | C15: https://boxd.it/159U6 | D15: Dau | E15: Dau | F15: Complementar / catálogo parcial | G15: Alemanha + 2 países | H15: Ficção | I15: 217 | J15: 2026 | K15: Alemanha, França, Suécia | L15: Documentário | M15: Sim | N15: Veneza | O15: Venezia 83 – Competição | P15: Ilya Khrzhanovsky | Q15: Ilya Khrzhanovsky, Susanne Marian, Vladimir Sorokin, Ilia Permyakov | R15: Phenomen Berlin | S15: Ilya Khrzhanovsky, Svetlana Dragayeva, Philippe Bober, Solal Coutard, Susanne Marian, Erik Hemmendorff | T15: Jürgen Jürges, Manuel Alberto Claro, Lol Crawley | U15: Ilya Permyakov, Rob Myers | W15: Teodor Currentzis, Radmila Shchogolieva, Anatoly Vasiliev | X15: Na União Soviética, Dau é um físico brilhante movido pelo desejo de compreender as leis do universo. Recrutado para trabalhar em um instituto secreto, vê sua pesquisa colocada a serviço da criação da bomba atômica. Entre a vigilância do Estado, os privilégios da vida no instituto e uma sucessão de relações amorosas, suas convicções cedem aos poucos. Acompanhando quatro décadas de sua vida, o filme observa como escolhas íntimas e concessões cotidianas se entrelaçam à história de um regime. Projeto de uma década e prêmio de melhor Direção no Festival de Veneza de 2026. | Y15: Direção: Ilya Khrzhanovsky | Roteiro: Ilya Khrzhanovsky, Susanne Marian, Vladimir Sorokin, Ilia Permyakov | Produtora: Phenomen Berlin | Produção: Ilya Khrzhanovsky, Svetlana Dragayeva, Philippe Bober, Solal Coutard, Susanne Marian, Erik Hemmendorff | Fotografia: Jürgen Jürges, Manuel Alberto Claro, Lol Crawley | Montagem: Ilya Permyakov, Rob Myers | Elenco: Teodor Currentzis, Radmila Shchogolieva, Anatoly Vasiliev | Z15: 3 | AA15: 2026 | AB15: Documentário
A16: 015 | B16: Panorama Mundial | C16: https://boxd.it/TCSY | D16: Diários de Nagi | E16: Nagi daiarî | F16: Catálogo | G16: Japão + 3 países | H16: Ficção | I16: 110 | J16: 2026 | K16: Japão, França, Singapura, Filipinas | L16: Ficção | M16: Sim | N16: Cannes | O16: Competição Oficial | P16: Koji Fukada | Q16: Koji Fukada | R16: Survivance, Star Sands | S16: Atsuko Ohno, Ryo Nagai, Michiaki Tsunoda | T16: Hidetoshi Shinomiya | U16: Sylvie Lager | V16: Lee Pei-Chin | W16: Takako Matsu, Shizuka Ishibashi, Ken’ichi Matsuyama, Waku Kawaguchi, Kiyora Fujiwara, Sawako Fujima, Long Mizuma, Suhkye Shin | X16: Na pequena cidade rural de Nagi, Yoriko divide seus dias entre o trabalho no campo e a escultura, enquanto tenta conviver com as marcas de um amor do passado. Sua rotina é interrompida pela chegada de Yuri, sua amiga e ex-cunhada, uma arquiteta que deixa Tóquio após o fim do casamento. Yuri vai posar para uma escultura de Yoriko, e ao longo dos dias, nesse processo, elas se reaproximam e encontram, uma na outra, novas formas de lidar com a perda, a solidão e os caminhos que acabaram por não seguir na vida. Exibido na Competição Oficial do Festival de Cannes 2026. | Y16: Direção: Koji Fukada | Roteiro: Koji Fukada | Produtora: Survivance, Star Sands | Produção: Atsuko Ohno, Ryo Nagai, Michiaki Tsunoda | Fotografia: Hidetoshi Shinomiya | Montagem: Sylvie Lager | Música: Lee Pei-Chin | Elenco: Takako Matsu, Shizuka Ishibashi, Ken’ichi Matsuyama, Waku Kawaguchi, Kiyora Fujiwara, Sawako Fujima, Long Mizuma, Suhkye Shin | Z16: 3 | AA16: 2026 | AB16: Ficção
A17: 016 | B17: Panorama Mundial | C17: https://boxd.it/Og8k | D17: Eu Juro | E17: I Swear | F17: Catálogo | G17: Reino Unido | H17: Ficção | I17: 120 | J17: 2025 | K17: Reino Unido | L17: Ficção | P17: Kirk Jones | Q17: Kirk Jones | R17: Tempo Productions, One Story High | S17: Georgia Bayliff, Kirk Jones, Piers Tempest | T17: James Blann | U17: Sam Sneade | V17: Stephen Rennicks | W17: Robert Aramayo, Maxine Peake, Peter Mullan, Sanjeev Kohli, Shirley Henderson | X17: Escócia, anos 1980. Quando o adolescente John Davidson começa a manifestar tiques e explosões verbais involuntárias, pouco se sabia ainda sobre a síndrome de Tourette. Incompreendido pela família, pela escola e pela comunidade, ele enfrenta preconceito e isolamento. O apoio inesperado de pessoas dispostas a enxergá-lo para além de sua condição o ajuda a transformar a própria experiência em uma luta por reconhecimento. Inspirado em uma história real. | Y17: Direção: Kirk Jones | Roteiro: Kirk Jones | Produtora: Tempo Productions, One Story High | Produção: Georgia Bayliff, Kirk Jones, Piers Tempest | Fotografia: James Blann | Montagem: Sam Sneade | Música: Stephen Rennicks | Elenco: Robert Aramayo, Maxine Peake, Peter Mullan, Sanjeev Kohli, Shirley Henderson | Z17: 3 | AA17: 2025 | AB17: Ficção
A18: 017 | B18: Panorama Mundial | C18: https://boxd.it/DYn2 | D18: Euforia | E18: Euphoria | F18: Catálogo | G18: Alemanha + 3 países | H18: Documentário | I18: 91 | J18: 2026 | K18: Alemanha, Bulgária, Estados Unidos, Ucrânia | L18: Documentário | P18: Julian Rosefeldt | Q18: Julian Rosefeldt | R18: Park Avenue Armory New York | S18: Julian Rosefeldt | T18: Christoph Krauss | U18: Bobby Good | V18: Samy Moussa | W18: Giancarlo Esposito, Virginia Newcomb, Jeff Wood, Tim Williams, Eric Hansen, Jeff Burrell, Robert Bronzi, Kate Strong, Ayesha Jordan, Dora Zygouri, Esther Odumade, Tia Murrell, Asa Ali, Luis Rosefeldt, Rocio Rodriguez-Inniss | X18: Em uma Nova York distópica à beira do colapso, personagens e animais surreais conduzem uma viagem hipnótica pelo capitalismo e pela ganância humana. Realizado ao longo de seis anos, reunindo dois mil anos de ideias, de Platão e Karl Marx a bell hooks, Snoop Dogg e Cardi B, este filme visualmente arrebatador questiona por que um sistema econômico reconhecidamente destrutivo continua tão sedutor e aparentemente sem alternativa. Com Giancarlo Esposito e a voz de Cate Blanchett. | Y18: Direção: Julian Rosefeldt | Roteiro: Julian Rosefeldt | Produtora: Park Avenue Armory New York | Produção: Julian Rosefeldt | Fotografia: Christoph Krauss | Montagem: Bobby Good | Música: Samy Moussa | Elenco: Giancarlo Esposito, Virginia Newcomb, Jeff Wood, Tim Williams, Eric Hansen, Jeff Burrell, Robert Bronzi, Kate Strong, Ayesha Jordan, Dora Zygouri, Esther Odumade, Tia Murrell, Asa Ali, Luis Rosefeldt, Rocio Rodriguez-Inniss | Z18: 3 | AA18: 2026 | AB18: Documentário
A19: 018 | B19: Panorama Mundial | C19: https://boxd.it/Nyto | D19: Histórias de Família | E19: Etwas ganz Besonderes | F19: Catálogo | G19: Alemanha | H19: Ficção | I19: 116 | J19: 2026 | K19: Alemanha | L19: Ficção | P19: Eva Trobisch | Q19: Eva Trobisch | R19: Trimafilm | S19: Trini Götze, David Armati Lechner | T19: Adrian Campean | U19: Laura Lauzemis | V19: Teho Teardo | W19: Frida Hornemann, Max Riemelt, Eva Löbau, Rahel Ohm, Peter René Lüdicke, Gina Henkel | X19: Lea tem 16 anos, pais recém-divorciados e talento para cantar. Durante a seleção para participar de um reality show musical, a equipe pergunta quem ela é e o que a torna especial. Sem encontrar resposta, a adolescente passa a experimentar diferentes versões de si mesma e se aproxima da tia Kati, que retorna à cidade após anos no exterior. Nas florestas da antiga Alemanha Oriental, enquanto os avós tentam salvar o hotel da família da falência, três gerações confrontam suas histórias, tensões e desejos de partir. Exibido na competição oficial do Festival de Berlim 2026. | Y19: Direção: Eva Trobisch | Roteiro: Eva Trobisch | Produtora: Trimafilm | Produção: Trini Götze, David Armati Lechner | Fotografia: Adrian Campean | Montagem: Laura Lauzemis | Música: Teho Teardo | Elenco: Frida Hornemann, Max Riemelt, Eva Löbau, Rahel Ohm, Peter René Lüdicke, Gina Henkel | Z19: 3 | AA19: 2026 | AB19: Ficção
A20: 019 | B20: Panorama Mundial | C20: https://boxd.it/Jd66 | D20: Histórias Noturnas | E20: Histoires De La Nuit | F20: Catálogo | G20: França | H20: Ficção | I20: 114 | J20: 2026 | K20: França | L20: Ficção | P20: Léa Mysius | Q20: Léa Mysius | R20: Beside Productions, Division, F Comme Film, France 3 Cinéma | S20: Marie-Ange Luciani, Jean-Louis Livi | T20: Paul Guilhaume | U20: Yorgos Lamprinos | V20: Florencia di Concilio | W20: Hafsia Herzi, Benoît Magimel, Bastien Bouillon, Monica Bellucci, Tawba El Gharchi, Paul Hamy, Alane Delhaye, Servane Ducorps, Tatia Tsuladze, Jean-Paul Daniel, Dario Hardouin Spurio | X20: Nora, Thomas e a filha adolescente vivem isolados em uma fazenda no interior, tendo como única vizinha uma pintora italiana. Enquanto organizam uma festa surpresa de aniversário para Nora, a tranquilidade do lugar é quebrada. Três homens misteriosos surgem e invadem a comemoração, trazendo à tona segredos perigosos e bem guardados do passado. Um thriller rural claustrofóbico e tenso sobre uma noite de terror, invasão e revelações familiares violentas. | Y20: Direção: Léa Mysius | Roteiro: Léa Mysius | Produtora: Beside Productions, Division, F Comme Film, France 3 Cinéma | Produção: Marie-Ange Luciani, Jean-Louis Livi | Fotografia: Paul Guilhaume | Montagem: Yorgos Lamprinos | Música: Florencia di Concilio | Elenco: Hafsia Herzi, Benoît Magimel, Bastien Bouillon, Monica Bellucci, Tawba El Gharchi, Paul Hamy, Alane Delhaye, Servane Ducorps, Tatia Tsuladze, Jean-Paul Daniel, Dario Hardouin Spurio | Z20: 3 | AA20: 2026 | AB20: Ficção
A21: 020 | B21: Panorama Mundial | C21: https://boxd.it/N8by | D21: I want your sex | E21: want your sex, I | F21: Catálogo | G21: Estados Unidos | H21: Ficção | I21: 90 | J21: 2026 | K21: Estados Unidos | L21: Ficção | M21: Sim | N21: Sundance | O21: Premieres | P21: Gregg Araki | Q21: Karley Sciortino, Gregg Araki | R21: Desperate Pictures, Black Bear Pictures | S21: Gregg Araki, Seth Caplan, Teddy Schwarzman, Michael Heimler, Courtney L. Cunniff, , Karley Sciortino | T21: Tucker Korte | U21: Gregg Araki, Victor de la Parra | V21: James Clements | W21: Olivia Wilde, Cooper Hoffman, Mason Gooding, Chase Sui Wonders, Johnny Knoxville, Margaret Cho, Roxane Mesquida | X21: Quando o jovem Elliot consegue um emprego com Erika Tracy, artista célebre, provocadora e imprevisível, suas fantasias parecem se tornar realidade. Escolhido por ela como objeto de inspiração e parceiro sexual, ele é arrastado para uma relação marcada pelo desejo e por jogos de poder. Mas o que começa como uma aventura libertadora logo conduz Elliot a um universo de obsessão, traição e assassinato. Estreia mundial na seção Premieres do Festival de Sundance de 2026. | Y21: Direção: Gregg Araki | Roteiro: Karley Sciortino, Gregg Araki | Produtora: Desperate Pictures, Black Bear Pictures | Produção: Gregg Araki, Seth Caplan, Teddy Schwarzman, Michael Heimler, Courtney L. Cunniff, , Karley Sciortino | Fotografia: Tucker Korte | Montagem: Gregg Araki, Victor de la Parra | Música: James Clements | Elenco: Olivia Wilde, Cooper Hoffman, Mason Gooding, Chase Sui Wonders, Johnny Knoxville, Margaret Cho, Roxane Mesquida | Z21: 3 | AA21: 2026 | AB21: Ficção
A22: 021 | B22: Panorama Mundial | C22: https://boxd.it/X3MY | D22: Ink | F22: Complementar / catálogo parcial | G22: Reino Unido | H22: Ficção | I22: 116 | J22: 2026 | K22: Reino Unido | L22: Ficção | M22: Sim | N22: Veneza | O22: Venezia 83 – Competição | P22: Danny Boyle | Q22: James Graham | R22: Studiocanal, Media Res, House Productions | S22: Anna Marsh, Ron Halpern, Joe Naftalin, Tessa Ross, Michael Ellenberg | T22: Alwin Küchler, Bsc | U22: Fin Oates | V22: Daniel Pemberton | W22: Jack O’connell, Guy Pearce, Claire Foy, Blake Harrison, Patrick Kennedy, Brian Gleeson, Bertie Carvel, Christopher Fulford, Jonathan Hyde | X22: Londres, 1969. Rupert Murdoch compra o decadente jornal The Sun e entrega ao editor Larry Lamb uma missão aparentemente impossível: tirar do Daily Mirror o posto de jornal mais vendido do país. À frente de uma equipe disposta a romper convenções, Lamb reinventa a linguagem do jornal para conquistar o público. Em meio a manchetes provocadoras e uma disputa feroz por leitores, nasce um novo modelo de imprensa, cujos efeitos se fariam sentir muito além das bancas. Adaptação da peça de James Graham. Filme de abertura do Festival de Veneza 2026. | Y22: Direção: Danny Boyle | Roteiro: James Graham | Produtora: Studiocanal, Media Res, House Productions | Produção: Anna Marsh, Ron Halpern, Joe Naftalin, Tessa Ross, Michael Ellenberg | Fotografia: Alwin Küchler, Bsc | Montagem: Fin Oates | Música: Daniel Pemberton | Elenco: Jack O’connell, Guy Pearce, Claire Foy, Blake Harrison, Patrick Kennedy, Brian Gleeson, Bertie Carvel, Christopher Fulford, Jonathan Hyde | Z22: 3 | AA22: 2026 | AB22: Ficção
A23: 022 | B23: Panorama Mundial | C23: https://boxd.it/NzPA | D23: Josephine - Fragmentos de um Crime | E23: Josephine | F23: Catálogo | G23: Estados Unidos | H23: Ficção | I23: 119 | J23: 2026 | K23: Estados Unidos | L23: Ficção | M23: Sim | N23: Sundance; Berlinale | O23: U.S. Dramatic Competition; Competição Oficial | P23: Beth de Araújo | Q23: Beth de Araújo | R23: Kaplan Morrison, Yintai Entertainment, Free Association, Spark Features | S23: David Kaplan, Josh Peters, Beth de Araújo, Marina Stabile, Channing Tatum, Gemma Chan, Mark H. Rapaport, Josh Beirne-Golden, Crystine Zhang | T23: Greta Zozula | U23: Anisha Acharya | V23: Miles Ross | W23: Mason Reeves, Channing Tatum, Gemma Chan, Philip Ettinger, Syra Mccarthy, Nico Leunen, Kyle Reiter | X23: Aos oito anos, Josephine testemunha uma violência sexual no Golden Gate Park, em San Francisco. A experiência abala profundamente sua sensação de segurança e a mergulha no medo e na paranoia. Sem conseguir elaborar o trauma, ela passa a reagir com violência, numa tentativa de recuperar o controle. Seus pais procuram ajudá-la, mas também precisam lidar com os próprios temores e divergências. Inspirado em uma experiência da infância da diretora Beth de Araújo. Vencedor do Grande Prêmio do Júri e do Prêmio do Público em Sundance 2026. | Y23: Direção: Beth de Araújo | Roteiro: Beth de Araújo | Produtora: Kaplan Morrison, Yintai Entertainment, Free Association, Spark Features | Produção: David Kaplan, Josh Peters, Beth de Araújo, Marina Stabile, Channing Tatum, Gemma Chan, Mark H. Rapaport, Josh Beirne-Golden, Crystine Zhang | Fotografia: Greta Zozula | Montagem: Anisha Acharya | Música: Miles Ross | Elenco: Mason Reeves, Channing Tatum, Gemma Chan, Philip Ettinger, Syra Mccarthy, Nico Leunen, Kyle Reiter | Z23: 3 | AA23: 2026 | AB23: Ficção
A24: 023 | B24: Panorama Mundial | C24: https://boxd.it/UEAa | D24: Monstro Gentil | E24: Gentle Monster | F24: Catálogo | G24: Alemanha + 2 países | H24: Ficção | I24: 115 | J24: 2026 | K24: Alemanha, França, Áustria | L24: Ficção | M24: Sim | N24: Cannes | O24: Competição Oficial | P24: Marie Kreutzer | Q24: Marie Kreutzer | R24: Film Ag | S24: Alexander Glehr, Johanna Scherz | T24: Judith Kaufmann | U24: Ulrike Kofler | V24: Camille | W24: Léa Seydoux, Laurence Rupp, Jella Haase, Malo Blanchet, Anton Rubtsov, Nils Strunk, Catherine Deneuve | X24: A pianista Lucy muda-se para o campo com o marido, Philip, e o filho pequeno deles, deixando a carreira em segundo plano para ajudar o parceiro a se recuperar de um esgotamento. Mas uma visita súbita da polícia ao amanhecer de um dia comum revela um segredo devastador e desestrutura a família. Enquanto Lucy busca a verdade e tenta proteger o filho, a agente-investigadora Elsa enfrenta revelações perturbadoras em sua própria vida pessoal. Estreia mundial na competição do Festival de Cannes 2026. | Y24: Direção: Marie Kreutzer | Roteiro: Marie Kreutzer | Produtora: Film Ag | Produção: Alexander Glehr, Johanna Scherz | Fotografia: Judith Kaufmann | Montagem: Ulrike Kofler | Música: Camille | Elenco: Léa Seydoux, Laurence Rupp, Jella Haase, Malo Blanchet, Anton Rubtsov, Nils Strunk, Catherine Deneuve | Z24: 3 | AA24: 2026 | AB24: Ficção
A25: 024 | B25: Panorama Mundial | C25: https://boxd.it/Lc9s | D25: No Good Men | E25: Kabul Jan | F25: Catálogo | G25: Alemanha + 4 países | H25: Ficção | I25: 104 | J25: 2026 | K25: Alemanha, França, Noruega, Dinamarca, Afeganistão | L25: Ficção | P25: Shahrbanoo Sadat | Q25: Shahrbanoo Sadat | R25: Amerikafilm, Wolf Pictures, Motlys, La Fabrica Nocturna Cinéma, Adomeit Film (Dk), Adomeit Film (D) | S25: Katja Adomeit, Shahrbanoo Sadat, Jeep Wowk, Marina Perales Marhuenda, Xavier Rocher, Ingvil Sæther Berger, Balthasar Busmann, Maxi Haslberger | T25: Virginie Surdej | U25: Alexandra Strauss | V25: Harpheet Bansal, Therese Aune, Kristian Eidnes Andersen | W25: Shahrbanoo Sadat, Anwar Hashimi, Liam Hussaini, Yasin Negah, Ahmad Azizi, Fatima Hassani, Masihullah Tajzai | X25: Afeganistão, 2021, pouco antes do retorno do Talibã ao poder. Naru, a única cinegrafista da principal emissora de TV de Cabul, luta para manter a guarda do filho de três anos. Após deixar o marido infiel, ela se convence de que não existem homens bons no país. Naru é pega de surpresa quando Qodrat, o jornalista mais importante da TV, lhe oferece uma oportunidade de carreira. Ao cobrirem os últimos dias de liberdade da cidade, surge uma faísca entre eles. Exibido na Berlinale Special Gala 2026. | Y25: Direção: Shahrbanoo Sadat | Roteiro: Shahrbanoo Sadat | Produtora: Amerikafilm, Wolf Pictures, Motlys, La Fabrica Nocturna Cinéma, Adomeit Film (Dk), Adomeit Film (D) | Produção: Katja Adomeit, Shahrbanoo Sadat, Jeep Wowk, Marina Perales Marhuenda, Xavier Rocher, Ingvil Sæther Berger, Balthasar Busmann, Maxi Haslberger | Fotografia: Virginie Surdej | Montagem: Alexandra Strauss | Música: Harpheet Bansal, Therese Aune, Kristian Eidnes Andersen | Elenco: Shahrbanoo Sadat, Anwar Hashimi, Liam Hussaini, Yasin Negah, Ahmad Azizi, Fatima Hassani, Masihullah Tajzai | Z25: 5 | AA25: 2026 | AB25: Ficção
A26: 025 | B26: Panorama Mundial | C26: https://boxd.it/XZ0I | D26: Nós Somos os Frutos da Floresta | E26: Nous sommes les fruits de la forêt | F26: Catálogo | G26: Camboja + 1 país | H26: Documentário | I26: 87 | J26: 2025 | K26: Camboja, França | L26: Documentário | P26: Rithy Panh | Q26: Rithy Panh | R26: Catherine Dussart Productions (Cdp) | S26: Catherine Dussart, Quentin François | T26: Prum Mésar, Mourng Vet, Cheng Socheat, Sok Chan Rado, Rithy Panh | U26: Rithy Panh, Eang Pisith | V26: Marc Mader | W26: Pa Kreb, Mak Kreb, Mak Lisa, Pouk Choeut, Mak Choeut, Yeay Kreb, Pouk Pritch, Mak Pritch, Pouk Vath, Pouk Loun, Lisa Choeut, Noas Pritch Kreb | X26: Filmado ao longo de quatro anos o documentário foca em algumas famílias da minoria étnica Bunong, que vive nas montanhas do nordeste do Camboja. Eles sobrevivem graças à terra e a práticas ancestrais, guiando-se pelos ciclos da floresta, que estão sendo severamente afetados por alterações nas estações do ano. Vencedor do Prêmio Especial do Júri no Festival Internacional de Cinema de Tóquio 2025. | Y26: Direção: Rithy Panh | Roteiro: Rithy Panh | Produtora: Catherine Dussart Productions (Cdp) | Produção: Catherine Dussart, Quentin François | Fotografia: Prum Mésar, Mourng Vet, Cheng Socheat, Sok Chan Rado, Rithy Panh | Montagem: Rithy Panh, Eang Pisith | Música: Marc Mader | Elenco: Pa Kreb, Mak Kreb, Mak Lisa, Pouk Choeut, Mak Choeut, Yeay Kreb, Pouk Pritch, Mak Pritch, Pouk Vath, Pouk Loun, Lisa Choeut, Noas Pritch Kreb | Z26: 3 | AA26: 2025 | AB26: Documentário
A27: 026 | B27: Panorama Mundial | C27: https://boxd.it/V6FC | D27: O Cheiro das Maçãs | E27: Reuk van Appels, Die | F27: Catálogo | G27: África do Sul + 2 países | H27: Ficção | I27: 104 | J27: 2026 | K27: Chile, Países Baixos, África do Sul | L27: Ficção | P27: John Trengove | Q27: John Trengove, Chris Ciancimino | R27: Portobello Productions, Cadence, Baldr Film, Quijote Films | S27: Eric Abraham, Jack Sidey, Cait Pansegrouw, Frank Hoeve | T27: Lennert Hillege, Nsc | U27: Matthew Swanepoel | W27: Dawian van Der Westhuizen, Hilton Pelser, Maude Sandham, Celeste Matthews Wan- Nenburgh, Alejandro Goic | X27: Na África do Sul de 1974, em pleno apartheid, Marnus, de 11 anos, leva uma vida protegida no universo privilegiado de sua família branca. Durante as férias de verão, uma acusação aparentemente banal desencadeia acontecimentos que abalam a imagem idealizada de seu pai e expõem a violência sob a fachada de normalidade. Adaptado do romance de Mark Behr, o drama acompanha o despertar doloroso de um menino para as contradições do mundo que o formou. Estreia mundial na competição Platform do Festival de Toronto 2026. | Y27: Direção: John Trengove | Roteiro: John Trengove, Chris Ciancimino | Produtora: Portobello Productions, Cadence, Baldr Film, Quijote Films | Produção: Eric Abraham, Jack Sidey, Cait Pansegrouw, Frank Hoeve | Fotografia: Lennert Hillege, Nsc | Montagem: Matthew Swanepoel | Elenco: Dawian van Der Westhuizen, Hilton Pelser, Maude Sandham, Celeste Matthews Wan- Nenburgh, Alejandro Goic | Z27: 3 | AA27: 2026 | AB27: Ficção
A28: 027 | B28: Panorama Mundial | C28: https://boxd.it/UlXY | D28: O Objeto do Delito | E28: L’objet du délit | F28: Catálogo | G28: França + 1 país | H28: Ficção | I28: 134 | J28: 2026 | K28: Bélgica, França | L28: Ficção | P28: Agnès Jaoui | Q28: Agnès Jaqui, Emmanuel Salinger, Laurent Jaqui, Noé Debré, Florence Seyvos | R28: Les Films du Kiosque | S28: François Kraus, Denis Pineau-Valencienne | T28: David Chizallet | U28: Christel Dewynter | V28: Fernando Fiszbein | W28: Eye Haidara, Claire Chust, Oussama Kheddam, Lucie Gallo, Tiphaine Daviot, Maxime Pambet, Loie Legendre, Vicenzo Amato | X28: Nos bastidores de uma ambiciosa produção da ópera As Bodas de Fígaro, as tensões aumentam quando surge uma acusação de agressão sexual, colocando em risco a produção e forçando todos a tomarem uma posição. | Y28: Direção: Agnès Jaoui | Roteiro: Agnès Jaqui, Emmanuel Salinger, Laurent Jaqui, Noé Debré, Florence Seyvos | Produtora: Les Films du Kiosque | Produção: François Kraus, Denis Pineau-Valencienne | Fotografia: David Chizallet | Montagem: Christel Dewynter | Música: Fernando Fiszbein | Elenco: Eye Haidara, Claire Chust, Oussama Kheddam, Lucie Gallo, Tiphaine Daviot, Maxime Pambet, Loie Legendre, Vicenzo Amato | Z28: 3 | AA28: 2026 | AB28: Ficção
A29: 028 | B29: Panorama Mundial | C29: https://boxd.it/AWo2 | D29: O Rebelde | E29: Uprising, The | F29: Catálogo | G29: Reino Unido + 2 países | H29: Ficção | I29: 127 | J29: 2026 | K29: Alemanha, Reino Unido, Estados Unidos | L29: Ficção | P29: Paul Greengrass | Q29: Paul Greengrass | R29: Electric Shadow Company, Blumhouse Productions, Atomic Monster, Thank You Pictures, Supernix, Filmnation Entertainment | S29: Jason Blum, Gregory Goodman, Paul Greengrass, Joanna Kaye, Joe Neurauter, Lars Sylvest | T29: Pål Ulvik Rokseth | U29: William Goldenberg | V29: Volker Bertelmann | W29: Andrew Garfield, Woody Norman, Katherine Waterson, Mark Redhead, Tom Hollander, Stephen Dillane, Stanley Townsend, Dónal Finn | X29: Inglaterra, 1381. Após a Peste Negra, a população enfrenta a fome, os impostos abusivos e a violência da Coroa. Devastado por uma perda pessoal, um humilde camponês se une à revolta contra o rei Ricardo II e acaba se tornando um de seus líderes. À frente de um exército popular, ele parte rumo a Londres em uma luta por justiça e sobrevivência que acabaria por inspirar a lenda de Robin Hood. | Y29: Direção: Paul Greengrass | Roteiro: Paul Greengrass | Produtora: Electric Shadow Company, Blumhouse Productions, Atomic Monster, Thank You Pictures, Supernix, Filmnation Entertainment | Produção: Jason Blum, Gregory Goodman, Paul Greengrass, Joanna Kaye, Joe Neurauter, Lars Sylvest | Fotografia: Pål Ulvik Rokseth | Montagem: William Goldenberg | Música: Volker Bertelmann | Elenco: Andrew Garfield, Woody Norman, Katherine Waterson, Mark Redhead, Tom Hollander, Stephen Dillane, Stanley Townsend, Dónal Finn | Z29: 3 | AA29: 2026 | AB29: Ficção
A30: 029 | B30: Panorama Mundial | C30: https://letterboxd.com/film/the-assassins-2026/ | D30: O(s) Assassino(s) | E30: Assassins, The | F30: Catálogo | G30: Coreia do Sul | H30: Ficção | I30: 131 | J30: 2026 | K30: Coreia do Sul | L30: Ficção | P30: Hur Jin-Ho | Q30: Gwon Gi-Jun, Lee Ji-Min | R30: Hive Media Corp. | S30: Kim Won-Kuk | T30: Lee Mo-Gae | U30: Kim Hana, Kim Woo-Hyun | V30: Cho Young-Wuk | W30: Yoo Hai-Jin, Park Hae-Il, Lee Min-Ho | X30: Coreia do Sul, 15 de agosto de 1974. Durante uma cerimônia transmitida ao vivo, tiros são disparados contra o presidente Park Chung-hee. Ele sobrevive, mas a primeira-dama Yuk Young-soo e uma menina são mortas. Quando duas balas desaparecem dos registros oficiais, um inspetor que testemunhou o atentado, um editor de jornal veterano e um repórter iniciante conduzem investigações paralelas. Entre censura, ameaças e interesses ocultos, os três desafiam uma engrenagem determinada a enterrar a verdade. Estreia mundial no Festival de Toronto 2026. | Y30: Direção: Hur Jin-Ho | Roteiro: Gwon Gi-Jun, Lee Ji-Min | Produtora: Hive Media Corp. | Produção: Kim Won-Kuk | Fotografia: Lee Mo-Gae | Montagem: Kim Hana, Kim Woo-Hyun | Música: Cho Young-Wuk | Elenco: Yoo Hai-Jin, Park Hae-Il, Lee Min-Ho | Z30: 3 | AA30: 2026 | AB30: Ficção
A31: 030 | B31: Panorama Mundial | C31: https://letterboxd.com/film/the-last-resort-2026/ | D31: O Último Resort | E31: Paradis | F31: Catálogo | G31: Dinamarca + 1 país | H31: Ficção | I31: 98 | J31: 2026 | K31: Dinamarca, Noruega | L31: Ficção | P31: Maria Sødahl | Q31: Maria Sødahl, Therese Hasman, Eske Troelstrup | R31: Nordisk Film Production | S31: Thomas Robsahm, Sigurd Mikal Karoliussen | T31: John-Erling Holmenes Fredriksen | U31: Kristofer Nordin | V31: Martin Juel Dirkov | W31: Danica Curcic, Esben Smed, Aziz Çapkurt, Sif Lucca Gersby, Chili Olivia Jensen, Claes Ljungmark, Per Kjerstad, Marte Engebrigtsen, Petrine Agger, Nanna Finding Koppel | X31: Mikkel e Louise viajam com as duas filhas para férias num resort com tudo incluído em Gran Canaria. O descanso termina quando atropelam acidentalmente um homem que, mais tarde, aparece no hotel pedindo ajuda. Convencido de que deve fazer o que é certo, o casal aceita o pedido. Mas, à medida que se envolve, seus valores são postos à prova, e a família precisa confrontar o que significa ser uma boa pessoa — e quanto está disposta a arriscar por alguém em necessidade. Vencedor do Dragon Award de melhor filme nórdico no Festival de Gotemburgo 2026. | Y31: Direção: Maria Sødahl | Roteiro: Maria Sødahl, Therese Hasman, Eske Troelstrup | Produtora: Nordisk Film Production | Produção: Thomas Robsahm, Sigurd Mikal Karoliussen | Fotografia: John-Erling Holmenes Fredriksen | Montagem: Kristofer Nordin | Música: Martin Juel Dirkov | Elenco: Danica Curcic, Esben Smed, Aziz Çapkurt, Sif Lucca Gersby, Chili Olivia Jensen, Claes Ljungmark, Per Kjerstad, Marte Engebrigtsen, Petrine Agger, Nanna Finding Koppel | Z31: 3 | AA31: 2026 | AB31: Ficção
A32: 031 | B32: Panorama Mundial | C32: https://letterboxd.com/film/eight-bridges/ | D32: Oito Pontes | E32: Eight Bridges | F32: Catálogo | G32: Estados Unidos | H32: Ficção | I32: 82 | J32: 2026 | K32: Estados Unidos | L32: Ficção | P32: James Benning | X32: Em oito planos fixos de dez minutos, James Benning contempla pontes dos Estados Unidos, indo da Golden Gate, em São Francisco, à histórica Edmund Pettus, em Selma. No encontro entre terra, água e céu, essas estruturas conectam os mundos construído e natural, conduzindo fluxos de pessoas, capital e história. Sem diálogos, este ensaio visual meditativo transforma a observação paciente em uma reflexão sobre os Estados Unidos, a percepção e o tempo. Estreia mundial no Fórum do Festival de Berlim 2026. | Y32: Direção: James Benning | Z32: 3 | AA32: 2026 | AB32: Ficção
A33: 032 | B33: Panorama Mundial | C33: https://letterboxd.com/film/growth-of-the-soil-2026/ | D33: Os Frutos da Terra | E33: Markens grøde | F33: Catálogo | G33: Noruega | H33: Ficção | I33: 155 | J33: 2026 | K33: Noruega | L33: Ficção | P33: Hans Petter Moland | Q33: Hans Petter Moland, Gard B. Eidsvold | R33: Scanbox Entertainment, 4 1/2 Fiction as | S33: Håkon Øverås | T33: Oskar Dahlsbakken | U33: Linda Man | V33: Kaspar Kaae | W33: Herbert Nordrum, Asta Kamma August, Gard B Eidsvold, Anders Baasmo | X33: Umm homem e uma mulher enfrentam a imensidão da natureza, abrindo caminhos nos arredores isolados do norte da Noruega. Guiados pelas necessidades elementares da vida, suas habilidades e resistência são postas à prova à medida que grandes desafios se aproximam. Baseado no romance que deu o Prêmio Nobel de Literatura a Knut Hamsun, este drama retrata com fidelidade a força da terra e os limites da sobrevivência. Exibido no Toronto International Film Festival 2026 na mostra Special Presentations. | Y33: Direção: Hans Petter Moland | Roteiro: Hans Petter Moland, Gard B. Eidsvold | Produtora: Scanbox Entertainment, 4 1/2 Fiction as | Produção: Håkon Øverås | Fotografia: Oskar Dahlsbakken | Montagem: Linda Man | Música: Kaspar Kaae | Elenco: Herbert Nordrum, Asta Kamma August, Gard B Eidsvold, Anders Baasmo | Z33: 3 | AA33: 2026 | AB33: Ficção
A34: 033 | B34: Panorama Mundial | C34: https://letterboxd.com/film/prima-facie-2026/ | D34: Prima Facie | F34: Complementar / catálogo parcial | G34: Austrália + 1 país | H34: Ficção | I34: 106 | J34: 2026 | K34: Austrália, Reino Unido | L34: Ficção | P34: Susanna White | Q34: Suzie Miller | R34: Camelback Productions, Minderoo Pictures, Edith's Daughter, Embankment Films, Bunya Productions | S34: Greer Simpkin, Kevin Loader, David Jowsey | T34: Mike Eley | U34: Justine Wright | V34: Isobel Waller-Bridge | W34: Cynthia Erivo, Daniel Ings, Noma Dumezweni, Elizabeth Dulau, Toheeb Jimoh, Harry Treadaway, Khalid Abdalla, Elliot Levey, Simon Russell-Beale, Sarah Junillon | X34: A indicada ao Oscar Cynthia Erivo (Wicked) estrela esta adaptação da peça de Suzie Miller. A trama examina o que acontece quando uma advogada ambiciosa, que defende principalmente acusados de crimes sexuais, inesperadamente se torna a denunciante em um caso de agressão sexual. Forçada a ir ao banco das testemunhas, ela deve enfrentar o mesmo sistema jurídico em que confiava, confrontando as duras realidades da justiça e do poder pelo outro lado. | Y34: Direção: Susanna White | Roteiro: Suzie Miller | Produtora: Camelback Productions, Minderoo Pictures, Edith's Daughter, Embankment Films, Bunya Productions | Produção: Greer Simpkin, Kevin Loader, David Jowsey | Fotografia: Mike Eley | Montagem: Justine Wright | Música: Isobel Waller-Bridge | Elenco: Cynthia Erivo, Daniel Ings, Noma Dumezweni, Elizabeth Dulau, Toheeb Jimoh, Harry Treadaway, Khalid Abdalla, Elliot Levey, Simon Russell-Beale, Sarah Junillon | Z34: 3 | AA34: 2026 | AB34: Ficção
A35: 034 | B35: Panorama Mundial | C35: https://letterboxd.com/film/four-minus-three/ | D35: Quatro Menos Três | E35: Vier Minus Drei | F35: Catálogo | G35: Áustria + 1 país | H35: Ficção | I35: 121 | J35: 2025 | K35: Áustria, Alemanha | L35: Ficção | P35: Adrian Goiginger | Q35: Senad Halilbašić | R35: Giganten Film Produktions Gmbh, 2010 Entertainment Gmbh | S35: Peter Wildling, Gerrit Klein, Martin Pfeil, David Stöllinger, Adrian Goiginger | T35: Paul Sprinz | U35: Martin Pfeil, Simon Blasi | V35: Arash Safaian | W35: Valerie Pachner, Robert Stadlober, Stefanie Reinsperger, Hanno Koffler, Margarethe Tiesel, Paul Wolff-Plottegg, Michael Gampe, Ronald Zehrfeld, Michael Fuith, Wolfgang Lampl, Sophia Laggner, Petra Morzé | X35: Barbara, uma animadora profissional, vê seu mundo desmoronar após uma perda familiar devastadora. Como única sobrevivente de uma tragédia, ela enfrenta o doloroso processo de luto e isolamento. Este drama sensível explora as profundezas da dor humana e o difícil desafio de reconstruir a vida do zero. Baseado em uma emocionante história real, o filme foca na busca por um novo sentido e na resiliência necessária para reencontrar a esperança quando tudo parece perdido. Exibido na Mostra Panorama do Festival de Berlim 2026. | Y35: Direção: Adrian Goiginger | Roteiro: Senad Halilbašić | Produtora: Giganten Film Produktions Gmbh, 2010 Entertainment Gmbh | Produção: Peter Wildling, Gerrit Klein, Martin Pfeil, David Stöllinger, Adrian Goiginger | Fotografia: Paul Sprinz | Montagem: Martin Pfeil, Simon Blasi | Música: Arash Safaian | Elenco: Valerie Pachner, Robert Stadlober, Stefanie Reinsperger, Hanno Koffler, Margarethe Tiesel, Paul Wolff-Plottegg, Michael Gampe, Ronald Zehrfeld, Michael Fuith, Wolfgang Lampl, Sophia Laggner, Petra Morzé | Z35: 3 | AA35: 2025 | AB35: Ficção
A36: 035 | B36: Panorama Mundial | C36: https://letterboxd.com/film/queen-at-sea/ | D36: Rainha ao Mar | E36: Queen At Sea | F36: Catálogo | G36: Estados Unidos + 1 país | H36: Ficção | I36: 121 | J36: 2026 | K36: Estados Unidos, Reino Unido | L36: Ficção | M36: Sim | N36: Berlinale | O36: Competição Oficial | P36: Lance Hammer | Q36: Lance Hammer | R36: Alluvial Film Company, The Bureau | S36: Tristan Goligher, Lance Hammer | T36: Adolpho Veloso | U36: Lance Hammer | V36: Georgiamae Bromley, Connie Farr | W36: Juliette Binoche, Tom Courtenay, Anna Calder-Marshall, Florence Hunt | X36: À medida que a demência avançada compromete a capacidade de Leslie expressar seus desejos, sua filha Amanda e seu marido, Martin, entram em conflito sobre quem deve decidir o que é melhor para ela. As tentativas de equilibrar amor, proteção e autonomia levam a escolhas cada vez mais difíceis, com consequências que escapam ao controle de todos. Vencedor do Prêmio do Júri e de Melhor Atriz Coadjuvante para Anna Calder-Marshall no Festival de Berlim 2026. | Y36: Direção: Lance Hammer | Roteiro: Lance Hammer | Produtora: Alluvial Film Company, The Bureau | Produção: Tristan Goligher, Lance Hammer | Fotografia: Adolpho Veloso | Montagem: Lance Hammer | Música: Georgiamae Bromley, Connie Farr | Elenco: Juliette Binoche, Tom Courtenay, Anna Calder-Marshall, Florence Hunt | Z36: 3 | AA36: 2026 | AB36: Ficção
A37: 036 | B37: Panorama Mundial | C37: https://letterboxd.com/film/rose-2026/ | D37: Rose | F37: Complementar / catálogo parcial | G37: Áustria + 1 país | H37: Ficção | I37: 93 | J37: 2026 | K37: Áustria, Alemanha | L37: Ficção | M37: Sim | N37: Berlinale | O37: Competição Oficial | P37: Markus Schleinzer | Q37: Markus Schleinzer, Alexander Born | S37: Johannes Schubert, Philipp Worm, Tobias Walker, Karsten Stöter | T37: Gerald Kerkletz | U37: Hansjörg Weissbrich | V37: Tara Nome Doyle | W37: Sandra Hüller, Caro Braun, Marissa Growaldt, Robert Gwisdek, Godehard Giese | X37: No início do século XVII, em meio à devastação da Guerra dos Trinta Anos, um misterioso soldado chega a um isolado vilarejo protestante na Alemanha, afirmando ser o herdeiro de uma propriedade abandonada. Embora aos poucos vá conquistando a confiança dos moradores, as suspeitas sobre sua identidade nunca deixam de existir, e ameaçam destruir a vida construída sobre uma farsa impossível. Estreia mundial na competição do Festival de Berlim 2026, em que Sandra Hüller recebeu o Urso de Prata de Melhor Atriz. | Y37: Direção: Markus Schleinzer | Roteiro: Markus Schleinzer, Alexander Born | Produção: Johannes Schubert, Philipp Worm, Tobias Walker, Karsten Stöter | Fotografia: Gerald Kerkletz | Montagem: Hansjörg Weissbrich | Música: Tara Nome Doyle | Elenco: Sandra Hüller, Caro Braun, Marissa Growaldt, Robert Gwisdek, Godehard Giese | Z37: 4 | AA37: 2026 | AB37: Ficção
A38: 037 | B38: Panorama Mundial | C38: https://letterboxd.com/film/rosebush-pruning/ | D38: Rosebush Pruning | F38: Complementar / catálogo parcial | G38: Itália + 3 países | H38: Ficção | I38: 97 | J38: 2026 | K38: Itália, Alemanha, Espanha, Reino Unido | L38: Ficção | P38: Karim Aïnouz | Q38: Efthimis Filippou | R38: The Match Factory, Kavac Film, The Apartment (a Freemantle Company), Sur Film, Rosebushpruning, Crybaby | S38: Viola Fügen, Michael Weber | T38: Hélène Louvart | U38: Heike Parpi, David Jancso, Ilka Janka Nagy | V38: Matthew Herbert | W38: Callun Turner, Elena Anaya, Elle Fanning, Jamie Bell, Lukas Gage, Pamela Anderson, Riley Keough, Tracy Letts | X38: Sob o sol da Catalunha, quatro irmãos norte-americanos vivem com o pai cego em uma mansão, entregues ao isolamento, à fortuna herdada, às roupas de grife e a uma relação de dependência mútua. Quando Jack, o irmão mais velho e pilar da família, anuncia que vai morar com a namorada Martha, o frágil equilíbrio começa a ruir. À medida que Ed investiga a verdade sobre a morte da mãe, antigos segredos e mentiras vêm à tona, desintegrando os laços familiares. Estreia mundial na Competição Oficial do Festival de Berlim 2026. | Y38: Direção: Karim Aïnouz | Roteiro: Efthimis Filippou | Produtora: The Match Factory, Kavac Film, The Apartment (a Freemantle Company), Sur Film, Rosebushpruning, Crybaby | Produção: Viola Fügen, Michael Weber | Fotografia: Hélène Louvart | Montagem: Heike Parpi, David Jancso, Ilka Janka Nagy | Música: Matthew Herbert | Elenco: Callun Turner, Elena Anaya, Elle Fanning, Jamie Bell, Lukas Gage, Pamela Anderson, Riley Keough, Tracy Letts | Z38: 4 | AA38: 2026 | AB38: Ficção
A39: 038 | B39: Panorama Mundial | C39: https://letterboxd.com/film/no-pain-2026/ | D39: Sem Dor | E39: Nessun dolore | F39: Catálogo | G39: Itália | H39: Ficção | I39: 96 | J39: 2026 | K39: Itália | L39: Ficção | M39: Sim | N39: Veneza | O39: Venice Open – Fora de Competição | P39: Gianni Amelio | Q39: Gianni Amelio, Davide Serino, Andrea Quetti | R39: Kavac Film, Our Films, Be Water Film | S39: Simone Gattoni, Marco Bellocchio, Lorenzo Mieli, Mario Gianani, Mattia Guerra | T39: Luan Amelio Ujkaj | U39: Stefano Mariotti | V39: Fabio Massimo Capogrosso | W39: Alessandro Borghi, Valeria Golino, Valerio Mastandrea, Beidja Yahiaoui, Ramzi Lafrindi, Gabriel Bovino | X39: Davide, um livreiro de trinta e poucos anos, vende livros usados numa praça de Roma e leva uma vida solitária, tendo como principal companhia Elsa, professora de literatura com quem mantém uma relação de amizade e afeto. Tudo muda quando um desconhecido deixa sob seus cuidados um menino norte-africano. Após um acidente que o enche de culpa, Davide acolhe Aminah, uma adolescente argelina grávida e sem ter para onde ir. Aos poucos, sua casa se transforma em abrigo para migrantes. Exibido fora de competição no Festival de Veneza 2026. | Y39: Direção: Gianni Amelio | Roteiro: Gianni Amelio, Davide Serino, Andrea Quetti | Produtora: Kavac Film, Our Films, Be Water Film | Produção: Simone Gattoni, Marco Bellocchio, Lorenzo Mieli, Mario Gianani, Mattia Guerra | Fotografia: Luan Amelio Ujkaj | Montagem: Stefano Mariotti | Música: Fabio Massimo Capogrosso | Elenco: Alessandro Borghi, Valeria Golino, Valerio Mastandrea, Beidja Yahiaoui, Ramzi Lafrindi, Gabriel Bovino | Z39: 3 | AA39: 2026 | AB39: Ficção
A40: 039 | B40: Panorama Mundial | C40: https://letterboxd.com/film/well-find-happiness/ | D40: Seremos Felizes | E40: On Seura Heureux | F40: Catálogo | G40: Canadá + 1 país | H40: Ficção | I40: 101 | J40: 2025 | K40: Canadá, Luxemburgo | L40: Ficção | P40: Lea Pool | Q40: Michel Marc Bouchard | S40: Lyse Lafontaine, Katarzyna Ozg | T40: Yves Bélanger | U40: Michel Arcand | V40: Kyan Bayani | W40: Mehdi Meskar, Alexandre Landry, Aron Archer, Céline Bonnier, Sascha Ley | X40: Saad, um refugiado marroquino, vive no Canadá com Reza, seu companheiro iraniano. Quando Reza enfrenta a ameaça de deportação para um país onde sua vida corre perigo, o casal inicia uma corrida contra o tempo. Diante do rigoroso sistema de imigração, Saad arrisca tudo em um plano desesperado para salvar o homem que ama, testando os limites do afeto e da sobrevivência. | Y40: Direção: Lea Pool | Roteiro: Michel Marc Bouchard | Produção: Lyse Lafontaine, Katarzyna Ozg | Fotografia: Yves Bélanger | Montagem: Michel Arcand | Música: Kyan Bayani | Elenco: Mehdi Meskar, Alexandre Landry, Aron Archer, Céline Bonnier, Sascha Ley | Z40: 4 | AA40: 2025 | AB40: Ficção
A41: 040 | B41: Panorama Mundial | C41: https://letterboxd.com/film/sheep-in-the-box/ | D41: Sheep in the Box | E41: Hako no Naka no Hitsuji | F41: Catálogo | G41: Japão | H41: Ficção | I41: 126 | J41: 2026 | K41: Japão | L41: Ficção | M41: Sim | N41: Cannes | O41: Competição Oficial | P41: Hirokazu Kore-Eda | Q41: Hirokazu Kore-Eda | R41: Fuji Television Network | S41: Kaoru Matsuzaki, Megumi Banse | T41: Ryuto Kondo | W41: Haruka Ayase, Daigo, Kuwaki Rimu | X41: Em um futuro próximo, o casal Otone e Kensuke tenta superar a dor devastadora de perder o filho pequeno. Diante do luto, eles decidem acolher em sua casa um robô humanoide de última geração projetado com a mesma aparência e voz do filho falecido. Enquanto a mãe aceita a réplica para tentar restaurar sua rotina, o pai reluta em acolher a máquina. A dinâmica familiar se complica quando o androide começa a escapar secretamente para se conectar com outros de sua espécie. Exibido na mostra competitiva do Festival de Cannes 2026. | Y41: Direção: Hirokazu Kore-Eda | Roteiro: Hirokazu Kore-Eda | Produtora: Fuji Television Network | Produção: Kaoru Matsuzaki, Megumi Banse | Fotografia: Ryuto Kondo | Elenco: Haruka Ayase, Daigo, Kuwaki Rimu | Z41: 3 | AA41: 2026 | AB41: Ficção
A42: 041 | B42: Panorama Mundial | C42: https://letterboxd.com/film/seuls-les-rebelles/ | D42: Só os Rebeldes Vencem | E42: Seuls les rebelles | F42: Catálogo | G42: França + 2 países | H42: Ficção | I42: 98 | J42: 2026 | K42: França, Líbano, Catar | L42: Ficção | P42: Danielle Arbid | Q42: Danielle Arbid | R42: Easy Riders Films, Abbout Productions, Sunnyland Film | S42: Nadia Turincev, Georges Schoucair, Omar El Kadi | T42: Céline Bozon | U42: Clément Pinteaux | V42: Bachar Mar-Khalifé | W42: Hiam Abbass, Amine Benrachid, Shaden Fakih, Alexandre Paulikevitch, Cynthia El Khazen | X42: Beirute. Suzanne conhece Osmane após salvá-lo de um ataque racista. Ele é um jovem sudanês sem documentos; ela, uma viúva de classe média com o dobro de sua idade. Contra as expectativas, os dois se apaixonam. Em um Líbano à beira do colapso, o romance gera indignação: os filhos se afastam, vizinhos chamam a polícia e padres recusam o casamento. Diante da hostilidade de uma sociedade fraturada, eles resistem. Exibido na mostra Panorama do Festival de Berlim 2026. | Y42: Direção: Danielle Arbid | Roteiro: Danielle Arbid | Produtora: Easy Riders Films, Abbout Productions, Sunnyland Film | Produção: Nadia Turincev, Georges Schoucair, Omar El Kadi | Fotografia: Céline Bozon | Montagem: Clément Pinteaux | Música: Bachar Mar-Khalifé | Elenco: Hiam Abbass, Amine Benrachid, Shaden Fakih, Alexandre Paulikevitch, Cynthia El Khazen | Z42: 3 | AA42: 2026 | AB42: Ficção
A43: 042 | B43: Panorama Mundial | C43: https://letterboxd.com/film/we-are-all-strangers/ | D43: Somos Todos Estranhos | E43: Wo Men Bu Shi Mo Sheng Ren | F43: Catálogo | G43: Singapura | H43: Ficção | I43: 157 | J43: 2026 | K43: Singapura | L43: 2026, Singapura | M43: Sim | N43: Berlinale | O43: Competição Oficial | P43: Anthony Chen | Q43: Anthony Chen | R43: Giraffe Pictures | S43: Anthony Chen | T43: Teoh Gay Hian | U43: Hoping Chen | V43: Kin Leonn, Thomas Foguenne | W43: Yeo Yann Yann, Koh Jia Ler, Andi Lim, Regene Lim | X43: Na agitada Singapura contemporânea, Junyang, de 21 anos, aproveita a despreocupação da juventude enquanto o pai luta para sustentar a vida modesta que compartilham. Uma transformação inesperada em seu namoro o obriga a encarar a vida adulta antes do previsto. Ao mesmo tempo, a chegada de uma mulher expansiva à vida do pai altera o equilíbrio entre os dois. Diante do amor, da perda e da responsabilidade, pai e filho precisam repensar o significado de família e os vínculos que escolhem construir. Estreia mundial na competição oficial do Festival de Berlim 2026. | Y43: Direção: Anthony Chen | Roteiro: Anthony Chen | Produtora: Giraffe Pictures | Produção: Anthony Chen | Fotografia: Teoh Gay Hian | Montagem: Hoping Chen | Música: Kin Leonn, Thomas Foguenne | Elenco: Yeo Yann Yann, Koh Jia Ler, Andi Lim, Regene Lim | Z43: 3 | AA43: 2026 | AB43: Ficção
A44: 043 | B44: Panorama Mundial | C44: https://letterboxd.com/film/soumsoum-the-night-of-the-stars/ | D44: Soumsoum, a Noite das Estrelas | E44: Soumsoum, la nuit des astres | F44: Catálogo | G44: França + 1 país | H44: Ficção | I44: 101 | J44: 2026 | K44: Chade, França | L44: Ficção | M44: Sim | N44: Berlinale | O44: Competição Oficial | P44: Mahamat-Saleh Haroun | Q44: Mahamat-Saleh Haroun, Laurent Gaudé | R44: Goï Goï Productions, Pili Films, Florence Stern | S44: Florence Stern | T44: Mathieu Giombini | U44: Svetlana Vaynblat | V44: Bibi Tanga | W44: Maïmouna Miawama, Eriq Ebouaney, Achouackh Abakar Souleymane, Brigitte Tchanegue, Christ Assidjim Mbaihornom, Alias Small Christ, Sambo Saleh Adam | X44: No deserto de Ennedi, no Chade, montanhas milenares emergem da areia, guardando a memória de um passado esquecido e sussurrando antigas lendas. Kellou, de 17 anos, é atormentada por visões que não compreende e que a afastam dos outros moradores de seu vilarejo. Sua vida muda ao conhecer Aya, uma mulher rejeitada pela comunidade. Do encontro entre as duas nasce um vínculo que aproxima o visível e o invisível, a memória e a resistência. Vencedor do Prêmio FIPRESCI no Festival de Berlim 2026, onde integrou a competição oficial. | Y44: Direção: Mahamat-Saleh Haroun | Roteiro: Mahamat-Saleh Haroun, Laurent Gaudé | Produtora: Goï Goï Productions, Pili Films, Florence Stern | Produção: Florence Stern | Fotografia: Mathieu Giombini | Montagem: Svetlana Vaynblat | Música: Bibi Tanga | Elenco: Maïmouna Miawama, Eriq Ebouaney, Achouackh Abakar Souleymane, Brigitte Tchanegue, Christ Assidjim Mbaihornom, Alias Small Christ, Sambo Saleh Adam | Z44: 3 | AA44: 2026 | AB44: Ficção
A45: 044 | B45: Panorama Mundial | C45: https://letterboxd.com/film/mr-nelson-did-you-kill-people/ | D45: Sr. Nelson, o senhor Matou Pessoas? | E45: Nelson-san, anata wa hito o koro shimashita ka? | F45: Catálogo | G45: Japão + 3 países | H45: Ficção | I45: 116 | J45: 2026 | K45: Japão, Estados Unidos, Tailândia, Vietnã | L45: Ficção | P45: Shinya Tsukamoto | Q45: Shinya Tsukamoto | R45: Kino Films Co., Kinoshita Group. Ltd | S45: Yumiko Takebe, Christopher Frey | T45: Shinya Tsukamoto | U45: Shinya Tsukamoto | V45: Ermhoi | W45: Rodney Hicks, Geoffrey Rush, Mark Merphy, Tatyana Ali, Lily Franky | X45: Aos 18 anos, Allen Nelson se alista nos fuzileiros navais para escapar da pobreza e da discriminação. Enviado à Guerra do Vietnã em 1966, logo descobre que nada o havia preparado para a violência do combate nem para os crimes que seria obrigado a cometer. De volta aos Estados Unidos, atormentado pelas lembranças e por um grave transtorno de estresse pós-traumático, Allen encontra no acompanhamento do psiquiatra Dr. Daniels um caminho para confrontar o passado. Baseado em uma história real. Exibido em competição no Festival de Veneza 2026. | Y45: Direção: Shinya Tsukamoto | Roteiro: Shinya Tsukamoto | Produtora: Kino Films Co., Kinoshita Group. Ltd | Produção: Yumiko Takebe, Christopher Frey | Fotografia: Shinya Tsukamoto | Montagem: Shinya Tsukamoto | Música: Ermhoi | Elenco: Rodney Hicks, Geoffrey Rush, Mark Merphy, Tatyana Ali, Lily Franky | Z45: 3 | AA45: 2026 | AB45: Ficção
A46: 045 | B46: Panorama Mundial | C46: https://letterboxd.com/film/tender-loving-care-2026/ | D46: Tender Loving Care | F46: Complementar / catálogo parcial | G46: Reino Unido | H46: Ficção | I46: 107 | J46: 2026 | K46: Reino Unido | L46: Ficção | P46: Mike Leigh | Q46: Mike Leigh | R46: Bleecker Street | S46: Georgina Lowe | T46: Lucy Bristow | U46: Tania Reddin | V46: Gary Yershon | W46: Marion Bailey, Paul Jesson, Kate O'flynn, Alice Bailey Johnson | X46: Após o fim de um relacionamento, Amy, assistente social dedicada à proteção de crianças, volta a morar com Rosie, sua melhor amiga e também assistente social. As duas passam os dias amparando pessoas que o Estado já não consegue proteger, ao mesmo tempo que enfrentam suas próprias fragilidades. A preocupação dos pais idosos de Amy com a felicidade da filha ganha novo sentido quando eles se veem diante de uma crise. Com humor e ternura, Mike Leigh retrata os laços que nos sustentam quando cuidar e aceitar cuidado se tornam igualmente difíceis. | Y46: Direção: Mike Leigh | Roteiro: Mike Leigh | Produtora: Bleecker Street | Produção: Georgina Lowe | Fotografia: Lucy Bristow | Montagem: Tania Reddin | Música: Gary Yershon | Elenco: Marion Bailey, Paul Jesson, Kate O'flynn, Alice Bailey Johnson | Z46: 3 | AA46: 2026 | AB46: Ficção
A47: 046 | B47: Panorama Mundial | C47: https://letterboxd.com/film/the-echo-chamber/ | D47: The Echo Chamber | E47: Echo Chamber, The | F47: Catálogo | G47: Itália + 1 país | H47: Ficção | I47: 123 | J47: 2026 | K47: Itália, Bélgica | L47: Ficção | P47: Andrea Pallaoro | Q47: Bernardo Bertolucci, Ilaria Bernardini, Ludovica Rampoldi | R47: Indigo Film | S47: Nicola Giuliano, Francesca Cima, Carlotta Calori, Viola Prestieri | T47: Diego Garçia | U47: Paola Freddi | V47: Clément Ducol | W47: Luca Marinelli, Alicia Vikander, Susan Sarandon | X47: Leo, um célebre produtor musical, leva uma vida glamourosa que começa a fugir do controle. Durante um caso com Anne, uma fisioterapeuta, os limites entre afeto e dependência e desejo e dominação tornam-se cada vez mais incertos. Presos a um ciclo de vai e vem, os dois não conseguem permanecer juntos nem se libertar um do outro. Pelos cômodos do apartamento, a voz de Ava atravessa o tempo, trazendo à tona lembranças, feridas e tudo aquilo que já não pode ser contido. O filme parte do último roteiro de Bernardo Bertolucci. Competição principal do Festival de Veneza de 2026. | Y47: Direção: Andrea Pallaoro | Roteiro: Bernardo Bertolucci, Ilaria Bernardini, Ludovica Rampoldi | Produtora: Indigo Film | Produção: Nicola Giuliano, Francesca Cima, Carlotta Calori, Viola Prestieri | Fotografia: Diego Garçia | Montagem: Paola Freddi | Música: Clément Ducol | Elenco: Luca Marinelli, Alicia Vikander, Susan Sarandon | Z47: 3 | AA47: 2026 | AB47: Ficção
A48: 047 | B48: Panorama Mundial | C48: https://letterboxd.com/film/the-man-i-love-2026/ | D48: The Man I Love | E48: Man I Love, The | F48: Catálogo | G48: Estados Unidos + 1 país | H48: Ficção | I48: 97 | J48: 2026 | K48: Estados Unidos, França | L48: Ficção | M48: Sim | N48: Cannes | O48: Competição Oficial | P48: Ira Sachs | Q48: Mauricio Zacharias, Ira Sachs | R48: Big Greek | S48: Scott Mcgehee, David Siegel, Mike Spreter, Myriam Schroeter, Said Ben Said | T48: Josée Deshaies, Afc | U48: Affonso Goncalves, A.C.E. | W48: Rami Malek, Tom Sturridge, Luther Ford, Rebecca Hall, Ebon Moss-Bachrach, Amy Carlson, Maisy Stella, Stephen Bradbury, Stephen Adly Guirgis, Dennis Courtis, Sasha Lane, Kevin Rennard, Chris Giarmo, Nath Ann Carrera, Ryan Sands, Johannes Kienast, Mohammad Ghaffari, Lizbeth Mackay | X48: Ambientado na vibrante Nova York do final dos anos 1980, a história acompanha Jimmy George, um ator e artista performático, morador de downtown, navegando a dura realidade do diagnóstico de AIDS naquela década. Depois de uma internação delicada, na qual esteve à beira da morte, ele vivencia uma janela preciosa e desafiadora de tempo entre a doença grave e a perspectiva da morte. Recusando- -se a ser definido pela doença, Jimmy coloca todas as energias na busca pela beleza, pela arte e pelo desejo. Competição Principal no Festival de Cannes 2026. | Y48: Direção: Ira Sachs | Roteiro: Mauricio Zacharias, Ira Sachs | Produtora: Big Greek | Produção: Scott Mcgehee, David Siegel, Mike Spreter, Myriam Schroeter, Said Ben Said | Fotografia: Josée Deshaies, Afc | Montagem: Affonso Goncalves, A.C.E. | Elenco: Rami Malek, Tom Sturridge, Luther Ford, Rebecca Hall, Ebon Moss-Bachrach, Amy Carlson, Maisy Stella, Stephen Bradbury, Stephen Adly Guirgis, Dennis Courtis, Sasha Lane, Kevin Rennard, Chris Giarmo, Nath Ann Carrera, Ryan Sands, Johannes Kienast, Mohammad Ghaffari, Lizbeth Mackay | Z48: 3 | AA48: 2026 | AB48: Ficção
A49: 048 | B49: Panorama Mundial | C49: https://letterboxd.com/film/everybody-digs-bill-evans/ | D49: Todo Mundo Curte Bill Evans | E49: Everybody Digs Bill Evans | F49: Catálogo | G49: Irlanda + 1 país | H49: Ficção | I49: 102 | J49: 2026 | K49: Irlanda, Reino Unido | L49: Ficção | P49: Grant Gee | Q49: Mark O’halloran | R49: Hot Property Films, Cowtown Pictures | S49: Janine Mamot, Alan Maher | T49: Piers Mcgrail Isc | U49: Piers Mcgrail | V49: Roger Goula | W49: Anders Danielsen Lie, Barry Ward, Bill Pullman, Katie Mcgrath, Laurie Metcalf, Valene Kane | X49: Junho de 1961, Nova York. O lendário pianista de jazz Bill Evans encontrou sua voz musical e formou o trio perfeito, que incluía o baixista Scott LaFaro, sua alma gêmea musical. Dias depois de uma temporada no Village Vanguard, LaFaro morre tragicamente em um acidente de carro. Paralisado pela dor, Evans para de tocar pela primeira vez desde a infância. O documentário registra o que aconteceu a seguir com uma das figuras mais influentes e talentosas da música do século XX. Vencedor do Urso de Prata de Melhor Direção no Festival de Berlim 2026. | Y49: Direção: Grant Gee | Roteiro: Mark O’halloran | Produtora: Hot Property Films, Cowtown Pictures | Produção: Janine Mamot, Alan Maher | Fotografia: Piers Mcgrail Isc | Montagem: Piers Mcgrail | Música: Roger Goula | Elenco: Anders Danielsen Lie, Barry Ward, Bill Pullman, Katie Mcgrath, Laurie Metcalf, Valene Kane | Z49: 3 | AA49: 2026 | AB49: Ficção
A50: 049 | B50: Panorama Mundial | C50: https://letterboxd.com/film/all-the-lovers-in-the-night/ | D50: Todos os Amantes da Noite | E50: Subete Mayonaka No Koibitotachi | F50: Catálogo | G50: Japão | H50: Ficção | I50: 139 | J50: 2026 | K50: Japão | L50: Ficção | M50: Sim | N50: Cannes | O50: Un Certain Regard | P50: Yukiko Sode | Q50: Yukiko Sode | R50: C&i Entertainment, Bitters End | T50: Yasuyuki Sasaki | U50: Azusa Yamazaki | V50: Masato Suzuki | W50: Yukino Kishii, Tadanobu Asano, Misato Morita, Mai Fukagawa, Akihisa Shiono, Yuko Nakamura, Mijika Nagai, Kilala Inori, Tomo Nakai, Yuta Hayashi, Tori Matsuzaka | X50: Fuyuko leva uma vida silenciosa como revisora freelancer, quase sem contato com outras pessoas. Em seu aniversário, cultiva um único ritual: caminhar sozinha pela cidade à meia-noite. Sua rotina começa a mudar ao conhecer Mitsutsuka, um reservado professor de física que a convida a conversar sobre a luz. À medida que os encontros se repetem, uma conexão delicada surge entre esses dois desconhecidos que guardam o que não conseguem revelar. Adaptação do romance de Mieko Kawakami. Seleção oficial da mostra Un Certain Regard do Festival de Cannes 2026. | Y50: Direção: Yukiko Sode | Roteiro: Yukiko Sode | Produtora: C&i Entertainment, Bitters End | Fotografia: Yasuyuki Sasaki | Montagem: Azusa Yamazaki | Música: Masato Suzuki | Elenco: Yukino Kishii, Tadanobu Asano, Misato Morita, Mai Fukagawa, Akihisa Shiono, Yuko Nakamura, Mijika Nagai, Kilala Inori, Tomo Nakai, Yuta Hayashi, Tori Matsuzaka | Z50: 3 | AA50: 2026 | AB50: Ficção
A51: 050 | B51: Panorama Mundial | C51: https://letterboxd.com/film/notre-salut/ | D51: Um Homem do seu Tempo | E51: Notre Salut | F51: Catálogo | G51: Bélgica + 1 país | H51: Ficção | I51: 158 | J51: 2026 | K51: Bélgica, França | L51: Ficção | M51: Sim | N51: Cannes | O51: Competição Oficial | P51: Emmanuel Marre | Q51: Emmanuel Marre | R51: Kidam, Michigan Films | S51: Alexandre Perrier, François Pierre Clavel, Sébastien Andres, Alice Lemaire | T51: Olivier Boonjing | U51: Nicolas Rumpl | W51: Sandrine Blancke, Harpo Guit, Jean-Baptiste Marre, Mathieu Perotto, Mathilde Abd-El-Kader, Swann Arlaud | X51: Setembro de 1940. Enquanto o regime autoritário de Vichy se instala, Henri Marre, falido e afastado da família, chega à cidade com exemplares de seu manifesto político. Convencido de que merece um lugar na nova administração, o engenheiro oferece seu patriotismo e sua obsessão pela eficiência a uma máquina que exige obediência crescente. Inspirado nos arquivos familiares do diretor, o drama examina como ambição, fracasso e desejo de pertencimento alimentam a engrenagem da colaboração. Vencedor do prêmio de Melhor Roteiro no Festival de Cannes 2026. | Y51: Direção: Emmanuel Marre | Roteiro: Emmanuel Marre | Produtora: Kidam, Michigan Films | Produção: Alexandre Perrier, François Pierre Clavel, Sébastien Andres, Alice Lemaire | Fotografia: Olivier Boonjing | Montagem: Nicolas Rumpl | Elenco: Sandrine Blancke, Harpo Guit, Jean-Baptiste Marre, Mathieu Perotto, Mathilde Abd-El-Kader, Swann Arlaud | Z51: 3 | AA51: 2026 | AB51: Ficção
A52: 051 | B52: Panorama Mundial | C52: https://letterboxd.com/film/a-long-winter-2026/ | D52: Um Longo Inverno | E52: Long Winter, A | F52: Catálogo | G52: Canadá + 1 país | H52: Ficção | I52: 119 | J52: 2026 | K52: Canadá, Reino Unido | L52: Ficção | P52: Andrew Haigh | Q52: Andrew Haigh | R52: Nomadic Pictures | S52: Trsitan Goligher, Mike Elliott | T52: Andrew Turpin | U52: Jonathan Alberts | W52: Fred Hechinger, Catríona Balfe, D'pharaoh Woon-A-Tai, David Furr, Ebon Moss-Bachrach, Kit Connor, Manuel Garcia-Rulfo, Martin Freman | X52: No início dos anos 1950, nas montanhas do oeste dos Estados Unidos, Mikey vê sua família se desfazer lentamente. O irmão parte para a Guerra da Coreia, enquanto a mãe se sente cada vez mais aprisionada ao casamento e à vida isolada ao lado do marido, um mineiro de carvão. Quando ela desaparece durante uma tempestade de neve, pai e filho enfrentam a paisagem hostil em sua busca. Adaptado do conto de Colm Tóibín, o drama transforma a ausência em uma jornada íntima de amadurecimento e desejo. Seleção oficial dos festivais de Toronto e Nova York 2026. | Y52: Direção: Andrew Haigh | Roteiro: Andrew Haigh | Produtora: Nomadic Pictures | Produção: Trsitan Goligher, Mike Elliott | Fotografia: Andrew Turpin | Montagem: Jonathan Alberts | Elenco: Fred Hechinger, Catríona Balfe, D'pharaoh Woon-A-Tai, David Furr, Ebon Moss-Bachrach, Kit Connor, Manuel Garcia-Rulfo, Martin Freman | Z52: 3 | AA52: 2026 | AB52: Ficção
A53: 052 | B53: Panorama Mundial | C53: https://letterboxd.com/film/15-18/ | D53: Um Lugar Para se Curar | E53: 15/18 | F53: Catálogo | G53: França | H53: Ficção | I53: 104 | J53: 2026 | K53: França | L53: Ficção | M53: Sim | N53: Veneza | O53: Venezia 83 – Competição | P53: Cédric Kahn | Q53: Cédric Kahn, Kahina le Querrec | R53: Ad Vitam Films | S53: Alexandra Henochsberg | T53: Patrick Ghiringhelli | U53: Géraldine Mangenot | V53: Gael Rakotondrabe | W53: Malou Khebizi, Zoé Monpart, Kenji Peyran, Raphaël Besson, Patience Munchenbach, Ahleme Sahraoui, Jade Philip | X53: Levada pela polícia à ala psiquiátrica juvenil de um hospital público, Lucia, de 17 anos, reencontra a amiga Eloïse e um grupo de jovens em sofrimento. Conduzida por Etienne, a equipe médica ouve famílias e gerencia a rotina de um setor sobrecarregado. Entre pacientes e cuidadores, surgem laços frágeis que abrem espaço para lampejos de esperança. Contudo, o equilíbrio é ameaçado com a misteriosa chegada de Enzo. O drama integrou a Seleção Oficial Competitiva do Festival de Veneza de 2026. | Y53: Direção: Cédric Kahn | Roteiro: Cédric Kahn, Kahina le Querrec | Produtora: Ad Vitam Films | Produção: Alexandra Henochsberg | Fotografia: Patrick Ghiringhelli | Montagem: Géraldine Mangenot | Música: Gael Rakotondrabe | Elenco: Malou Khebizi, Zoé Monpart, Kenji Peyran, Raphaël Besson, Patience Munchenbach, Ahleme Sahraoui, Jade Philip | Z53: 3 | AA53: 2026 | AB53: Ficção
A54: 053 | B54: Panorama Mundial | C54: https://letterboxd.com/film/un-bon-petit-soldat/ | D54: Um Pequeno Bom Soldado | E54: Un bon petit soldat | F54: Catálogo | G54: França | H54: Ficção | I54: 102 | J54: 2026 | K54: França | L54: Ficção | M54: Sim | N54: Veneza | O54: Venezia 83 – Competição | P54: Stéphane Brizé | Q54: Stéphane Brizé, Coralie Amédéo, Olivier Gorce | R54: Gaumont, France 3 Cinéma | S54: Sidonie Dumas | T54: Antoine Héberlé | U54: Géraldine Mangenot | V54: Bertrand Blessing | W54: Alba Rohrwacher, Vincent Lindon, Sharif Andoura, David Talbot, Adrien Bobinet, Philippe Pollet-Villard, Rose Bourdon, Carine Rouvier, Sandra le Gall | X54: Aos 43 anos, Carla construiu uma carreira de sucesso à custa da vida familiar. Contratada para dirigir os recursos humanos de uma grande empresa, recebe a missão de promover o bem-estar dos funcionários sem comprometer as metas de desempenho. Ao descobrir um caso de gestão abusiva, percebe que cumprir as ordens pode significar trair aquilo que deveria defender. O filme venceu o prêmio de melhor roteiro no Festival de Veneza de 2026. | Y54: Direção: Stéphane Brizé | Roteiro: Stéphane Brizé, Coralie Amédéo, Olivier Gorce | Produtora: Gaumont, France 3 Cinéma | Produção: Sidonie Dumas | Fotografia: Antoine Héberlé | Montagem: Géraldine Mangenot | Música: Bertrand Blessing | Elenco: Alba Rohrwacher, Vincent Lindon, Sharif Andoura, David Talbot, Adrien Bobinet, Philippe Pollet-Villard, Rose Bourdon, Carine Rouvier, Sandra le Gall | Z54: 3 | AA54: 2026 | AB54: Ficção
A55: 054 | B55: Panorama Mundial | C55: https://letterboxd.com/film/le-vertige/ | D55: Vertigem | E55: Vertige, Le | F55: Catálogo | G55: França | H55: Animação | I55: 67 | J55: 2026 | K55: França | L55: Animação | P55: Quentin Dupieux | Q55: Quentin Dupieux | R55: Chi-Fou-Mi Productions | S55: Hugo Sélignac, Quentin Dupieux | T55: Quentin Dupieux | U55: Quentin Dupieux, Léo Pouliquen | V55: Franck Lascombes | W55: Alain Chabat, Jonathan Cohen, Anaïs Demoustier, Jean-Marie Winling | X55: Jacques visita seu grande amigo Bruno para compartilhar uma notícia urgente e monumental: toda a humanidade vive dentro de uma gigantesca simulação digital. Levando a teoria surpreendentemente a sério, Bruno inicia uma busca frenética por falhas na realidade cotidiana, o que aos poucos desestabiliza completamente o seu dia comum. Com uma estética deliberada de videogame retrô, esta comédia surreal explora os limites da existência. Exibido no Festival de Cannes 2026 na mostra Quinzena dos Realizadores. | Y55: Direção: Quentin Dupieux | Roteiro: Quentin Dupieux | Produtora: Chi-Fou-Mi Productions | Produção: Hugo Sélignac, Quentin Dupieux | Fotografia: Quentin Dupieux | Montagem: Quentin Dupieux, Léo Pouliquen | Música: Franck Lascombes | Elenco: Alain Chabat, Jonathan Cohen, Anaïs Demoustier, Jean-Marie Winling | Z55: 3 | AA55: 2026 | AB55: Animação
A56: 055 | B56: Panorama Mundial | C56: https://letterboxd.com/film/your-mother-your-mother-your-mother/ | D56: Your Mother Your Mother Your Mother | F56: Complementar / catálogo parcial | G56: Estados Unidos | H56: Ficção | I56: 112 | J56: 2026 | K56: Estados Unidos | L56: Ficção | P56: Bassam Tariq | Q56: Bassam Tariq | R56: Two & Two Pictures | S56: Lucan Toh, Babak Anvari, Bassam Tariq | T56: Katelin Arizmendi | U56: Cam Mclauchlin | V56: Son Lux | W56: Mahershala Ali, John Cho, Abubakr Ali, Adia, Giancarlo Esposito | X56: Latif é um muçulmano devoto, pai de três filhos e matador de aluguel guiado por um rígido código: não usa armas de fogo e só aceita alvos que considera merecedores. Após a morte da esposa, decide abandonar o crime e se dedicar à família. Mas o antigo patrão e uma guerra entre grupos religiosos de Houston frustram seus planos. Latif precisa encontrar leite materno para a filha bebê, ao mesmo tempo que a violência volta a cercá-lo e põe à prova sua fé e suas convicções. Estreia mundial no Festival de Toronto de 2026. | Y56: Direção: Bassam Tariq | Roteiro: Bassam Tariq | Produtora: Two & Two Pictures | Produção: Lucan Toh, Babak Anvari, Bassam Tariq | Fotografia: Katelin Arizmendi | Montagem: Cam Mclauchlin | Música: Son Lux | Elenco: Mahershala Ali, John Cho, Abubakr Ali, Adia, Giancarlo Esposito | Z56: 3 | AA56: 2026 | AB56: Ficção
A57: 056 | B57: Expectativa | C57: https://letterboxd.com/film/3-weeks-after/ | D57: 3 Semanas Depois | E57: 3 nedelje posle | F57: Catálogo | G57: Sérvia + 4 países | H57: Ficção | I57: 96 | J57: 2026 | K57: Sérvia, Bulgária, Itália, Croácia, Luxemburgo | L57: Ficção | P57: Miroslav Terzić | Q57: Vladimir Arsenijević, Miroslav Terzić, Bojan Vuletić | R57: This And That Productions | S57: Snežana van Houwelingen, Branislav Trifunović | T57: Damjan Radovanović | U57: Marko Ferković | V57: Lp Duo, Sonja Lončar & Andy Pavlov | W57: Jovan Ginić, Tihana Lazović, Branislav Trifunović, Andjela Alavirević, Klara Karaulić, Andrija Marković | X57: Três semanas após o suicídio de um colega, uma turma de adolescentes parte para uma excursão escolar à Bulgária. Quando o ônibus quebra e o grupo fica isolado em um antigo hotel nas montanhas, Zoza, melhor amigo do jovem morto, decide confrontar colegas e professores sobre o bullying que o levou à morte. Um olhar sobre os dilemas da adolescência, a omissão dos adultos e um acerto de contas com a culpa, o silêncio e a responsabilidade coletiva. | Y57: Direção: Miroslav Terzić | Roteiro: Vladimir Arsenijević, Miroslav Terzić, Bojan Vuletić | Produtora: This And That Productions | Produção: Snežana van Houwelingen, Branislav Trifunović | Fotografia: Damjan Radovanović | Montagem: Marko Ferković | Música: Lp Duo, Sonja Lončar & Andy Pavlov | Elenco: Jovan Ginić, Tihana Lazović, Branislav Trifunović, Andjela Alavirević, Klara Karaulić, Andrija Marković | Z57: 3 | AA57: 2026 | AB57: Ficção
A58: 057 | B58: Expectativa | C58: ="https://" & "letterboxd" & ".com/film/9-temples-vers-le-ciel/" -> https://letterboxd.com/film/9-temples-vers-le-ciel/ | D58: 9 Templos Para o Céu | E58: 9 Temples Vers le Ciel | F58: Catálogo | G58: Tailândia | H58: Ficção | I58: 140 | J58: 2026 | K58: Tailândia | L58: Ficção | M58: Sim | N58: Cannes | O58: Quinzena dos Cineastas | P58: Sompot Chidgasornpongse | Q58: Sompot Chidgasornpongse | R58: Kick The Machine Films | T58: Jonathan Ricquebourg | U58: Tham Kattiyakul, Jirapat Mekkrajai, Daniel Hui, Sompot Chidgasornpongse | W58: Amara Ramnarong, Surachai Ningsanond, Jirawut Chiwaruck, Yaneenan Jiraphatjittrin, Klaichan Phunman, Sompot Songkampol, Poon Sirapob, Yada Karnjanisakorn, Nichmon Shintadapong, Napasin Samkaewcham | X58: Quando uma vidente alerta que sua mãe pode morrer em breve, Sakol reúne a família para visitar nove templos budistas num único dia, na esperança de prolongar a vida dela. Espremidas numa van, três gerações atravessam a exuberante arquitetura tailandesa em meio a tensões antigas, diferenças religiosas e a saúde frágil da matriarca. Conjugando o sagrado e o cotidiano, a peregrinação se torna uma reflexão sobre fé, família e mortalidade. Exibido na Quinzena dos Cineastas do Festival de Cannes 2026 e representante da Tailândia no Oscar de 2027. | Y58: Direção: Sompot Chidgasornpongse | Roteiro: Sompot Chidgasornpongse | Produtora: Kick The Machine Films | Fotografia: Jonathan Ricquebourg | Montagem: Tham Kattiyakul, Jirapat Mekkrajai, Daniel Hui, Sompot Chidgasornpongse | Elenco: Amara Ramnarong, Surachai Ningsanond, Jirawut Chiwaruck, Yaneenan Jiraphatjittrin, Klaichan Phunman, Sompot Songkampol, Poon Sirapob, Yada Karnjanisakorn, Nichmon Shintadapong, Napasin Samkaewcham | Z58: 4 | AA58: 2026 | AB58: Ficção
A59: 058 | B59: Expectativa | C59: ="https://" & "letterboxd" & ".com/film/la-buena-hija/" -> https://letterboxd.com/film/la-buena-hija/ | D59: A Boa Filha | E59: Buena Hija, La | F59: Catálogo | G59: Espanha | H59: Ficção | I59: 103 | J59: 2025 | K59: Espanha | L59: Ficção | P59: Júlia de Paz Solvas | Q59: Núria Dunjó López, Júlia de Paz Solvas | R59: Astra Pictures, Avalon, Krater Films | S59: Sergio Grobas, Stefan Schmitz | T59: Sandra Roca | U59: Oriol Milán | V59: Natasha Pirard | W59: Alea Montesinos, Clàudia Ávila, Fortún, Iona Burriel, Janet Novás, Julián Villagran, Kiara Arancibia Pinto, Marcel Sanchez, Marta Millà, Martí Ribot, Oscar Rubio, Petra Martinez, Sandra Pujol Torguet | X59: Após a separação dos pais, Carmela e sua mãe vão morar na casa da avó. Enquanto luta para se adaptar à nova realidade, Carmela anseia por passar mais tempo na casa do pai, um artista plástico que ela admira e idolatra. A sombra e o carisma do pai impactam a vida, as decisões e a identidade da protagonista e das mulheres de sua família, levando-as a repensarem o futuro. | Y59: Direção: Júlia de Paz Solvas | Roteiro: Núria Dunjó López, Júlia de Paz Solvas | Produtora: Astra Pictures, Avalon, Krater Films | Produção: Sergio Grobas, Stefan Schmitz | Fotografia: Sandra Roca | Montagem: Oriol Milán | Música: Natasha Pirard | Elenco: Alea Montesinos, Clàudia Ávila, Fortún, Iona Burriel, Janet Novás, Julián Villagran, Kiara Arancibia Pinto, Marcel Sanchez, Marta Millà, Martí Ribot, Oscar Rubio, Petra Martinez, Sandra Pujol Torguet | Z59: 3 | AA59: 2025 | AB59: Ficção
A60: 059 | B60: Expectativa | C60: ="https://" & "letterboxd" & ".com/film/jiuri-ganeun-gil/" -> https://letterboxd.com/film/jiuri-ganeun-gil/ | D60: A Caminho | E60: Jiuri ganeun gil | F60: Catálogo | G60: Coreia do Sul | H60: Ficção | I60: 105 | J60: 2025 | K60: Coreia do Sul | L60: Ficção | P60: Yoo Jaein | Q60: Yoo Jaein | R60: Korean Academy Of Film Arts | S60: Kim Jihyoung | T60: Baek Jaeryung | U60: Yoo Jaein | V60: Lee Eunjoo | W60: Jang Jae-Hee, Jang Sun, Kim Sowan, Lee Hwawon, Lee Jiwon, Lee Ye-In, Oh Hani, Sim Subin, Yang Heung-Joo | X60: Na Coreia do Sul, a estudante Yun-ji engravida após uma relação secreta com seu professor casado. Quando ele desaparece misteriosamente, ela decide interromper a gravidez e roubar as economias da colega de quarto, Kyung-sun, para comprar pílulas abortivas ilegais. Furiosa, a amiga sai à sua procura, mas o conflito acaba dando origem a um vínculo inesperado. Com humor e delicadeza, este delicado filme aborda autonomia corporal, abandono e solidariedade feminina. Prêmio New Currents no Festival de Busan 2025 e selecionado para a Geração 14plus do Festival de Berlim. | Y60: Direção: Yoo Jaein | Roteiro: Yoo Jaein | Produtora: Korean Academy Of Film Arts | Produção: Kim Jihyoung | Fotografia: Baek Jaeryung | Montagem: Yoo Jaein | Música: Lee Eunjoo | Elenco: Jang Jae-Hee, Jang Sun, Kim Sowan, Lee Hwawon, Lee Jiwon, Lee Ye-In, Oh Hani, Sim Subin, Yang Heung-Joo | Z60: 3 | AA60: 2025 | AB60: Ficção
A61: 060 | B61: Expectativa | C61: https://letterboxd.com/film/the-education-of-jane-cumming/ | D61: A Educação de Jane Cumming | E61: Education of Jane Cumming, The | F61: Catálogo | G61: Alemanha + 2 países | H61: Ficção | I61: 114 | J61: 2026 | K61: Alemanha, Suíça, Reino Unido | L61: Ficção | P61: Sophie Heldman | Q61: Flora Nicholson, Sophie Heldman | R61: Heimatfilm Gmbh + Co. Kg | S61: Bettina Brokemper | T61: Kate Reid | U61: Isabel Meier | V61: Balz Bachman | W61: Clare Dunne, Fiona Shaw, Flora Nicholson, Mia Tharia, Sadie Shimmin | X61: Edimburgo, 1810. Jane Pirie e Marianne Woods abrem um internato para meninas, na esperança de construir juntas uma vida independente. Seu frágil universo é abalado pela chegada de Jane Cumming, uma adolescente mestiça criada na Índia que luta para encontrar lugar entre as colegas. À medida que afeto, ciúme e desejos não expressos confundem os limites entre elas, uma acusação desencadeia um escândalo que ameaça a reputação das professoras. Inspirado em fatos reais, o filme aborda raça, classe e sexualidade em uma sociedade dominada pelo preconceito. | Y61: Direção: Sophie Heldman | Roteiro: Flora Nicholson, Sophie Heldman | Produtora: Heimatfilm Gmbh + Co. Kg | Produção: Bettina Brokemper | Fotografia: Kate Reid | Montagem: Isabel Meier | Música: Balz Bachman | Elenco: Clare Dunne, Fiona Shaw, Flora Nicholson, Mia Tharia, Sadie Shimmin | Z61: 3 | AA61: 2026 | AB61: Ficção
A62: 061 | B62: Expectativa | C62: https://letterboxd.com/film/la-gradiva/ | D62: A Gradiva | E62: Gradiva, La | F62: Catálogo | G62: França + 1 país | H62: Ficção | I62: 145 | J62: 2026 | K62: França, Itália | L62: Ficção | M62: Sim | N62: Cannes | O62: Semana da Crítica – Competição | P62: Marine Atlan | Q62: Marine Atlan, Anne Brouillet | R62: Les Films du Poisson | S62: Inès Daïen Dasi | T62: Pierre Mazoyer, Marine Atlan | U62: Guillaume Lillo | W62: Antonia Buresi, Colas Quignard, Suzanne Gerin, Mitia Capellier-Audat | X62: Uma turma de alunos do ensino médio viaja para Pompéia para conhecer as ruínas e os corpos petrificados pelo Vesúvio. A viagem se torna um momento único em que a energia da juventude se choca com um mundo congelado no tempo. Os desejos dos jovens começam a vir à tona com uma intensidade inesperada, levando-os a uma ruptura irreversível. Exibido na Semana da Crítica de Cannes 2026. | Y62: Direção: Marine Atlan | Roteiro: Marine Atlan, Anne Brouillet | Produtora: Les Films du Poisson | Produção: Inès Daïen Dasi | Fotografia: Pierre Mazoyer, Marine Atlan | Montagem: Guillaume Lillo | Elenco: Antonia Buresi, Colas Quignard, Suzanne Gerin, Mitia Capellier-Audat | Z62: 3 | AA62: 2026 | AB62: Ficção
A63: 062 | B63: Expectativa | C63: https://letterboxd.com/film/bearcave/ | D63: A Gruta | E63: Arkoudotrypa | F63: Catálogo | G63: Grécia + 1 país | H63: Ficção | I63: 128 | J63: 2025 | K63: Grécia, Reino Unido | L63: Ficção | P63: Stergios Dinopoulos, Krysianna Papadakis | Q63: Krysianna B. Papadakis, Stergios Dinopoulos | R63: Greek Film Centre, Pucci Productions, Pame Ligo Collective | S63: Emily Sky Hickin, Stergios Dinopoulos, Krysianna Papadakis, Ishan Sanjay Deshpande, Thanasis Michalopoulos, Arsinoi Pilou | T63: Arsinoi Pilou | U63: Stergios Dinopoulos, Krysianna B. Papadakis, Vaggelis Katsaros | V63: John Tournas | W63: Hara Kyriazi, Pamela Oikonomaki, Sofia Linospori, Vaso Gkougkara, Leyteris Tsatsis, Sozos Christou | X63: No montanhoso vilarejo de Tirna, na Grécia, a agricultora Argyro e a manicure Anneta são amigas inseparáveis desde a infância. Quando Anneta revela que está grávida e pretende ir embora com o namorado policial, Argyro, secretamente apaixonada por ela, a desafia a caminhar até a lendária Caverna do Urso. A jornada transforma a amizade das duas em um confronto com o desejo, a liberdade e os destinos que lhes foram impostos. Indicado ao Queer Lion e vencedor do Europa Cinemas Label no Festival de Cinema de Veneza 2025. | Y63: Direção: Stergios Dinopoulos, Krysianna Papadakis | Roteiro: Krysianna B. Papadakis, Stergios Dinopoulos | Produtora: Greek Film Centre, Pucci Productions, Pame Ligo Collective | Produção: Emily Sky Hickin, Stergios Dinopoulos, Krysianna Papadakis, Ishan Sanjay Deshpande, Thanasis Michalopoulos, Arsinoi Pilou | Fotografia: Arsinoi Pilou | Montagem: Stergios Dinopoulos, Krysianna B. Papadakis, Vaggelis Katsaros | Música: John Tournas | Elenco: Hara Kyriazi, Pamela Oikonomaki, Sofia Linospori, Vaso Gkougkara, Leyteris Tsatsis, Sozos Christou | Z63: 3 | AA63: 2025 | AB63: Ficção
A64: 063 | B64: Expectativa | C64: ="https://" & "letterboxd" & ".com/film/la-mas-dulce/" -> https://letterboxd.com/film/la-mas-dulce/ | D64: A Mais Doce | E64: más dulce, La | F64: Catálogo | G64: Marrocos + 3 países | H64: Ficção | I64: 113 | J64: 2026 | K64: Marrocos, França, Espanha, Bélgica | L64: Ficção | M64: Sim | N64: Cannes | O64: Un Certain Regard | P64: Laïla Marrakchi | Q64: Laïla Marrakchi, Delphine Agut, Marion Bernard | R64: Lumen, Atelier de Production | S64: Juliette Schrameck, Mathieu Verhaeghe, Thomas Verhaeghe | T64: Tristan Galand - Sbc | U64: Jean-François Elie, Nicolas Chaudeurge | V64: Clara de Asís | W64: Nisrin Erradi, Hajar Graigaa, Hind Braik, Fatima Zahra Khoulati, Itsaso Arana, Paco Mora, Mohamed Larbi Ajbar, Fran Cantos, Nando Pérez, Fatima Attif, Antonio Estrada | X64: Duas jovens marroquinas deixam seu país para trabalhar na colheita de morangos no sul da Espanha, mas o que seria uma chance de mudar de vida vira um pesadelo de abusos e exploração. Unidas pela dor, elas encontram forças para quebrar o silêncio. Com a ajuda de um advogado, decidem enfrentar um sistema econômico poderoso e denunciar a violência que sofrem. Um drama social forte sobre coragem, sobrevivência e a luta de mulheres imigrantes invisíveis contra a injustiça. | Y64: Direção: Laïla Marrakchi | Roteiro: Laïla Marrakchi, Delphine Agut, Marion Bernard | Produtora: Lumen, Atelier de Production | Produção: Juliette Schrameck, Mathieu Verhaeghe, Thomas Verhaeghe | Fotografia: Tristan Galand - Sbc | Montagem: Jean-François Elie, Nicolas Chaudeurge | Música: Clara de Asís | Elenco: Nisrin Erradi, Hajar Graigaa, Hind Braik, Fatima Zahra Khoulati, Itsaso Arana, Paco Mora, Mohamed Larbi Ajbar, Fran Cantos, Nando Pérez, Fatima Attif, Antonio Estrada | Z64: 3 | AA64: 2026 | AB64: Ficção
A65: 064 | B65: Expectativa | C65: ="https://" & "letterboxd" & ".com/film/staatsschutz/" -> https://letterboxd.com/film/staatsschutz/ | D65: A Promotora | E65: Staatsschutz | F65: Catálogo | G65: Alemanha | H65: Ficção | I65: 114 | J65: 2026 | K65: Alemanha | L65: Ficção | P65: Faraz Shariat | Q65: Claudia Schaefer, Jee-Un Kim, Dr. Sun-Ju Choi | R65: Jünglinge Film | S65: Paulina Lorenz, Jorgo Narjes, Faraz Shariat | T65: Lotta Kilian | U65: Friederike Hohmuth | V65: Gabríel Ólafs | W65: Chen Emilie Yan, Julia Jentsch, Alev Irmak, Arnd Klawitter, Sebastian Urzendowsky | X65: Seyo Kim, jovem promotora teuto-coreana, está determinada a combater a violência da extrema-direita na Alemanha. Quando ela própria se torna alvo de um ataque racista, desafia os superiores e inicia uma investigação própria. À medida que as provas apontam para uma ampla rede neonazista, Seyo enfrenta não apenas os criminosos mas também um sistema de justiça que minimiza o extremismo e dificulta sua busca pela verdade. Vencedor do Prêmio do Público da mostra Panorama no Festival de Berlim 2026. | Y65: Direção: Faraz Shariat | Roteiro: Claudia Schaefer, Jee-Un Kim, Dr. Sun-Ju Choi | Produtora: Jünglinge Film | Produção: Paulina Lorenz, Jorgo Narjes, Faraz Shariat | Fotografia: Lotta Kilian | Montagem: Friederike Hohmuth | Música: Gabríel Ólafs | Elenco: Chen Emilie Yan, Julia Jentsch, Alev Irmak, Arnd Klawitter, Sebastian Urzendowsky | Z65: 3 | AA65: 2026 | AB65: Ficção
A66: 065 | B66: Expectativa | C66: https://letterboxd.com/film/allegro-pastell/ | D66: Allegro Pastell | F66: Complementar / catálogo parcial | G66: Alemanha | H66: Ficção | I66: 100 | J66: 2026 | K66: Alemanha | L66: Ficção | P66: Anna Roller | Q66: Leif Randt | R66: Bayerischer Rundfunk (Br), Ard Degeto Film Gmbh, Walker + Worm | S66: Max Rieger, Philipp Worm | T66: Felix Pflieger | U66: Andreas Wodraschke | V66: Max Rieger | W66: Haley Louise Jones, Jannis Niewöhner, Sylvaine Faligant | X66: A escritora Tanja e o web designer Jerome vivem o relacionamento à distância ideal entre Berlim e Maintal. Equilibrando intimidade e independência através de mensagens e visitas, a rotina dos millennials parece perfeita. Contudo, quando completam 30 anos e uma visão concreta de futuro juntos ganha força, o equilíbrio entre liberdade e apego desaba. Eles passam a questionar se o modelo de relação que adotaram é o que realmente desejam, testando os limites do próprio amor em uma análise precisa das neuroses modernas. | Y66: Direção: Anna Roller | Roteiro: Leif Randt | Produtora: Bayerischer Rundfunk (Br), Ard Degeto Film Gmbh, Walker + Worm | Produção: Max Rieger, Philipp Worm | Fotografia: Felix Pflieger | Montagem: Andreas Wodraschke | Música: Max Rieger | Elenco: Haley Louise Jones, Jannis Niewöhner, Sylvaine Faligant | Z66: 3 | AA66: 2026 | AB66: Ficção
A67: 066 | B67: Expectativa | C67: ="https://" & "letterboxd" & ".com/film/prima-della-guerra/" -> https://letterboxd.com/film/prima-della-guerra/ | D67: Antes da Guerra | E67: Prima Della Guerra | F67: Catálogo | G67: França + 1 país | H67: Ficção | I67: 76 | J67: 2026 | K67: França, Itália | L67: Ficção | P67: Tommaso Usberti | Q67: Tommaso Usberti | R67: Mir Cinematografica, L’heure D’été | S67: Lucas le Postec, Thibault de Gantès, Francesco Virga, Adele Dell’erario, Marco Serrecchia | T67: Mathieu Kauffmann | U67: Souliman Schelfout, Nathan Jacquard | W67: Piero Usberti, Luàna Bajrami, Cisky Capizzi, Sebastien Halnaut, Massimiliano Balduzzi, Dinu Corminboeuf, Giovanni Simiele, Claudia Poli, Sebastiano Amidani, Marica Pace, Giulia Rossini, Matteo Curseri, Béatrice Barichella | X67: Guido (23) vive em Piadena, uma cidade moldada pela agricultura industrial no Vale do Pó. Órfão de pai e adotado, obcecado por caça e sedutor habitual, ele conquistou profundo respeito em seu ambiente por meio da violência. Seu intenso encontro com Sonia, uma jovem que veio do Kosovo para visitar a família durante o verão, expõe inesperadamente todas as suas maiores fragilidades, forçando-o a escolher de forma definitiva entre seu verdadeiro amor por Sonia e todos aqueles que se opõem a isso. Exibido no Festival de Cannes 2026 na seção Cannes Première. | Y67: Direção: Tommaso Usberti | Roteiro: Tommaso Usberti | Produtora: Mir Cinematografica, L’heure D’été | Produção: Lucas le Postec, Thibault de Gantès, Francesco Virga, Adele Dell’erario, Marco Serrecchia | Fotografia: Mathieu Kauffmann | Montagem: Souliman Schelfout, Nathan Jacquard | Elenco: Piero Usberti, Luàna Bajrami, Cisky Capizzi, Sebastien Halnaut, Massimiliano Balduzzi, Dinu Corminboeuf, Giovanni Simiele, Claudia Poli, Sebastiano Amidani, Marica Pace, Giulia Rossini, Matteo Curseri, Béatrice Barichella | Z67: 3 | AA67: 2026 | AB67: Ficção
A68: 067 | B68: Expectativa | C68: ="https://" & "letterboxd" & ".com/film/le-rose-di-marrakech/" -> https://letterboxd.com/film/le-rose-di-marrakech/ | D68: As Rosas de Marrakech | E68: Rose di Marrakech, Le | F68: Catálogo | G68: Itália + 2 países | H68: Ficção | I68: 90 | J68: 2026 | K68: Itália, França, Marrocos | L68: Ficção | P68: Ginevra Elkann | Q68: Ginevra Elkann, Babak Jalali, Chiara Barzini | R68: Asmara Films, Tessalit Productions, Agora Films, Rai Cinema | S68: Ginevra Elkann, Souad Lamriki, Fabrizio Mosca, Jean Bréhat | T68: Simone D'arcangelo | U68: Francesca Calvelli | W68: Fanny Ardant, Ahmed Hammoud, Boubker Fahmi, Jalila Talemsi, Nisrin Erradi | X68: Leila é a dedicada governanta de Madame Isabelle, proprietária de uma luxuosa propriedade em Marrakech. Sob seus cuidados, a rotina da casa preserva a ordem minuciosa de um universo aparentemente perfeito. Quando alguém do passado de Leila chega inesperadamente, porém, a tranquilidade desse microcosmo começa a se desfazer, abalando o equilíbrio que ela se esforça diariamente para manter. | Y68: Direção: Ginevra Elkann | Roteiro: Ginevra Elkann, Babak Jalali, Chiara Barzini | Produtora: Asmara Films, Tessalit Productions, Agora Films, Rai Cinema | Produção: Ginevra Elkann, Souad Lamriki, Fabrizio Mosca, Jean Bréhat | Fotografia: Simone D'arcangelo | Montagem: Francesca Calvelli | Elenco: Fanny Ardant, Ahmed Hammoud, Boubker Fahmi, Jalila Talemsi, Nisrin Erradi | Z68: 3 | AA68: 2026 | AB68: Ficção
A69: 068 | B69: Expectativa | C69: ="https://" & "letterboxd" & ".com/film/balcanica/" -> https://letterboxd.com/film/balcanica/ | D69: Balcânica | E69: Balcanica | F69: Catálogo | G69: Itália + 2 países | H69: Ficção | I69: 86 | J69: 2026 | K69: Itália, Sérvia, Croácia | L69: Ficção | M69: Sim | N69: Veneza | O69: Giornate degli Autori | P69: Nicola Sorcinelli | Q69: Nicola Sorcinelli, Andrea Brusa | R69: Nightswim, Wildside | S69: Ines Vasiljević, Stefano Sardo, Sonia Rovai, Ludovica Damiani | T69: Damjan Radovanović | U69: Ian Degrassi | V69: Michele Braga | W69: Matilda de Angelis, Babak Karimi, Ivar Wafaei, Giovanni Toscano | X69: Quando a música é proibida no Afeganistão, Nazar, maestro de uma orquestra, e seu filho Jalil, tubista, são obrigados a abandonar o país. Os dois seguem pela rota dos Bálcãs rumo à Itália, na esperança de encontrar um lugar onde possam voltar a tocar. Durante a travessia, conhecem Greta, uma jovem médica italiana em sua primeira missão humanitária. O encontro coloca os três diante de escolhas que mudarão suas vidas. Estreia mundial na Giornate degli Autori do Festival de Veneza de 2026. | Y69: Direção: Nicola Sorcinelli | Roteiro: Nicola Sorcinelli, Andrea Brusa | Produtora: Nightswim, Wildside | Produção: Ines Vasiljević, Stefano Sardo, Sonia Rovai, Ludovica Damiani | Fotografia: Damjan Radovanović | Montagem: Ian Degrassi | Música: Michele Braga | Elenco: Matilda de Angelis, Babak Karimi, Ivar Wafaei, Giovanni Toscano | Z69: 3 | AA69: 2026 | AB69: Ficção
A70: 069 | B70: Expectativa | C70: https://letterboxd.com/film/benimana/ | D70: Ben'Imana: Filhas de Deus | E70: Ben’Imana | F70: Catálogo | G70: Ruanda + 4 países | H70: Ficção | I70: 101 | J70: 2026 | K70: Ruanda, Gabão, França, Norue- ga, Costa do Marfim | L70: Ficção | M70: Sim | N70: Cannes | O70: Un Certain Regard | P70: Marie-Clémentine Dusabe- Jambo | Q70: Marie-Clémentine Dusabe- Jambo, Delphine Agut | R70: Ogweli Productions, Ejo Cine Ltd | S70: Samantha Biffot, Marie Epiphanie Uwayezu, Pierre-Adrien Ceccaldi, Marie-Clémentine Dusabe- Jambo | T70: Mostafa El Kashef | U70: Nadia Ben Rachid | V70: Igor Mabano | W70: Clémentine U. Nyirinkindi, Kesia Kelly Nishimwe, Arivere Kagoyire, Isabelle Kabano, Antoinette Uwamahoro, Léocadie Uwabeza, Aime Valens Tuyisenge, Hamida Uwimana, Adelite Mugabo, Clémence Murorunkwer | X70: Ruanda, 2012. Anos após o genocídio contra os Tutsi, julgamentos comunitários buscam justiça. Vénéranda, uma sobrevivente, lidera o diálogo entre vítimas e famílias de perpetradores, ajudando a reconstruir vidas. Mas quando descobre a gravidez inesperada de sua filha, ela é forçada a confrontar os limites de suas próprias convicções. Exibido na mostra Un Certain Regard do Festival de Cannes 2026. | Y70: Direção: Marie-Clémentine Dusabe- Jambo | Roteiro: Marie-Clémentine Dusabe- Jambo, Delphine Agut | Produtora: Ogweli Productions, Ejo Cine Ltd | Produção: Samantha Biffot, Marie Epiphanie Uwayezu, Pierre-Adrien Ceccaldi, Marie-Clémentine Dusabe- Jambo | Fotografia: Mostafa El Kashef | Montagem: Nadia Ben Rachid | Música: Igor Mabano | Elenco: Clémentine U. Nyirinkindi, Kesia Kelly Nishimwe, Arivere Kagoyire, Isabelle Kabano, Antoinette Uwamahoro, Léocadie Uwabeza, Aime Valens Tuyisenge, Hamida Uwimana, Adelite Mugabo, Clémence Murorunkwer | Z70: 3 | AA70: 2026 | AB70: Ficção
A71: 070 | B71: Expectativa | C71: ="https://" & "letterboxd" & ".com/film/moragheb/" -> https://letterboxd.com/film/moragheb/ | D71: Casa em Queda | E71: Moragheb | F71: Catálogo | G71: Irã + 2 países | H71: Ficção | I71: 125 | J71: 2026 | K71: Irã, Estados Unidos, Alemanha | L71: Ficção | P71: Mohsen Gharaei | Q71: Mohsen Gharaei, Amirmohammad Abdi | R71: Raefilm Studios, Seven Springs Pictures | S71: Daya Fernandez, Milad Khosravi | T71: Farshad Mohammadi | U71: Evelyn Rack, Emad Khodabakhsh | V71: Max Richter | W71: Farhad Aslani, Laleh Marzban, Rima Raminfar, Elena Khakbazan | X71: Na periferia de Teerã, uma família vê sua casa ameaçada de demolição por um grande projeto de reurbanização. Rashid, o pai, é um agente penitenciário acusado de corrupção. Em meio à crise, ele descobre que Ensi, sua filha mais velha, planeja deixar o Irã para seguir a carreira de modelo. Enquanto as escavadeiras se aproximam, Rashid tenta impedir a partida da jovem, e as tensões dentro de casa conduzem a família ao limite. | Y71: Direção: Mohsen Gharaei | Roteiro: Mohsen Gharaei, Amirmohammad Abdi | Produtora: Raefilm Studios, Seven Springs Pictures | Produção: Daya Fernandez, Milad Khosravi | Fotografia: Farshad Mohammadi | Montagem: Evelyn Rack, Emad Khodabakhsh | Música: Max Richter | Elenco: Farhad Aslani, Laleh Marzban, Rima Raminfar, Elena Khakbazan | Z71: 3 | AA71: 2026 | AB71: Ficção
A72: 071 | B72: Expectativa | C72: ="https://" & "letterboxd" & ".com/film/ji-guang/" -> https://letterboxd.com/film/ji-guang/ | D72: Cassowary | E72: Ji Guang | F72: Catálogo | G72: China | H72: Ficção | I72: 87 | J72: 2026 | K72: China | L72: Ficção | P72: Zhang Hanyi | Q72: Zhang Hanyi | S72: Ma Xiaotian | T72: Sou Wai Kin | U72: Paulie Chih-Chia Huang | V72: He Guofeng | W72: Huang Miyi, Liu Dan, Wei Ruguang, Yang Bo | X72: Em uma ilha isolada, Sumin, a mãe e a avó compartilham uma rotina tranquila, embora separadas por silêncios e antigas feridas. Desejando deixar o lugar, Sumin é obrigada a voltar para casa após um acontecimento inesperado. Quando um tufão atravessa a ilha e surge uma ave misteriosa capaz de devorar fogo, a busca pela criatura rompe o frágil equilíbrio familiar e conduz as três gerações por lembranças, afetos não expressos e desejos de fuga. Exibido na competição Asian New Talent do Festival de Xangai 2026. | Y72: Direção: Zhang Hanyi | Roteiro: Zhang Hanyi | Produção: Ma Xiaotian | Fotografia: Sou Wai Kin | Montagem: Paulie Chih-Chia Huang | Música: He Guofeng | Elenco: Huang Miyi, Liu Dan, Wei Ruguang, Yang Bo | Z72: 3 | AA72: 2026 | AB72: Ficção
A73: 072 | B73: Expectativa | C73: https://letterboxd.com/film/chica-checa/ | D73: Chica Checa | F73: Complementar / catálogo parcial | G73: República Tcheca + 2 países | H73: Ficção | I73: 96 | J73: 2026 | K73: República Tcheca, França, Eslováquia | L73: Ficção | P73: Šimon Holý | Q73: Šimon Holý | R73: Silk Films | S73: Alzbeta Janackova | T73: Jana Hojdová | U73: Sabina Mladenová | V73: Šimon Holý | W73: Alena Doláková, Alexandra Borbély, Daniela Seemannová, Erwan Kepoa Fale, František Cech, Hana Seidlová, Jan Cina, Jitka Schneiderová, Lubomíra Sonková, Martin Hronský, Martin Talaga, Michal Černý, Miroslav Kumhala, Natalie Řehořová, Naďa Kovářová, Pavla Tomicová, Sara Venclovská, Věra Janků | X73: Zdena é uma viúva de meia-idade que leva uma rotina pacata como carteira em uma pequena aldeia checa. Enquanto cuida de sua mãe debilitada, ela recebe a visita do filho, Lukáš, que mora em Paris. O retorno dele desencadeia a revelação de um grande segredo: longe de casa, o jovem não trabalha em um banco, mas atua profissionalmente como a drag queen Chica Checa. O choque inicial força mãe e filho a confrontar preconceitos locais, transformando a descoberta em uma emocionante e bem-humorada jornada de aceitação e redescoberta familiar. | Y73: Direção: Šimon Holý | Roteiro: Šimon Holý | Produtora: Silk Films | Produção: Alzbeta Janackova | Fotografia: Jana Hojdová | Montagem: Sabina Mladenová | Música: Šimon Holý | Elenco: Alena Doláková, Alexandra Borbély, Daniela Seemannová, Erwan Kepoa Fale, František Cech, Hana Seidlová, Jan Cina, Jitka Schneiderová, Lubomíra Sonková, Martin Hronský, Martin Talaga, Michal Černý, Miroslav Kumhala, Natalie Řehořová, Naďa Kovářová, Pavla Tomicová, Sara Venclovská, Věra Janků | Z73: 3 | AA73: 2026 | AB73: Ficção
A74: 073 | B74: Expectativa | C74: https://letterboxd.com/film/congo-boy/ | D74: Congo Boy | F74: Complementar / catálogo parcial | G74: Centro-Africana República + 3 países | H74: Ficção | I74: 90 | J74: 2026 | K74: Centro-Africana República, França, Congo República Democrática, Itália | L74: Ficção | M74: Sim | N74: Cannes | O74: Un Certain Regard | P74: Rafiki Fariala | Q74: Rafiki Fariala, Tommy Baron | R74: Makongo Films, Karta Film, Kiripifilms, Unité | S74: Boris Lojkine, Elvis Sabin Ngaïbino, Daniele Incalcaterra | T74: Adrien Lallau | U74: César Simonot, Xavier Sirven | V74: Rafiki Fariala, Lillo Morealle | W74: Bradley Fiomona, Christy Djomanda Louba, Pétruche Mbomba, Rosiana Kotozia, Gloria Ambacko, Dieufera Sana, Carlos Suffisant Djihoro, David Ningando, Hubert Ngbolo | X74: Em Bangui, na República Centro-Africana, Robert, de 17 anos, sonha em seguir carreira na música enquanto a guerra civil devasta o país. Quando seus pais são presos, ele se vê sozinho e responsável pelos quatro irmãos mais novos. Determinado a realizar seu grande sonho, o jovem precisa conciliar a rotina da família, trabalhos ocasionais, provas escolares e apresentações musicais. O longa teve sua aguardada estreia mundial no Festival de Cannes 2026, na competição da mostra Un Certain Regard. | Y74: Direção: Rafiki Fariala | Roteiro: Rafiki Fariala, Tommy Baron | Produtora: Makongo Films, Karta Film, Kiripifilms, Unité | Produção: Boris Lojkine, Elvis Sabin Ngaïbino, Daniele Incalcaterra | Fotografia: Adrien Lallau | Montagem: César Simonot, Xavier Sirven | Música: Rafiki Fariala, Lillo Morealle | Elenco: Bradley Fiomona, Christy Djomanda Louba, Pétruche Mbomba, Rosiana Kotozia, Gloria Ambacko, Dieufera Sana, Carlos Suffisant Djihoro, David Ningando, Hubert Ngbolo | Z74: 3 | AA74: 2026 | AB74: Ficção
A75: 074 | B75: Expectativa | C75: ="https://" & "letterboxd" & ".com/film/diya-2026/" -> https://letterboxd.com/film/diya-2026/ | D75: Diya - O Preço do Sangue | E75: Diya | F75: Catálogo | G75: Chade + 2 países | H75: Ficção | I75: 96 | J75: 2025 | K75: Chade, França, Alemanha | L75: Ficção | P75: Achille Ronaimou | Q75: Achille Ronaimou | R75: Babi Pictures, Sic Productions, Artisans du Film, Film Galerie451, L'atelier | S75: Issa Serge Coelo, Valery du Peloux, Frieder Schlaich, Frederic Ouziel, Jacques Trabi | T75: Cyrille Hubert | U75: Guillaume Talvas | V75: Afrotronix | W75: Ferdinand Mbaissané, Moussa Zakaria Ibet, Ramada Mahamat, Youssouf Djaoro, Haikal Zakaria | X75: Em N'Djamena, Dane trabalha como motorista de uma ONG humanitária e leva uma vida tranquila com Delphine, sua jovem esposa, grávida de oito meses. Um instante de distração ao volante termina no atropelamento de um menino. Após certa confusão no hospital, ele é informado de que a criança morreu. A família exige a diya — o “preço do sangue”, uma compensação pelo acidente. Para reunir o valor e proteger os seus, Dane parte rumo ao deserto do norte do Chade, onde sua busca assume contornos inesperados. Prêmio de melhor ator para Ferdinand Mbaïssané no Fespaco 2025. | Y75: Direção: Achille Ronaimou | Roteiro: Achille Ronaimou | Produtora: Babi Pictures, Sic Productions, Artisans du Film, Film Galerie451, L'atelier | Produção: Issa Serge Coelo, Valery du Peloux, Frieder Schlaich, Frederic Ouziel, Jacques Trabi | Fotografia: Cyrille Hubert | Montagem: Guillaume Talvas | Música: Afrotronix | Elenco: Ferdinand Mbaissané, Moussa Zakaria Ibet, Ramada Mahamat, Youssouf Djaoro, Haikal Zakaria | Z75: 3 | AA75: 2025 | AB75: Ficção
A76: 075 | B76: Expectativa | C76: ="https://" & "letterboxd" & ".com/film/dua-2026/" -> https://letterboxd.com/film/dua-2026/ | D76: Dua - Tempos de Guerra | E76: Dua | F76: Catálogo | G76: França + 2 países | H76: Ficção | I76: 101 | J76: 2026 | K76: Kosovo, França, Suíça | L76: Ficção | P76: Blerta Basholli | Q76: Blerta Basholli, Nicole Borgeat | R76: Ikonë Studio, Alva Film | S76: Valon Bajgora, Yll Uka | T76: Lucie Baudinaud, Afc | U76: Enis Saraçi | V76: Audrey Ismaël | W76: Pinea Matoshi, Kaona Matoshi, Yllka Gashi, Kushtrim Hoxha, Andi Bajgora, Vlera Bilalli | X76: Em Pristina, no fim dos anos 90, Dua tenta viver a adolescência enquanto a Guerra do Kosovo se inicia. Quando um incidente violento abala sua comunidade, a menina de 13 anos vira alvo de forte discriminação. Sua força surge ao conhecer Maki, uma jovem corajosa que lhe ensina uma forma inesperada de resistência. Exibido na Semana da Crítica do Festival de Cannes 2026. | Y76: Direção: Blerta Basholli | Roteiro: Blerta Basholli, Nicole Borgeat | Produtora: Ikonë Studio, Alva Film | Produção: Valon Bajgora, Yll Uka | Fotografia: Lucie Baudinaud, Afc | Montagem: Enis Saraçi | Música: Audrey Ismaël | Elenco: Pinea Matoshi, Kaona Matoshi, Yllka Gashi, Kushtrim Hoxha, Andi Bajgora, Vlera Bilalli | Z76: 3 | AA76: 2026 | AB76: Ficção
A77: 076 | B77: Expectativa | C77: https://letterboxd.com/film/elephants-in-the-fog/ | D77: Elefantes na Névoa | E77: Tinīharū | F77: Catálogo | G77: Nepal + 4 países | H77: Ficção | I77: 108 | J77: 2026 | K77: Nepal, Alemanha, Brasil, França, Noruega | L77: Ficção | M77: Sim | N77: Cannes | O77: Un Certain Regard | P77: Abinash Bikram Shah | Q77: Abinash Bikram Shah, Abinash Bikram Shah & Sandeep Bada, Sandeep Badal | R77: Die Gesellschaft Dgs, Underground Talkies Nepal, Les Valseurs | S77: Anup Poudel, Justin Pechberty, Damien Megherbi, Michael Henrichs | T77: Noé Bach | U77: Andrew Bird, Paris J. Ludwig | V77: Frédéric Alvarez | W77: Puspa Thing Lama, Sahab Din Miya, Jasmin Bishwokarma, Aliz Ghimire, Joel Gurung, Aashant Sharma, Sanjay Gupta, Umesha Pandey, Gauri Malla, Maotse Gurung | X77: Em uma pequena aldeia do Nepal, à beira de uma floresta onde elefantes selvagens circulam durante a noite, Pirati lidera uma comunidade Kinnar, formada por mulheres trans que construíram entre si uma família de afeto e proteção. Pirati, porém, sonha em deixar tudo para trás e partir com o homem que ama. Mas quando uma de suas “filhas” desaparece durante na ronda noturna, ela se vê obrigada a iniciar uma busca por conta própria, dividida entre o desejo de liberdade, os laços afetivos e as pressões de uma sociedade que mantém sua comunidade à margem. | Y77: Direção: Abinash Bikram Shah | Roteiro: Abinash Bikram Shah, Abinash Bikram Shah & Sandeep Bada, Sandeep Badal | Produtora: Die Gesellschaft Dgs, Underground Talkies Nepal, Les Valseurs | Produção: Anup Poudel, Justin Pechberty, Damien Megherbi, Michael Henrichs | Fotografia: Noé Bach | Montagem: Andrew Bird, Paris J. Ludwig | Música: Frédéric Alvarez | Elenco: Puspa Thing Lama, Sahab Din Miya, Jasmin Bishwokarma, Aliz Ghimire, Joel Gurung, Aashant Sharma, Sanjay Gupta, Umesha Pandey, Gauri Malla, Maotse Gurung | Z77: 4 | AA77: 2026 | AB77: Ficção
A78: 077 | B78: Expectativa | C78: ="https://" & "letterboxd" & ".com/film/a-voix-basse/" -> https://letterboxd.com/film/a-voix-basse/ | D78: Em Segredo | E78: À voix basse | F78: Catálogo | G78: França + 1 país | H78: Ficção | I78: 112 | J78: 2026 | K78: França, Tunísia | L78: Ficção | P78: Leyla Bouzid | Q78: Leyla Bouzid | R78: Unité | S78: Caroline Nataf | T78: Sebastien Goepfert | U78: Lilian Corbeille | V78: Yom | W78: Eya Bouteraa, Feriel Chamari, Hiam Abbass, Karim Rmadi, Lassaad Jamoussi, Marion Barbeau, Salma Baccar | X78: Lilia volta de Paris à Tunísia para o funeral do tio, acompanhada da namorada, Alice, que fica escondida em um hotel, já que a família de Lilia nada sabe sobre sua vida amorosa. Determinada a compreender a morte repentina do tio, ela retorna a uma casa onde convivem três gerações de mulheres e na qual memórias e verdades silenciadas aos poucos vêm à tona. Uma história sobre amor, repressão e segredos familiares. Estreia mundial na competição do Festival de Berlim 2026. | Y78: Direção: Leyla Bouzid | Roteiro: Leyla Bouzid | Produtora: Unité | Produção: Caroline Nataf | Fotografia: Sebastien Goepfert | Montagem: Lilian Corbeille | Música: Yom | Elenco: Eya Bouteraa, Feriel Chamari, Hiam Abbass, Karim Rmadi, Lassaad Jamoussi, Marion Barbeau, Salma Baccar | Z78: 3 | AA78: 2026 | AB78: Ficção
A79: 078 | B79: Expectativa | C79: https://letterboxd.com/film/animol/ | D79: Enjaulados | E79: Animol | F79: Catálogo | G79: Reino Unido | H79: Ficção | I79: 92 | J79: 2026 | K79: Reino Unido | L79: Ficção | P79: Ashley Walters | Q79: Nick Love | R79: Rogue State, Sky, Film 4, Joi Productions, Snlda, Bfi | S79: Tom Hawkins, Joy Gharoro-Akpojotor, Nick Love, Ashley Walters | T79: Tasha Back | U79: Danielle Palemer | V79: Swindle | W79: Ryan Dean, Sekou Diaby, Sharon Duncan-Brewster, Stephen Graham, Tut Nyuot, Vladyslav Baliuk | X79: Encarcerado em um centro de detenção juvenil, Troy é lançado em um universo regido pela violência, pelas gangues e por rígidas hierarquias de poder. Posto à prova desde o momento em que chega, ele precisa aprender rapidamente as regras de lealdade e confiança. Um vínculo inesperado com outro jovem lhe oferece um raro momento de acolhimento, mas também o expõe a novos riscos. Enquanto sua assistente social tenta reaproximá-lo da mãe, Troy se vê cada vez mais enredado na lógica implacável da instituição. Exibido na mostra Perspectives do Festival de Berlim 2026. | Y79: Direção: Ashley Walters | Roteiro: Nick Love | Produtora: Rogue State, Sky, Film 4, Joi Productions, Snlda, Bfi | Produção: Tom Hawkins, Joy Gharoro-Akpojotor, Nick Love, Ashley Walters | Fotografia: Tasha Back | Montagem: Danielle Palemer | Música: Swindle | Elenco: Ryan Dean, Sekou Diaby, Sharon Duncan-Brewster, Stephen Graham, Tut Nyuot, Vladyslav Baliuk | Z79: 3 | AA79: 2026 | AB79: Ficção
A80: 079 | B80: Expectativa | C80: ="https://" & "letterboxd" & ".com/film/dziecko-z-pylu/" -> https://letterboxd.com/film/dziecko-z-pylu/ | D80: Filho da Poeira | E80: Dziecko z Pyłu | F80: Catálogo | G80: Catar + 4 países | H80: Documentário | I80: 92 | J80: 2025 | K80: Polônia, Suécia, Vietnã, República Tcheca, Catar | L80: Documentário | P80: Weronika Mliczewska | Q80: Weronika Mliczewska | R80: Ya Man Studio | S80: Weronika Mliczewska, Bao Nguyen, Chi-Minh de Leo | T80: Mikael Lypinski | U80: Marcin Sucharski Psm, Mateusz Romaszkan | V80: Joaquin Garcia | X80: Meio século após o fim da Guerra do Vietnã, os filhos órfãos deixados por soldados americanos continuam pagando o preço de um conflito que nunca escolheram. Rejeitados e marcados pelo abandono, eles sobrevivem como fantasmas do passado. O documentário acompanha a saga dolorosa de um homem vietnamita consumido por uma obsessão: cruzar o oceano, encontrar o pai que jamais conheceu e reivindicar a identidade que lhe foi roubada. Prêmios de Melhor Documentário Internacional, Melhor Documentário Polonês e Melhor Montagem no Festival de Cracóvia 2025. | Y80: Direção: Weronika Mliczewska | Roteiro: Weronika Mliczewska | Produtora: Ya Man Studio | Produção: Weronika Mliczewska, Bao Nguyen, Chi-Minh de Leo | Fotografia: Mikael Lypinski | Montagem: Marcin Sucharski Psm, Mateusz Romaszkan | Música: Joaquin Garcia | Z80: 3 | AA80: 2025 | AB80: Documentário
A81: 080 | B81: Expectativa | C81: ="https://" & "letterboxd" & ".com/film/hanabi-2026/" -> https://letterboxd.com/film/hanabi-2026/ | D81: Flor de Fogo | E81: Hanabi | F81: Catálogo | G81: Brasil + 1 país | H81: Documentário | I81: 105 | J81: 2026 | K81: França, Brasil | L81: Documentário | P81: Ana Vaz | Q81: Ana Vaz | R81: Les Volcans, Tambores, A Noite | S81: Ana Vaz, Corinne Castel, Gustavo Pastorino | T81: Ana Vaz | U81: Ana Vaz, Chaghig Arzoumanian | V81: Ketu | X81: Adaptação visceral de Diário de um Cérebro Radioativo, de Yoko Hayasuke, escrito após o tsunami e o desastre nuclear provocados pelo terremoto de Tohoku, em 2011, o filme entrelaça o relato íntimo da autora a um mosaico de histórias de sobrevivência e resistência de comunidades que parecem já estar habitando um mundo em colapso. | Y81: Direção: Ana Vaz | Roteiro: Ana Vaz | Produtora: Les Volcans, Tambores, A Noite | Produção: Ana Vaz, Corinne Castel, Gustavo Pastorino | Fotografia: Ana Vaz | Montagem: Ana Vaz, Chaghig Arzoumanian | Música: Ketu | Z81: 4 | AA81: 2026 | AB81: Documentário
A82: 081 | B82: Expectativa | C82: https://letterboxd.com/film/furies-2026/ | D82: Furies | F82: Complementar / catálogo parcial | G82: Brasil + 1 país | H82: Ficção | I82: 133 | J82: 2026 | K82: Brasil, Líbano | L82: Ficção | P82: Rami Kodeih | Q82: Rami Kodeih, Nora Mariana | R82: Nausika Films, Rt Features | S82: Rodrigo Teixeira, Berta Marchiori, Rami Kodeih, Nora Mariana | T82: Tony Kopec | U82: Rami Kodeih | V82: Arthur Joly | W82: Hasan Akil, Issam Bou Khaled, Maria Nakouzi, Rym Mroue | X82: Durante o colapso econômico do Líbano em 2019, uma jovem em Beirute, sem poder retirar do banco as economias para pagar a cirurgia de câncer da irmã, junta-se a um caminhoneiro e a um ex-miliciano. Juntos, eles planejam um ousado assalto noturno para reaver o que é deles de um sistema bancário corrupto. Conforme o plano avança, o perigo cresce, forçando-os a encarar o real custo da sobrevivência, da justiça e da irmandade em uma cidade à beira do abismo. | Y82: Direção: Rami Kodeih | Roteiro: Rami Kodeih, Nora Mariana | Produtora: Nausika Films, Rt Features | Produção: Rodrigo Teixeira, Berta Marchiori, Rami Kodeih, Nora Mariana | Fotografia: Tony Kopec | Montagem: Rami Kodeih | Música: Arthur Joly | Elenco: Hasan Akil, Issam Bou Khaled, Maria Nakouzi, Rym Mroue | Z82: 3 | AA82: 2026 | AB82: Ficção
A83: 082 | B83: Expectativa | C83: ="https://" & "letterboxd" & ".com/film/wu-ming-nu-hai/" -> https://letterboxd.com/film/wu-ming-nu-hai/ | D83: Garota Sem Nome | E83: Wu ming nü hai | F83: Catálogo | G83: China + 1 país | H83: Ficção | I83: 128 | J83: 2026 | K83: China, França | L83: Ficção | M83: Sim | N83: Cannes | O83: Semana da Crítica – Competição | P83: Zou Jing | Q83: Zou Jing | R83: Eagle Media, Emei Film Group, Memoria Films, Maneki Films, Pure Light Films | S83: Wang Yang, Didar Domehri, Cao Xi | T83: Liang Zhongqiang | U83: Zou Jing, Tina Baz | V83: Valentin Hadjadj | W83: Li Gengxi, Shen Jiani, Zu Feng, Cao Ruofan | X83: Da infância à vida adulta, uma jovem chinesa passa por três famílias, recebendo a cada mudança um novo nome e uma nova identidade. Marcada pelo abandono e pela sensação de não pertencimento, ela busca seu lugar no mundo e a possibilidade de amar, enquanto tenta conciliar as feridas do passado com a incerteza do futuro. Ao acompanhar sua trajetória por diferentes lares e etapas da vida, o filme desenha um retrato íntimo sobre identidade, memória e a difícil construção de um lugar que se possa chamar de seu, ecoando as consequências da política do filho único da China. | Y83: Direção: Zou Jing | Roteiro: Zou Jing | Produtora: Eagle Media, Emei Film Group, Memoria Films, Maneki Films, Pure Light Films | Produção: Wang Yang, Didar Domehri, Cao Xi | Fotografia: Liang Zhongqiang | Montagem: Zou Jing, Tina Baz | Música: Valentin Hadjadj | Elenco: Li Gengxi, Shen Jiani, Zu Feng, Cao Ruofan | Z83: 3 | AA83: 2026 | AB83: Ficção
A84: 083 | B84: Expectativa | C84: ="https://" & "letterboxd" & ".com/film/yak-mai/" -> https://letterboxd.com/film/yak-mai/ | D84: Gigantes em Chamas | E84: Yak Mai | F84: Catálogo | G84: França + 3 países | H84: Ficção | I84: 118 | J84: 2026 | K84: Tailândia, Singapura, França, Países Baixos | L84: Ficção | P84: Putthipong Aaronpheng | Q84: Phuttiphong Aroonpheng | R84: Sluizer Film Productions, Diversion, 13 Little Pictures, Nord-Ouest Films | S84: Mai Meksawan, Bee Thiam Tan, Ola Byszuk, Anouk Sluizer | T84: Emo Weemhoff, Nsc | U84: Daniel Hui | V84: Christine Ott, Mathieu Gabry | W84: Awat Ratanapintha, Pakapol Srirongmuang, Waywiree Ittianunkul, Thanatwut Rodpai, Phunthida Phairuangkij, Teerawat Mulvilai, Gandhi Wasuvitchayagit | X84: Névoa tóxica misteriosa infecta o povo Karen nas montanhas da Tailândia, provocando graves lesões na pele. Fiscais florestais utilizam o surto como pretexto para incendiar os vilarejos, abrindo caminho para a criação de um parque nacional e deixando a comunidade desabrigada. Ao saber que um homem solitário da região foi capturado, uma migrante que trabalha como babá em Bangcoc abandona sua vida na cidade e leva a filha para buscar o marido desaparecido. Estreia mundial na mostra Orizzonti do Festival de Veneza (2026). | Y84: Direção: Putthipong Aaronpheng | Roteiro: Phuttiphong Aroonpheng | Produtora: Sluizer Film Productions, Diversion, 13 Little Pictures, Nord-Ouest Films | Produção: Mai Meksawan, Bee Thiam Tan, Ola Byszuk, Anouk Sluizer | Fotografia: Emo Weemhoff, Nsc | Montagem: Daniel Hui | Música: Christine Ott, Mathieu Gabry | Elenco: Awat Ratanapintha, Pakapol Srirongmuang, Waywiree Ittianunkul, Thanatwut Rodpai, Phunthida Phairuangkij, Teerawat Mulvilai, Gandhi Wasuvitchayagit | Z84: 3 | AA84: 2026 | AB84: Ficção
A85: 084 | B85: Expectativa | C85: https://letterboxd.com/film/guo-ran/ | D85: Guo Ran: Dias de Espera | E85: Guo Ran | F85: Catálogo | G85: China | H85: Ficção | I85: 87 | J85: 2025 | K85: China | L85: Ficção | P85: Li Dongmei | Q85: Li Dongmei | R85: Leopard Film | S85: Qi AI | T85: Matthias Delvaux | U85: Qin Yanan | W85: Rebecca Li, Roy Wang, Fengyi Xing | X85: Yu e o namorado são jovens profissionais que dividem um pequeno apartamento. Enquanto ela atravessa o início da gravidez, ele se refugia no trabalho e em outras distrações para evitar a crise silenciosa que se instala entre os dois. Em conversas breves, gestos cotidianos e momentos de solidão, o casal percebe que a expectativa de uma nova vida não basta para aproximá-los. Um drama íntimo sobre maternidade, identidade feminina e a fragilidade dos vínculos contemporâneos. Exibido na competição Tiger do Festival de Roterdã 2025. | Y85: Direção: Li Dongmei | Roteiro: Li Dongmei | Produtora: Leopard Film | Produção: Qi AI | Fotografia: Matthias Delvaux | Montagem: Qin Yanan | Elenco: Rebecca Li, Roy Wang, Fengyi Xing | Z85: 3 | AA85: 2025 | AB85: Ficção
A86: 085 | B86: Expectativa | C86: ="https://" & "letterboxd" & ".com/film/halima/" -> https://letterboxd.com/film/halima/ | D86: Halima | F86: Complementar / catálogo parcial | G86: Marrocos | H86: Ficção | I86: 85 | J86: 2026 | K86: Marrocos | L86: Ficção | P86: Yassine El Idrissi | Q86: Yassine El Idrissi | R86: Saffron Film Production | S86: Yassine El Idrissi, Rabii El Fikih | T86: Matteo de Angelis | U86: Yassine El Idrissi | W86: Abdlaziz Barioul, Achraf Tahiri, Benasser Amtaghri, Driss Assamadi, Khadija Amari, Mohcine Ghazali, Mustapha Chougane, Omar Beloud, Omar Hatim, Rabii El Fakih, Walid Wafi | X86: Halima, de 86 anos, vive de forma modesta à beira-mar coletando mexilhões com o marido. Sua rotina pacífica, contudo, esconde um segredo do passado. Anos antes, ela morava sozinha em uma casa isolada nas montanhas do Rif, no Marrocos. Quando um projeto ambiental exigiu a remoção dos moradores locais, Halima resistiu ferozmente para proteger as memórias do falecido primeiro marido. Mas a resistência ocultava uma verdade sombria: após a perda de seu gado e sem renda, ela passou a permitir que contrabandistas de haxixe usassem sua antiga casa como esconderijo. | Y86: Direção: Yassine El Idrissi | Roteiro: Yassine El Idrissi | Produtora: Saffron Film Production | Produção: Yassine El Idrissi, Rabii El Fikih | Fotografia: Matteo de Angelis | Montagem: Yassine El Idrissi | Elenco: Abdlaziz Barioul, Achraf Tahiri, Benasser Amtaghri, Driss Assamadi, Khadija Amari, Mohcine Ghazali, Mustapha Chougane, Omar Beloud, Omar Hatim, Rabii El Fakih, Walid Wafi | Z86: 3 | AA86: 2026 | AB86: Ficção
A87: 086 | B87: Expectativa | C87: https://letterboxd.com/film/identitti/ | D87: Identitti - Quem Você Pensa que É? | E87: Identitti | F87: Catálogo | G87: Alemanha | H87: Ficção | I87: 104 | J87: 2026 | K87: Alemanha | L87: Ficção | P87: Randa Chahoud | Q87: Friederike Jehn | R87: Razor Film, Zdf | S87: Gerhard Meixner, Roman Paul | T87: Friederike Jehn | U87: Andrew Bird | V87: Burak Özdemir | W87: Amanda Babaei Vieira, Stephanie Eidt, Sabrina Setlur, Zoe Magdalena, Saba Lou Khan, Anne Müller, Amir Nawfal, Mohamed Kanj Khamis | X87: Düsseldorf, 2019. Nivedita Anand, doutoranda alemã filha de pai indiano e mãe polonesa, descobre que Saraswati, sua celebrada professora de estudos pós-coloniais, é na verdade uma mulher branca que se apresenta como pessoa não branca. Quando a revelação explode nas redes sociais, a admiração dá lugar a um conflito político e íntimo. Entre apropriação cultural, cultura do cancelamento e pertencimento, Nivedita vê suas relações, convicções e a própria identidade colocadas em questão. Adaptação do romance de Mithu Sanyal. | Y87: Direção: Randa Chahoud | Roteiro: Friederike Jehn | Produtora: Razor Film, Zdf | Produção: Gerhard Meixner, Roman Paul | Fotografia: Friederike Jehn | Montagem: Andrew Bird | Música: Burak Özdemir | Elenco: Amanda Babaei Vieira, Stephanie Eidt, Sabrina Setlur, Zoe Magdalena, Saba Lou Khan, Anne Müller, Amir Nawfal, Mohamed Kanj Khamis | Z87: 3 | AA87: 2026 | AB87: Ficção
A88: 087 | B88: Expectativa | C88: ="https://" & "letterboxd" & ".com/film/in-waves-2026/" -> https://letterboxd.com/film/in-waves-2026/ | D88: In Waves | F88: Complementar / catálogo parcial | G88: Bélgica + 1 país | H88: Ficção | I88: 91 | J88: 2026 | K88: Bélgica, França | L88: Ficção | M88: Sim | N88: Cannes | O88: Semana da Crítica – Competição | P88: Phuong Mai Nguyen | Q88: Fanny Burdino, Samuel Doux | R88: Silex Films | S88: Priscilla Bertin, Judith Nora, Nick Shumaker | U88: Roberto Fernandez | V88: Oklou & Rob | W88: Stephanie Hsu, Will Sharpe | X88: Na ensolarada Los Angeles, o tímido AJ conhece Kristen. Ela vive para o surfe; ele, para o skate e o desenho. A paixão entre os dois parece anunciar um futuro feliz, até que uma doença repentina muda o rumo de suas vidas. Amparados pelos amigos, pelo amor e pela ligação que constroem com o oceano, enfrentam juntos a adversidade. Adaptada do romance gráfico autobiográfico de AJ Dungo, o filme foi a primeira animação a abrir a Semana da Crítica do Festival de Cannes. | Y88: Direção: Phuong Mai Nguyen | Roteiro: Fanny Burdino, Samuel Doux | Produtora: Silex Films | Produção: Priscilla Bertin, Judith Nora, Nick Shumaker | Montagem: Roberto Fernandez | Música: Oklou & Rob | Elenco: Stephanie Hsu, Will Sharpe | Z88: 3 | AA88: 2026 | AB88: Ficção
A89: 088 | B89: Expectativa | C89: https://letterboxd.com/film/ivan-hadoum/ | D89: Iván & Hadoum | F89: Complementar / catálogo parcial | G89: Espanha + 2 países | H89: Ficção | I89: 100 | J89: 2026 | K89: Espanha, Alemanha, Bélgica | L89: Ficção | P89: Ian de la Rosa | Q89: Ian de la Rosa | R89: Avalon, Pecado, Vayolet Films | S89: Stefan Schmitz, Emilia Fort, Jose Alba, Odile-Antonio Baez, Carlotta Schiavon | T89: Beatriz Sastre | U89: Yannick Leroy | V89: David Ferral | W89: Cisco Lara, Esperanza Guardado, Hadoum Benghnidira, Herminia Loh, Hugo Rodríguez, Nicolás Montoya, Silver Chicón, Úrsula Díaz | X89: Nos vastos campos de estufas de tomates do sul da Espanha, Iván, um homem trans, apaixona-se por Hadoum, sua nova colega de origem marroquina. Mas, quando Iván recebe a promoção que esperava e se torna supervisor de Hadoum, a paixão entra em choque com o poder, a classe e o preconceito. Dividido entre a ambição e a solidariedade, Iván precisa decidir que tipo de homem deseja ser — e o que está disposto a sacrificar. Vencedor do Teddy de Melhor Longa-Metragem no Festival de Berlim 2026. | Y89: Direção: Ian de la Rosa | Roteiro: Ian de la Rosa | Produtora: Avalon, Pecado, Vayolet Films | Produção: Stefan Schmitz, Emilia Fort, Jose Alba, Odile-Antonio Baez, Carlotta Schiavon | Fotografia: Beatriz Sastre | Montagem: Yannick Leroy | Música: David Ferral | Elenco: Cisco Lara, Esperanza Guardado, Hadoum Benghnidira, Herminia Loh, Hugo Rodríguez, Nicolás Montoya, Silver Chicón, Úrsula Díaz | Z89: 3 | AA89: 2026 | AB89: Ficção
A90: 089 | B90: Expectativa | C90: https://letterboxd.com/film/lady-2026/ | D90: Lady | F90: Complementar / catálogo parcial | G90: Nigéria + 1 país | H90: Ficção | I90: 93 | J90: 2026 | K90: Nigéria, Reino Unido | L90: Ficção | M90: Sim | N90: Sundance | O90: World Cinema Dramatic Competition | P90: Olive Nwosu | Q90: Olive Nwosu | R90: Ossian International | S90: Alex Pulonin, John Giwa-Amu, Stella Nwimo | T90: Alana Mejia Gonzalez | U90: Coline Monie, Gareth C Scales | V90: Ollie Mayo | W90: Jessica Gabriel’s Ujah, Amanda Oruh, Tinuade Jemiseye Binta Ayo Mogaji, Bucci Franklin | X90: Uma das poucas taxistas de Lagos, na Nigéria, a independente Lady economiza cada centavo para tentar construir uma vida longe do caos da cidade. Quando Pinky, amiga de infância que trabalha como profissional do sexo, reaparece em sua vida e lhe oferece emprego como motorista de um grupo de mulheres pelas noites da cidade, Lady aceita com relutância. O julgamento inicial que faz em relação ao grupo vai aos poucos dando lugar a uma sororidade intensa e afetuosa, que a conduz ao perigo e a uma nova ideia de liberdade. Prêmio Especial do Júri para o Elenco em Sundance 2026. | Y90: Direção: Olive Nwosu | Roteiro: Olive Nwosu | Produtora: Ossian International | Produção: Alex Pulonin, John Giwa-Amu, Stella Nwimo | Fotografia: Alana Mejia Gonzalez | Montagem: Coline Monie, Gareth C Scales | Música: Ollie Mayo | Elenco: Jessica Gabriel’s Ujah, Amanda Oruh, Tinuade Jemiseye Binta Ayo Mogaji, Bucci Franklin | Z90: 3 | AA90: 2026 | AB90: Ficção
A91: 090 | B91: Expectativa | C91: https://letterboxd.com/film/lali/ | D91: Lali: Entre os Vivos e os Mortos | E91: Lali | F91: Catálogo | G91: Paquistão | H91: Ficção | I91: 116 | J91: 2026 | K91: Paquistão | L91: Ficção | P91: Sarmad Sultan Khoosat | Q91: Sarmad Sultan Khoosat, Sundus Hashmi | R91: Khoosat Films | S91: Kanwal Khoosat P | T91: Khizer Idrees | U91: Saim Sadiq | V91: Abdullah Siddiqui | W91: Mamya Shajaffar, Channan Hanif, Rasti Farooq, Farazeh Syed, Mehar Bano | X91: Nos bairros populares de Sahiwal, Zeba e Sajawal se casam carregando feridas que não cicatrizaram. Ele vive atormentado pela insegurança e pelo medo de não corresponder às expectativas de masculinidade; ela é perseguida pela fama de trazer má sorte aos homens que ama. Entre desejo, superstição e presságios, a união assume contornos cada vez mais inquietantes, num mundo em que os mortos convivem com os vivos e o amor pode se confundir com obsessão. Exibido na mostra Panorama do Festival de Berlim 2026. | Y91: Direção: Sarmad Sultan Khoosat | Roteiro: Sarmad Sultan Khoosat, Sundus Hashmi | Produtora: Khoosat Films | Produção: Kanwal Khoosat P | Fotografia: Khizer Idrees | Montagem: Saim Sadiq | Música: Abdullah Siddiqui | Elenco: Mamya Shajaffar, Channan Hanif, Rasti Farooq, Farazeh Syed, Mehar Bano | Z91: 5 | AA91: 2026 | AB91: Ficção
A92: 091 | B92: Expectativa | C92: https://letterboxd.com/film/uhlanjululo/ | D92: Lavanderia | E92: Uhlanjululo | F92: Catálogo | G92: África do Sul + 1 país | H92: Ficção | I92: 106 | J92: 2025 | K92: África do Sul, Suíça | L92: Ficção | P92: Zamo Mkhwanazi | Q92: Zamo Mkhwanazi | R92: Kude Media, Akka Films | S92: Philippe Coeytaux, Zamo Mkhwanazi, Jim Stark | U92: Christine Hoffet | V92: Tracy September | W92: Tracy September, Ntobeko Sishi, Zekhethelo Zondi, Siyabonga Shibe, Bukamina Cebekhulu | X92: Johannesburgo, 1968. Khuthala, um jovem músico, sonha em viajar pelo mundo, mas a família espera que ele assuma a lavanderia mantida em um bairro reservado a brancos. Quando as leis do apartheid ameaçam o negócio e a segurança de todos, ele se vê dividido entre a liberdade que busca e a responsabilidade de proteger a única fonte de sustento da casa. Inspirado na história familiar da diretora, o drama observa como a opressão transforma sonhos, dever e lealdade em escolhas impossíveis. Exibido no Festival de Toronto 2025. | Y92: Direção: Zamo Mkhwanazi | Roteiro: Zamo Mkhwanazi | Produtora: Kude Media, Akka Films | Produção: Philippe Coeytaux, Zamo Mkhwanazi, Jim Stark | Montagem: Christine Hoffet | Música: Tracy September | Elenco: Tracy September, Ntobeko Sishi, Zekhethelo Zondi, Siyabonga Shibe, Bukamina Cebekhulu | Z92: 3 | AA92: 2025 | AB92: Ficção
A93: 092 | B93: Expectativa | C93: https://letterboxd.com/film/truly-naked/ | D93: Literalmente Nu | E93: Truly Naked | F93: Catálogo | G93: Bélgica + 2 países | H93: Ficção | I93: 102 | J93: 2026 | K93: Países Baixos, Bélgica, França | L93: Ficção | P93: Muriel D’ansembourg | Q93: Muriel D'ansembourg | R93: Isabella Films | S93: Els Vandevorst, Isabella Depeweg | T93: Myrthe Mosterman | U93: Emiel Nuninga | V93: Evgueni, Sacha Galperine | W93: Caolán O’gorman, Andrew Howard, Alessa Savage, Safiya Benaddi | X93: O introvertido Alec cresceu num universo familiar imerso no pequeno negócio de pornografia do pai, enxergando a vida e a sexualidade através da câmera. Quando os dois deixam Londres e se mudam para uma tranquila cidade litorânea, ele espera recomeçar a adolescência e o círculo de amizades sem revelar sua vida familiar pouco convencional. Mas o encontro com a independente Nina desafia tudo o que Alec sabe sobre desejo, vulnerabilidade e o que significa ser verdadeiramente visto. Estreia mundial na seção Perspectives do Festival de Berlim 2026. | Y93: Direção: Muriel D’ansembourg | Roteiro: Muriel D'ansembourg | Produtora: Isabella Films | Produção: Els Vandevorst, Isabella Depeweg | Fotografia: Myrthe Mosterman | Montagem: Emiel Nuninga | Música: Evgueni, Sacha Galperine | Elenco: Caolán O’gorman, Andrew Howard, Alessa Savage, Safiya Benaddi | Z93: 5 | AA93: 2026 | AB93: Ficção
A94: 093 | B94: Expectativa | C94: ="https://" & "letterboxd" & ".com/film/le-triangle-dor/" -> https://letterboxd.com/film/le-triangle-dor/ | D94: Madame | E94: Triangle d’or, Le | F94: Catálogo | G94: Bélgica + 2 países | H94: Ficção | I94: 90 | J94: 2026 | K94: Bélgica, Canadá, França | L94: Ficção | M94: Sim | N94: Cannes | O94: Sessão Especial | P94: Hélène Rosselet-Ruiz | Q94: Hélène Rosselet-Ruiz, Pauline Guéna | R94: Les Films de Pierre | S94: Nicolas Leclere | T94: David Chambille | U94: Suzana Pedro | V94: Dom la Nena | W94: Malou Khebizi, Soundos Mosbah, Ziad Bakri, Kassem Al Khoja | X94: Para garantir a sobrevivência, Laura aceita trabalhar para Souria em uma mansão no Triângulo Dourado de Paris. Instalada ali por seu amante, um rico príncipe saudita, Souria vive à espera de visitas dele. Enquanto Laura tenta se adaptar ao mundo de luxo extravagante e vigilância constante da casa, uma frágil ligação nasce entre as duas. Mas ela logo percebe que Souria corre perigo — e que a gaiola dourada pode estar se fechando sobre ambas. Estreia mundial nas Sessões Especiais de Cannes 2026. | Y94: Direção: Hélène Rosselet-Ruiz | Roteiro: Hélène Rosselet-Ruiz, Pauline Guéna | Produtora: Les Films de Pierre | Produção: Nicolas Leclere | Fotografia: David Chambille | Montagem: Suzana Pedro | Música: Dom la Nena | Elenco: Malou Khebizi, Soundos Mosbah, Ziad Bakri, Kassem Al Khoja | Z94: 3 | AA94: 2026 | AB94: Ficção
A95: 094 | B95: Expectativa | C95: ="https://" & "letterboxd" & ".com/film/maria-vitoria/" -> https://letterboxd.com/film/maria-vitoria/ | D95: Maria Vitória | F95: Complementar / catálogo parcial | G95: Portugal | H95: Ficção | I95: 114 | J95: 2025 | K95: Portugal | L95: Ficção | P95: Mário Patrocínio | Q95: Mário Patrocínio | R95: Apm – Actions Per Minute | S95: Ana Pinhão Moura | T95: Pedro J. Márquez | U95: Cláudia Silvestre | V95: Edgar Valente, Bernardo D’addario | W95: Mariana Cardoso, Miguel Borges, Miguel Nunes | X95: Em uma aldeia remota, a jovem Maria Vitória joga em um time juvenil masculino e treina arduamente com o seu pai, Nacho, focada em tornar-se goleira de futebol profissional. O frágil equilíbrio dessa rotina desaba com o regresso inesperado de seu irmão mais velho, Bruno, que havia partido após o incêndio trágico que vitimou a mãe deles. Às vésperas da partida mais crucial da sua vida, Maria passa a confrontar a autoridade do pai, iniciando uma jornada intensa e poética de autodescoberta e libertação das sombras e do luto do passado. | Y95: Direção: Mário Patrocínio | Roteiro: Mário Patrocínio | Produtora: Apm – Actions Per Minute | Produção: Ana Pinhão Moura | Fotografia: Pedro J. Márquez | Montagem: Cláudia Silvestre | Música: Edgar Valente, Bernardo D’addario | Elenco: Mariana Cardoso, Miguel Borges, Miguel Nunes | Z95: 3 | AA95: 2025 | AB95: Ficção
A96: 095 | B96: Expectativa | C96: https://letterboxd.com/film/marie-madeleine/ | D96: Marie Madeleine, uma mulher livre | E96: Marie Madeleine | F96: Catálogo | G96: Haiti + 4 países | H96: Ficção | I96: 103 | J96: 2026 | K96: Haiti, França, Bélgica, Canadá, Luxemburgo | L96: Ficção | M96: Sim | N96: Cannes | O96: Cannes Première | P96: Gessica Généus | Q96: Géssica Généus | R96: Ayizan Productions, Sanosi Productions, Stenola Productions, Bidibul Productions, Metafilms | S96: Jean-Marie Gigon, Géssica Généus, Anton Iffland-Stettner, Eva Kuperman, Lilian Eche, Christel Henon, Sylvain Corbeil | T96: Nicolas Canniccioni | U96: Martial Salomon | W96: Géssica Généus, Béonard Monteau, Mélissa Moldort, Ginou Jules, Luchue Mesidor, Gaëlle Bien-Aimé, Edouard Baptiste | X96: Na cidade de Jacmel, no Haiti, a prostituta Marie Madeleine vive de forma totalmente livre e marginalizada pelas regras rígidas da sociedade. Quando seus caminhos se cruzam com os de Joseph, um jovem e fervoroso crente evangélico, um laço profundamente intenso e improvável surge entre eles. À medida que a fé inabalável dele começa a vacilar, ela o atrai gradualmente para um universo de desejo, liberdade absoluta e reinvenção pessoal. Exibido no Festival de Cannes 2026 na seção Cannes Première. | Y96: Direção: Gessica Généus | Roteiro: Géssica Généus | Produtora: Ayizan Productions, Sanosi Productions, Stenola Productions, Bidibul Productions, Metafilms | Produção: Jean-Marie Gigon, Géssica Généus, Anton Iffland-Stettner, Eva Kuperman, Lilian Eche, Christel Henon, Sylvain Corbeil | Fotografia: Nicolas Canniccioni | Montagem: Martial Salomon | Elenco: Géssica Généus, Béonard Monteau, Mélissa Moldort, Ginou Jules, Luchue Mesidor, Gaëlle Bien-Aimé, Edouard Baptiste | Z96: 3 | AA96: 2026 | AB96: Ficção
A97: 096 | B97: Expectativa | C97: ="https://" & "letterboxd" & ".com/film/mata-2026/" -> https://letterboxd.com/film/mata-2026/ | D97: Mata | F97: Complementar / catálogo parcial | G97: França | H97: Ficção | I97: 99 | J97: 2026 | K97: França | L97: Ficção | P97: Rachel Lang | Q97: Rachel Lang | R97: Nolita, Chevaldeuxtrois | S97: Jérémy Forni, Maxime Delaunay | T97: Romain Lacoursbas | U97: Sophie Vercruysse, Matthieu Jamet-Louis | V97: Yuksek | W97: Raphaël Personnaz, Eye Haidara, Joséphine Japy, Mélanie Laurent | X97: Ferida durante uma operação clandestina no Níger, a agente secreta francesa Mata perde o contato com o colega Antoine, capturado na emboscada. De volta à França, ela assume uma missão de contraespionagem nos Alpes e percebe indícios de uma ligação entre o novo caso e o trauma vivido na África. Assombrada pelo cativeiro de Antoine e convencida de que seus superiores escondem informações, Mata inicia uma corrida contra o tempo à margem de qualquer protocolo, arriscando perder tudo. | Y97: Direção: Rachel Lang | Roteiro: Rachel Lang | Produtora: Nolita, Chevaldeuxtrois | Produção: Jérémy Forni, Maxime Delaunay | Fotografia: Romain Lacoursbas | Montagem: Sophie Vercruysse, Matthieu Jamet-Louis | Música: Yuksek | Elenco: Raphaël Personnaz, Eye Haidara, Joséphine Japy, Mélanie Laurent | Z97: 3 | AA97: 2026 | AB97: Ficção
A98: 097 | B98: Expectativa | C98: ="https://" & "letterboxd" & ".com/film/memoire-de-fille/" -> https://letterboxd.com/film/memoire-de-fille/ | D98: Memória de Menina | E98: Mémoire de Fille | F98: Catálogo | G98: França | H98: Ficção | I98: 117 | J98: 2026 | K98: França | L98: Ficção | M98: Sim | N98: Cannes | O98: Un Certain Regard | P98: Judith Godrèche | Q98: Judith Godrèche | R98: Moana Films, Windy Production | S98: Carole Lambert, Marc Missonnier | T98: Joachim Philippe | U98: Guillaume Lauras | V98: Faux Amis | W98: Tess Barthélemy, Valérie Dréville, Victor Bonnel, Ariane Labed, Maïwène Barthélémy, Anja Verderosa, Louise Labèque, Manon Valentin, Esther Archambault, Mamadou Sidibé, Thibault Bonenfant, Lancelot Courcieras, François-Xavier Raffier, Léa Leviant, Guslagie Malanda | X98: A caminho de Rouen para uma sessão de autógrafos, Annie Ernaux é tomada por uma vertigem que a transporta ao verão de 1958, quando, aos 18 anos, viveu a primeira experiência sexual. Décadas depois, ela revisita a jovem que um dia foi e aquela noite cuja marca atravessaria toda a sua vida. A diretora Judith Godrèche adapta o bestseller autobiográfico da vencedora do Nobel em um filme sobre desejo, vergonha, dominação e os caminhos da memória. Exibido na mostra Un Certain Regard do Festival de Cannes 2026. | Y98: Direção: Judith Godrèche | Roteiro: Judith Godrèche | Produtora: Moana Films, Windy Production | Produção: Carole Lambert, Marc Missonnier | Fotografia: Joachim Philippe | Montagem: Guillaume Lauras | Música: Faux Amis | Elenco: Tess Barthélemy, Valérie Dréville, Victor Bonnel, Ariane Labed, Maïwène Barthélémy, Anja Verderosa, Louise Labèque, Manon Valentin, Esther Archambault, Mamadou Sidibé, Thibault Bonenfant, Lancelot Courcieras, François-Xavier Raffier, Léa Leviant, Guslagie Malanda | Z98: 3 | AA98: 2026 | AB98: Ficção
A99: 098 | B99: Expectativa | C99: https://letterboxd.com/film/the-mad-dog-of-europe/ | D99: O Cachorro Louco da Europa | E99: Mad Dog of Europe, The | F99: Catálogo | G99: França + 1 país | H99: Documentário | I99: 80 | J99: 2025 | K99: França, Alemanha | L99: Documentário | P99: Rubika Shah | Q99: Rubika Shah | R99: Le Bureau Films, Heimatfilm | S99: Bertrand Faivre, Bettina Brokemper | T99: Janis Mazuch | V99: Aisling Brouwer | W99: Sydney Stern, Nick Davis, Steven J.ross, Ben Mankiewicz, Thomas Doherty | X99: Em 1932, Herman J. Mankiewicz, futuro roteirista de Cidadão Kane, escreveu O Cachorro Louco da Europa, um roteiro visionário sobre a ascensão de Hitler e a perseguição aos judeus. Temendo pressões diplomáticas e a perda do mercado alemão, Hollywood enterrou o projeto. Ao investigar a história desse filme jamais realizado, o documentário revela a influência nazista sobre os estúdios e questiona a responsabilidade do cinema diante do avanço do autoritarismo. | Y99: Direção: Rubika Shah | Roteiro: Rubika Shah | Produtora: Le Bureau Films, Heimatfilm | Produção: Bertrand Faivre, Bettina Brokemper | Fotografia: Janis Mazuch | Música: Aisling Brouwer | Elenco: Sydney Stern, Nick Davis, Steven J.ross, Ben Mankiewicz, Thomas Doherty | Z99: 3 | AA99: 2025 | AB99: Documentário
A100: 099 | B100: Expectativa | C100: https://letterboxd.com/film/cinlerin-dugunu/ | D100: O Casamento de Djinn | E100: Cinlerin Dügünü | F100: Catálogo | G100: Turquia | H100: Ficção | I100: 133 | J100: 2026 | K100: Turquia | L100: Ficção | P100: Ferit Karahan | Q100: Ferit Karahan | R100: Ferit Karahan Films | S100: Berkin Kaya, Kanat Doğramaci, Gülistan Acet Karahan, Ferit Karahan | T100: Serdar Özdemir | U100: Ferit Karahan, Marco Spoletini, Ahmet Boyacioğlu, Yusuf Ziya Kaya, Mustafa Umut Ay | V100: Noyan Coşarer | W100: Demet Özdemir, Kaan Yildirim, Sarp Bozkurt, İlhan Şen | X100: Quatro irmãos afastados voltam a uma remota aldeia na Anatólia para o casamento da irmã, Ceren. Conforme a celebração avança, segredos que foram guardados por gerações e outras lembranças apagadas começam a ressurgir, revelando uma maldição que paira sobre a casa ilegal onde vivem. O drama aborda o luto, o destino e a desintegração familiar. Selecionado para a mostra Platform no Festival de Toronto (TIFF) 2026. | Y100: Direção: Ferit Karahan | Roteiro: Ferit Karahan | Produtora: Ferit Karahan Films | Produção: Berkin Kaya, Kanat Doğramaci, Gülistan Acet Karahan, Ferit Karahan | Fotografia: Serdar Özdemir | Montagem: Ferit Karahan, Marco Spoletini, Ahmet Boyacioğlu, Yusuf Ziya Kaya, Mustafa Umut Ay | Música: Noyan Coşarer | Elenco: Demet Özdemir, Kaan Yildirim, Sarp Bozkurt, İlhan Şen | Z100: 3 | AA100: 2026 | AB100: Ficção
...

Sheet Sessões
A1: Data | B1: Dia | C1: Horário | D1: Mostra | E1: ID | F1: Filme | G1: Cinema | H1: Endereço | I1: Sala | J1: Observações | K1: Gratuita | L1: Com convidado | M1: Com debate
A2: 46301 | B2: Ter | C2: 0.8125 | D2: Panorama Mundial | E2: {=_xlfn.XLOOKUP(F2, Filmes!$D$2:$D$344, Filmes!$A$2:$A$344, "")} -> 001 | F2: A Grande Estreia | G2: Cine Odeon - CCLSR | H2: Praça Floriano, 7
A3: 46303 | B3: Qui | C3: 0.58333333 | D3: Panorama Mundial | E3: {=_xlfn.XLOOKUP(F3, Filmes!$D$2:$D$344, Filmes!$A$2:$A$344, "")} -> 001 | F3: A Grande Estreia | G3: Kinoplex São Luiz | H3: Rua do Catete, 311 - Catete | I3: 2
A4: 46305 | B4: Sáb | C4: 0.90625 | D4: Panorama Mundial | E4: {=_xlfn.XLOOKUP(F4, Filmes!$D$2:$D$344, Filmes!$A$2:$A$344, "")} -> 001 | F4: A Grande Estreia | G4: Estação Claro Gávea | H4: Rua Marquês de São Vicente, 52 | I4: 5
A5: 46296 | B5: Qui | C5: 0.6875 | D5: Panorama Mundial | E5: {=_xlfn.XLOOKUP(F5, Filmes!$D$2:$D$344, Filmes!$A$2:$A$344, "")} -> 002 | F5: A Noiva Difícil | G5: Cinesystem Belas Artes Botafogo | H5: Praia de Botafogo, 316 | I5: 1
A6: 46300 | B6: Seg | C6: 0.83333333 | D6: Panorama Mundial | E6: {=_xlfn.XLOOKUP(F6, Filmes!$D$2:$D$344, Filmes!$A$2:$A$344, "")} -> 002 | F6: A Noiva Difícil | G6: CineCarioca José Wilker | H6: Rua Leite Leal, 45 | I6: 1
A7: 46305 | B7: Sáb | C7: 0.58333333 | D7: Panorama Mundial | E7: {=_xlfn.XLOOKUP(F7, Filmes!$D$2:$D$344, Filmes!$A$2:$A$344, "")} -> 002 | F7: A Noiva Difícil | G7: Estação Claro Gávea | H7: Rua Marquês de São Vicente, 52 | I7: 1
A8: 46297 | B8: Sex | C8: 0.59375 | D8: Panorama Mundial | E8: {=_xlfn.XLOOKUP(F8, Filmes!$D$2:$D$344, Filmes!$A$2:$A$344, "")} -> 003 | F8: A Terceira Noite | G8: Cinesystem Belas Artes Botafogo | H8: Praia de Botafogo, 316 | I8: 6
A9: 46299 | B9: Dom | C9: 0.79166667 | D9: Panorama Mundial | E9: {=_xlfn.XLOOKUP(F9, Filmes!$D$2:$D$344, Filmes!$A$2:$A$344, "")} -> 003 | F9: A Terceira Noite | G9: Reserva Cultural Niterói | H9: Av. Visconde do Rio Branco, 880 | I9: 1
A10: 46300 | B10: Seg | C10: 0.70833333 | D10: Panorama Mundial | E10: {=_xlfn.XLOOKUP(F10, Filmes!$D$2:$D$344, Filmes!$A$2:$A$344, "")} -> 003 | F10: A Terceira Noite | G10: Estação Claro Gávea | H10: Rua Marquês de São Vicente, 52 | I10: 5
A11: 46305 | B11: Sáb | C11: 0.66666667 | D11: Panorama Mundial | E11: {=_xlfn.XLOOKUP(F11, Filmes!$D$2:$D$344, Filmes!$A$2:$A$344, "")} -> 004 | F11: Amazomania | G11: Cinesystem Belas Artes Botafogo | H11: Praia de Botafogo, 316 | I11: 6 | L11: Sim | M11: Sim
A12: 46308 | B12: Ter | C12: 0.58333333 | D12: Panorama Mundial | E12: {=_xlfn.XLOOKUP(F12, Filmes!$D$2:$D$344, Filmes!$A$2:$A$344, "")} -> 004 | F12: Amazomania | G12: Estação Claro Rio | H12: Rua Voluntários da Pátria, 35 | I12: 3
A13: 46297 | B13: Sex | C13: 0.88541667 | D13: Panorama Mundial | E13: {=_xlfn.XLOOKUP(F13, Filmes!$D$2:$D$344, Filmes!$A$2:$A$344, "")} -> 005 | F13: As Crianças Estão Bem | G13: Reserva Cultural Niterói | H13: Av. Visconde do Rio Branco, 880 | I13: 1
A14: 46298 | B14: Sáb | C14: 0.66666667 | D14: Panorama Mundial | E14: {=_xlfn.XLOOKUP(F14, Filmes!$D$2:$D$344, Filmes!$A$2:$A$344, "")} -> 005 | F14: As Crianças Estão Bem | G14: Cine Santa Teresa | H14: Rua Paschoal Carlos Magno, 136
A15: 46300 | B15: Seg | C15: 0.59375 | D15: Panorama Mundial | E15: {=_xlfn.XLOOKUP(F15, Filmes!$D$2:$D$344, Filmes!$A$2:$A$344, "")} -> 005 | F15: As Crianças Estão Bem | G15: Cinesystem Belas Artes Botafogo | H15: Praia de Botafogo, 316 | I15: 6
A16: 46304 | B16: Sex | C16: 0.79166667 | D16: Panorama Mundial | E16: {=_xlfn.XLOOKUP(F16, Filmes!$D$2:$D$344, Filmes!$A$2:$A$344, "")} -> 005 | F16: As Crianças Estão Bem | G16: Kinoplex São Luiz | H16: Rua do Catete, 311 - Catete | I16: 2
A17: 46307 | B17: Seg | C17: 0.69791667 | D17: Panorama Mundial | E17: {=_xlfn.XLOOKUP(F17, Filmes!$D$2:$D$344, Filmes!$A$2:$A$344, "")} -> 005 | F17: As Crianças Estão Bem | G17: Estação Claro Gávea | H17: Rua Marquês de São Vicente, 52 | I17: 5
A18: 46303 | B18: Qui | C18: 0.79166667 | D18: Panorama Mundial | E18: {=_xlfn.XLOOKUP(F18, Filmes!$D$2:$D$344, Filmes!$A$2:$A$344, "")} -> 006 | F18: Bucking Fastard | G18: Cinesystem Belas Artes Botafogo | H18: Praia de Botafogo, 316 | I18: 4
A19: 46304 | B19: Sex | C19: 0.59375 | D19: Panorama Mundial | E19: {=_xlfn.XLOOKUP(F19, Filmes!$D$2:$D$344, Filmes!$A$2:$A$344, "")} -> 006 | F19: Bucking Fastard | G19: Estação Claro Rio | H19: Rua Voluntários da Pátria, 35 | I19: 4
A20: 46308 | B20: Ter | C20: 0.90625 | D20: Panorama Mundial | E20: {=_xlfn.XLOOKUP(F20, Filmes!$D$2:$D$344, Filmes!$A$2:$A$344, "")} -> 006 | F20: Bucking Fastard | G20: Estação Claro Gávea | H20: Rua Marquês de São Vicente, 52 | I20: 5
A21: 46298 | B21: Sáb | C21: 0.89583333 | D21: Panorama Mundial | E21: {=_xlfn.XLOOKUP(F21, Filmes!$D$2:$D$344, Filmes!$A$2:$A$344, "")} -> 007 | F21: Cartas Amarelas | G21: Cinesystem Belas Artes Botafogo | H21: Praia de Botafogo, 316 | I21: 6
A22: 46302 | B22: Qua | C22: 0.69791667 | D22: Panorama Mundial | E22: {=_xlfn.XLOOKUP(F22, Filmes!$D$2:$D$344, Filmes!$A$2:$A$344, "")} -> 007 | F22: Cartas Amarelas | G22: Estação Claro Gávea | H22: Rua Marquês de São Vicente, 52 | I22: 5
A23: 46305 | B23: Sáb | C23: 0.79166667 | D23: Panorama Mundial | E23: {=_xlfn.XLOOKUP(F23, Filmes!$D$2:$D$344, Filmes!$A$2:$A$344, "")} -> 007 | F23: Cartas Amarelas | G23: Kinoplex São Luiz | H23: Rua do Catete, 311 - Catete | I23: 2
A24: 46297 | B24: Sex | C24: 0.80208333 | D24: Panorama Mundial | E24: {=_xlfn.XLOOKUP(F24, Filmes!$D$2:$D$344, Filmes!$A$2:$A$344, "")} -> 008 | F24: Cavalo Selvagem Nove | G24: Cinesystem Belas Artes Botafogo | H24: Praia de Botafogo, 316 | I24: 6 | J24: Sessão especial
A25: 46300 | B25: Seg | C25: 0.58333333 | D25: Panorama Mundial | E25: {=_xlfn.XLOOKUP(F25, Filmes!$D$2:$D$344, Filmes!$A$2:$A$344, "")} -> 008 | F25: Cavalo Selvagem Nove | G25: Estação Claro Rio | H25: Rua Voluntários da Pátria, 35 | I25: 5
A26: 46302 | B26: Qua | C26: 0.88541667 | D26: Panorama Mundial | E26: {=_xlfn.XLOOKUP(F26, Filmes!$D$2:$D$344, Filmes!$A$2:$A$344, "")} -> 008 | F26: Cavalo Selvagem Nove | G26: Reserva Cultural Niterói | H26: Av. Visconde do Rio Branco, 880 | I26: 1
A27: 46304 | B27: Sex | C27: 0.6875 | D27: Panorama Mundial | E27: {=_xlfn.XLOOKUP(F27, Filmes!$D$2:$D$344, Filmes!$A$2:$A$344, "")} -> 008 | F27: Cavalo Selvagem Nove | G27: Kinoplex São Luiz | H27: Rua do Catete, 311 - Catete | I27: 2
A28: 46308 | B28: Ter | C28: 0.80208333 | D28: Panorama Mundial | E28: {=_xlfn.XLOOKUP(F28, Filmes!$D$2:$D$344, Filmes!$A$2:$A$344, "")} -> 008 | F28: Cavalo Selvagem Nove | G28: Estação Claro Gávea | H28: Rua Marquês de São Vicente, 52 | I28: 5
A29: 46296 | B29: Qui | C29: 0.90625 | D29: Panorama Mundial | E29: {=_xlfn.XLOOKUP(F29, Filmes!$D$2:$D$344, Filmes!$A$2:$A$344, "")} -> 009 | F29: Cidadão Osama | G29: Estação Claro Gávea | H29: Rua Marquês de São Vicente, 52 | I29: 5
A30: 46301 | B30: Ter | C30: 0.58333333 | D30: Panorama Mundial | E30: {=_xlfn.XLOOKUP(F30, Filmes!$D$2:$D$344, Filmes!$A$2:$A$344, "")} -> 009 | F30: Cidadão Osama | G30: Kinoplex São Luiz | H30: Rua do Catete, 311 - Catete | I30: 2
A31: 46304 | B31: Sex | C31: 0.69791667 | D31: Panorama Mundial | E31: {=_xlfn.XLOOKUP(F31, Filmes!$D$2:$D$344, Filmes!$A$2:$A$344, "")} -> 009 | F31: Cidadão Osama | G31: Cinesystem Belas Artes Botafogo | H31: Praia de Botafogo, 316 | I31: 6
A32: 46297 | B32: Sex | C32: 0.79166667 | D32: Panorama Mundial | E32: {=_xlfn.XLOOKUP(F32, Filmes!$D$2:$D$344, Filmes!$A$2:$A$344, "")} -> 010 | F32: Contos Paralelos | G32: Cine Odeon - CCLSR | H32: Praça Floriano, 7 | L32: Sim
A33: 46298 | B33: Sáb | C33: 0.77083333 | D33: Panorama Mundial | E33: {=_xlfn.XLOOKUP(F33, Filmes!$D$2:$D$344, Filmes!$A$2:$A$344, "")} -> 010 | F33: Contos Paralelos | G33: Reserva Cultural Niterói | H33: Av. Visconde do Rio Branco, 880 | I33: 1 | L33: Sim
A34: 46299 | B34: Dom | C34: 0.88541667 | D34: Panorama Mundial | E34: {=_xlfn.XLOOKUP(F34, Filmes!$D$2:$D$344, Filmes!$A$2:$A$344, "")} -> 010 | F34: Contos Paralelos | G34: Kinoplex São Luiz | H34: Rua do Catete, 311 - Catete | I34: 2
A35: 46301 | B35: Ter | C35: 0.66666667 | D35: Panorama Mundial | E35: {=_xlfn.XLOOKUP(F35, Filmes!$D$2:$D$344, Filmes!$A$2:$A$344, "")} -> 010 | F35: Contos Paralelos | G35: Estação Claro Gávea | H35: Rua Marquês de São Vicente, 52 | I35: 3
A36: 46296 | B36: Qui | C36: 0.79166667 | D36: Panorama Mundial | E36: {=_xlfn.XLOOKUP(F36, Filmes!$D$2:$D$344, Filmes!$A$2:$A$344, "")} -> 011 | F36: Conversa com o Mar | G36: Estação Claro Rio | H36: Rua Voluntários da Pátria, 35 | I36: 5
A37: 46297 | B37: Sex | C37: 0.69791667 | D37: Panorama Mundial | E37: {=_xlfn.XLOOKUP(F37, Filmes!$D$2:$D$344, Filmes!$A$2:$A$344, "")} -> 011 | F37: Conversa com o Mar | G37: Cinesystem Belas Artes Botafogo | H37: Praia de Botafogo, 316 | I37: 6
A38: 46306 | B38: Dom | C38: 0.57291667 | D38: Panorama Mundial | E38: {=_xlfn.XLOOKUP(F38, Filmes!$D$2:$D$344, Filmes!$A$2:$A$344, "")} -> 011 | F38: Conversa com o Mar | G38: CineCarioca José Wilker | H38: Rua Leite Leal, 45 | I38: 2
A39: 46299 | B39: Dom | C39: 0.90625 | D39: Panorama Mundial | E39: {=_xlfn.XLOOKUP(F39, Filmes!$D$2:$D$344, Filmes!$A$2:$A$344, "")} -> 012 | F39: Covarde | G39: Cine Odeon - CCLSR | H39: Praça Floriano, 7
A40: 46304 | B40: Sex | C40: 0.59375 | D40: Panorama Mundial | E40: {=_xlfn.XLOOKUP(F40, Filmes!$D$2:$D$344, Filmes!$A$2:$A$344, "")} -> 012 | F40: Covarde | G40: Cinesystem Belas Artes Botafogo | H40: Praia de Botafogo, 316 | I40: 6
A41: 46306 | B41: Dom | C41: 0.70833333 | D41: Panorama Mundial | E41: {=_xlfn.XLOOKUP(F41, Filmes!$D$2:$D$344, Filmes!$A$2:$A$344, "")} -> 012 | F41: Covarde | G41: Estação Claro Gávea | H41: Rua Marquês de São Vicente, 52 | I41: 5
A42: 46298 | B42: Sáb | C42: 0.86458333 | D42: Panorama Mundial | E42: {=_xlfn.XLOOKUP(F42, Filmes!$D$2:$D$344, Filmes!$A$2:$A$344, "")} -> 013 | F42: Crianças Invisíveis | G42: Estação Claro Rio | H42: Rua Voluntários da Pátria, 35 | I42: 5
A43: 46301 | B43: Ter | C43: 0.57291667 | D43: Panorama Mundial | E43: {=_xlfn.XLOOKUP(F43, Filmes!$D$2:$D$344, Filmes!$A$2:$A$344, "")} -> 013 | F43: Crianças Invisíveis | G43: CineCarioca José Wilker | H43: Rua Leite Leal, 45 | I43: 2
A44: 46304 | B44: Sex | C44: 0.66666667 | D44: Panorama Mundial | E44: {=_xlfn.XLOOKUP(F44, Filmes!$D$2:$D$344, Filmes!$A$2:$A$344, "")} -> 013 | F44: Crianças Invisíveis | G44: Estação Claro Gávea | H44: Rua Marquês de São Vicente, 52 | I44: 2
A45: 46300 | B45: Seg | C45: 0.54166667 | D45: Panorama Mundial | E45: {=_xlfn.XLOOKUP(F45, Filmes!$D$2:$D$344, Filmes!$A$2:$A$344, "")} -> 014 | F45: Dau | G45: Cinesystem Belas Artes Botafogo | H45: Praia de Botafogo, 316 | I45: 2
A46: 46305 | B46: Sáb | C46: 0.70833333 | D46: Panorama Mundial | E46: {=_xlfn.XLOOKUP(F46, Filmes!$D$2:$D$344, Filmes!$A$2:$A$344, "")} -> 014 | F46: Dau | G46: Estação Claro Rio | H46: Rua Voluntários da Pátria, 35 | I46: 4
A47: 46309 | B47: Qua | C47: 0.625 | D47: Panorama Mundial | E47: {=_xlfn.XLOOKUP(F47, Filmes!$D$2:$D$344, Filmes!$A$2:$A$344, "")} -> 014 | F47: Dau | G47: Estação Claro Gávea | H47: Rua Marquês de São Vicente, 52 | I47: 5
A48: 46297 | B48: Sex | C48: 0.6875 | D48: Panorama Mundial | E48: {=_xlfn.XLOOKUP(F48, Filmes!$D$2:$D$344, Filmes!$A$2:$A$344, "")} -> 015 | F48: Diários de Nagi | G48: Cinesystem Belas Artes Botafogo | H48: Praia de Botafogo, 316 | I48: 4
A49: 46299 | B49: Dom | C49: 0.59375 | D49: Panorama Mundial | E49: {=_xlfn.XLOOKUP(F49, Filmes!$D$2:$D$344, Filmes!$A$2:$A$344, "")} -> 015 | F49: Diários de Nagi | G49: Estação Claro Rio | H49: Rua Voluntários da Pátria, 35 | I49: 4
A50: 46305 | B50: Sáb | C50: 0.83333333 | D50: Panorama Mundial | E50: {=_xlfn.XLOOKUP(F50, Filmes!$D$2:$D$344, Filmes!$A$2:$A$344, "")} -> 015 | F50: Diários de Nagi | G50: CineCarioca José Wilker | H50: Rua Leite Leal, 45 | I50: 2
A51: 46300 | B51: Seg | C51: 0.69791667 | D51: Panorama Mundial | E51: {=_xlfn.XLOOKUP(F51, Filmes!$D$2:$D$344, Filmes!$A$2:$A$344, "")} -> 016 | F51: Eu Juro | G51: Cinesystem Belas Artes Botafogo | H51: Praia de Botafogo, 316 | I51: 6
... A53: 46305 | B53: Sáb | C53: 0.58333333 | D53: Panorama Mundial | E53: {=_xlfn.XLOOKUP(F53, Filmes!$D$2:$D$344, Filmes!$A$2:$A$344, "")} -> 016 | F53: Eu Juro | G53: Estação Claro Gávea | H53: Rua Marquês de São Vicente, 52 | I53: 2
A54: 46302 | B54: Qua | C54: 0.80208333 | D54: Panorama Mundial | E54: {=_xlfn.XLOOKUP(F54, Filmes!$D$2:$D$344, Filmes!$A$2:$A$344, "")} -> 017 | F54: Euforia | G54: Cinesystem Belas Artes Botafogo | H54: Praia de Botafogo, 316 | I54: 6 | L54: Sim
A55: 46304 | B55: Sex | C55: 0.57291667 | D55: Panorama Mundial | E55: {=_xlfn.XLOOKUP(F55, Filmes!$D$2:$D$344, Filmes!$A$2:$A$344, "")} -> 017 | F55: Euforia | G55: CineCarioca José Wilker | H55: Rua Leite Leal, 45 | I55: 2
A56: 46306 | B56: Dom | C56: 0.69791667 | D56: Panorama Mundial | E56: {=_xlfn.XLOOKUP(F56, Filmes!$D$2:$D$344, Filmes!$A$2:$A$344, "")} -> 017 | F56: Euforia | G56: Estação Claro Rio | H56: Rua Voluntários da Pátria, 35 | I56: 5
A57: 46297 | B57: Sex | C57: 0.65625 | D57: Panorama Mundial | E57: {=_xlfn.XLOOKUP(F57, Filmes!$D$2:$D$344, Filmes!$A$2:$A$344, "")} -> 018 | F57: Histórias de Família | G57: CineCarioca José Wilker | H57: Rua Leite Leal, 45 | I57: 2
A58: 46298 | B58: Sáb | C58: 0.58333333 | D58: Panorama Mundial | E58: {=_xlfn.XLOOKUP(F58, Filmes!$D$2:$D$344, Filmes!$A$2:$A$344, "")} -> 018 | F58: Histórias de Família | G58: Reserva Cultural Niterói | H58: Av. Visconde do Rio Branco, 880 | I58: 1
A59: 46305 | B59: Sáb | C59: 0.875 | D59: Panorama Mundial | E59: {=_xlfn.XLOOKUP(F59, Filmes!$D$2:$D$344, Filmes!$A$2:$A$344, "")} -> 018 | F59: Histórias de Família | G59: Cinesystem Belas Artes Botafogo | H59: Praia de Botafogo, 316 | I59: 4
A60: 46296 | B60: Qui | C60: 0.58333333 | D60: Panorama Mundial | E60: {=_xlfn.XLOOKUP(F60, Filmes!$D$2:$D$344, Filmes!$A$2:$A$344, "")} -> 019 | F60: Histórias Noturnas | G60: Reserva Cultural Niterói | H60: Av. Visconde do Rio Branco, 880 | I60: 1
A61: 46298 | B61: Sáb | C61: 0.79861111 | D61: Panorama Mundial | E61: {=_xlfn.XLOOKUP(F61, Filmes!$D$2:$D$344, Filmes!$A$2:$A$344, "")} -> 019 | F61: Histórias Noturnas | G61: Kinoplex São Luiz | H61: Rua do Catete, 311 - Catete | I61: 2
A62: 46304 | B62: Sex | C62: 0.6875 | D62: Panorama Mundial | E62: {=_xlfn.XLOOKUP(F62, Filmes!$D$2:$D$344, Filmes!$A$2:$A$344, "")} -> 019 | F62: Histórias Noturnas | G62: Cinesystem Belas Artes Botafogo | H62: Praia de Botafogo, 316 | I62: 4
A63: 46302 | B63: Qua | C63: 0.82291667 | D63: Panorama Mundial | E63: {=_xlfn.XLOOKUP(F63, Filmes!$D$2:$D$344, Filmes!$A$2:$A$344, "")} -> 020 | F63: I want your sex | G63: Cine Odeon - CCLSR | H63: Praça Floriano, 7
A64: 46304 | B64: Sex | C64: 0.89583333 | D64: Panorama Mundial | E64: {=_xlfn.XLOOKUP(F64, Filmes!$D$2:$D$344, Filmes!$A$2:$A$344, "")} -> 020 | F64: I want your sex | G64: Kinoplex São Luiz | H64: Rua do Catete, 311 - Catete | I64: 2
A65: 46306 | B65: Dom | C65: 0.70833333 | D65: Panorama Mundial | E65: {=_xlfn.XLOOKUP(F65, Filmes!$D$2:$D$344, Filmes!$A$2:$A$344, "")} -> 020 | F65: I want your sex | G65: Cinesystem Belas Artes Botafogo | H65: Praia de Botafogo, 316 | I65: 6
A66: 46299 | B66: Dom | C66: 0.8125 | D66: Panorama Mundial | E66: {=_xlfn.XLOOKUP(F66, Filmes!$D$2:$D$344, Filmes!$A$2:$A$344, "")} -> 021 | F66: Ink | G66: Cine Odeon - CCLSR | H66: Praça Floriano, 7
A67: 46303 | B67: Qui | C67: 0.69791667 | D67: Panorama Mundial | E67: {=_xlfn.XLOOKUP(F67, Filmes!$D$2:$D$344, Filmes!$A$2:$A$344, "")} -> 021 | F67: Ink | G67: Cinesystem Belas Artes Botafogo | H67: Praia de Botafogo, 316 | I67: 6
A68: 46306 | B68: Dom | C68: 0.875 | D68: Panorama Mundial | E68: {=_xlfn.XLOOKUP(F68, Filmes!$D$2:$D$344, Filmes!$A$2:$A$344, "")} -> 021 | F68: Ink | G68: Kinoplex São Luiz | H68: Rua do Catete, 311 - Catete | I68: 2
A69: 46304 | B69: Sex | C69: 0.80208333 | D69: Panorama Mundial | E69: {=_xlfn.XLOOKUP(F69, Filmes!$D$2:$D$344, Filmes!$A$2:$A$344, "")} -> 022 | F69: Josephine - Fragmentos de um Crime | G69: Cine Odeon - CCLSR | H69: Praça Floriano, 7 | L69: Sim
A70: 46305 | B70: Sáb | C70: 0.88541667 | D70: Panorama Mundial | E70: {=_xlfn.XLOOKUP(F70, Filmes!$D$2:$D$344, Filmes!$A$2:$A$344, "")} -> 022 | F70: Josephine - Fragmentos de um Crime | G70: Reserva Cultural Niterói | H70: Av. Visconde do Rio Branco, 880 | I70: 1
A71: 46306 | B71: Dom | C71: 0.90625 | D71: Panorama Mundial | E71: {=_xlfn.XLOOKUP(F71, Filmes!$D$2:$D$344, Filmes!$A$2:$A$344, "")} -> 022 | F71: Josephine - Fragmentos de um Crime | G71: Estação Claro Gávea | H71: Rua Marquês de São Vicente, 52 | I71: 5
A72: 46296 | B72: Qui | C72: 0.79166667 | D72: Panorama Mundial | E72: {=_xlfn.XLOOKUP(F72, Filmes!$D$2:$D$344, Filmes!$A$2:$A$344, "")} -> 023 | F72: Monstro Gentil | G72: Kinoplex São Luiz | H72: Rua do Catete, 311 - Catete | I72: 2
A73: 46299 | B73: Dom | C73: 0.90625 | D73: Panorama Mundial | E73: {=_xlfn.XLOOKUP(F73, Filmes!$D$2:$D$344, Filmes!$A$2:$A$344, "")} -> 023 | F73: Monstro Gentil | G73: Estação Claro Gávea | H73: Rua Marquês de São Vicente, 52 | I73: 5
A74: 46301 | B74: Ter | C74: 0.69791667 | D74: Panorama Mundial | E74: {=_xlfn.XLOOKUP(F74, Filmes!$D$2:$D$344, Filmes!$A$2:$A$344, "")} -> 023 | F74: Monstro Gentil | G74: Cinesystem Belas Artes Botafogo | H74: Praia de Botafogo, 316 | I74: 6
A75: 46297 | B75: Sex | C75: 0.90277778 | D75: Panorama Mundial | E75: {=_xlfn.XLOOKUP(F75, Filmes!$D$2:$D$344, Filmes!$A$2:$A$344, "")} -> 024 | F75: No Good Men | G75: Kinoplex São Luiz | H75: Rua do Catete, 311 - Catete | I75: 2
A76: 46299 | B76: Dom | C76: 0.70833333 | D76: Panorama Mundial | E76: {=_xlfn.XLOOKUP(F76, Filmes!$D$2:$D$344, Filmes!$A$2:$A$344, "")} -> 024 | F76: No Good Men | G76: Reserva Cultural Niterói | H76: Av. Visconde do Rio Branco, 880 | I76: 1
A77: 46301 | B77: Ter | C77: 0.59375 | D77: Panorama Mundial | E77: {=_xlfn.XLOOKUP(F77, Filmes!$D$2:$D$344, Filmes!$A$2:$A$344, "")} -> 024 | F77: No Good Men | G77: Estação Claro Rio | H77: Rua Voluntários da Pátria, 35 | I77: 4
A78: 46303 | B78: Qui | C78: 0.84375 | D78: Panorama Mundial | E78: {=_xlfn.XLOOKUP(F78, Filmes!$D$2:$D$344, Filmes!$A$2:$A$344, "")} -> 024 | F78: No Good Men | G78: Cine Santa Teresa | H78: Rua Paschoal Carlos Magno, 136
A79: 46306 | B79: Dom | C79: 0.78125 | D79: Panorama Mundial | E79: {=_xlfn.XLOOKUP(F79, Filmes!$D$2:$D$344, Filmes!$A$2:$A$344, "")} -> 024 | F79: No Good Men | G79: Cinesystem Belas Artes Botafogo | H79: Praia de Botafogo, 316 | I79: 5
A80: 46297 | B80: Sex | C80: 0.76041667 | D80: Panorama Mundial | E80: {=_xlfn.XLOOKUP(F80, Filmes!$D$2:$D$344, Filmes!$A$2:$A$344, "")} -> 025 | F80: Nós Somos os Frutos da Floresta | G80: Estação Claro Gávea | H80: Rua Marquês de São Vicente, 52 | I80: 3
A81: 46300 | B81: Seg | C81: 0.6875 | D81: Panorama Mundial | E81: {=_xlfn.XLOOKUP(F81, Filmes!$D$2:$D$344, Filmes!$A$2:$A$344, "")} -> 025 | F81: Nós Somos os Frutos da Floresta | G81: Cinesystem Belas Artes Botafogo | H81: Praia de Botafogo, 316 | I81: 1
A82: 46302 | B82: Qua | C82: 0.83333333 | D82: Panorama Mundial | E82: {=_xlfn.XLOOKUP(F82, Filmes!$D$2:$D$344, Filmes!$A$2:$A$344, "")} -> 025 | F82: Nós Somos os Frutos da Floresta | G82: CineCarioca José Wilker | H82: Rua Leite Leal, 45 | I82: 1
A83: 46297 | B83: Sex | C83: 0.875 | D83: Panorama Mundial | E83: {=_xlfn.XLOOKUP(F83, Filmes!$D$2:$D$344, Filmes!$A$2:$A$344, "")} -> 026 | F83: O Cheiro das Maçãs | G83: Estação Claro Rio | H83: Rua Voluntários da Pátria, 35 | I83: 5 | L83: Sim
A84: 46299 | B84: Dom | C84: 0.66666667 | D84: Panorama Mundial | E84: {=_xlfn.XLOOKUP(F84, Filmes!$D$2:$D$344, Filmes!$A$2:$A$344, "")} -> 026 | F84: O Cheiro das Maçãs | G84: Cinesystem Belas Artes Botafogo | H84: Praia de Botafogo, 316 | I84: 2
A85: 46306 | B85: Dom | C85: 0.58333333 | D85: Panorama Mundial | E85: {=_xlfn.XLOOKUP(F85, Filmes!$D$2:$D$344, Filmes!$A$2:$A$344, "")} -> 026 | F85: O Cheiro das Maçãs | G85: CineCarioca José Wilker | H85: Rua Leite Leal, 45 | I85: 1
A86: 46296 | B86: Qui | C86: 0.89583333 | D86: Panorama Mundial | E86: {=_xlfn.XLOOKUP(F86, Filmes!$D$2:$D$344, Filmes!$A$2:$A$344, "")} -> 027 | F86: O Objeto do Delito | G86: Estação Claro Gávea | H86: Rua Marquês de São Vicente, 52 | I86: 2
A87: 46298 | B87: Sáb | C87: 0.72916667 | D87: Panorama Mundial | E87: {=_xlfn.XLOOKUP(F87, Filmes!$D$2:$D$344, Filmes!$A$2:$A$344, "")} -> 027 | F87: O Objeto do Delito | G87: CineCarioca José Wilker | H87: Rua Leite Leal, 45 | I87: 2
A88: 46302 | B88: Qua | C88: 0.66666667 | D88: Panorama Mundial | E88: {=_xlfn.XLOOKUP(F88, Filmes!$D$2:$D$344, Filmes!$A$2:$A$344, "")} -> 027 | F88: O Objeto do Delito | G88: Cinesystem Belas Artes Botafogo | H88: Praia de Botafogo, 316 | I88: 4
A89: 46300 | B89: Seg | C89: 0.79166667 | D89: Panorama Mundial | E89: {=_xlfn.XLOOKUP(F89, Filmes!$D$2:$D$344, Filmes!$A$2:$A$344, "")} -> 028 | F89: O Rebelde | G89: Kinoplex São Luiz | H89: Rua do Catete, 311 - Catete | I89: 2
A90: 46302 | B90: Qua | C90: 0.90625 | D90: Panorama Mundial | E90: {=_xlfn.XLOOKUP(F90, Filmes!$D$2:$D$344, Filmes!$A$2:$A$344, "")} -> 028 | F90: O Rebelde | G90: Cinesystem Belas Artes Botafogo | H90: Praia de Botafogo, 316 | I90: 6
A91: 46305 | B91: Sáb | C91: 0.60416667 | D91: Panorama Mundial | E91: {=_xlfn.XLOOKUP(F91, Filmes!$D$2:$D$344, Filmes!$A$2:$A$344, "")} -> 028 | F91: O Rebelde | G91: Estação Claro Gávea | H91: Rua Marquês de São Vicente, 52 | I91: 5
A92: 46298 | B92: Sáb | C92: 0.6875 | D92: Panorama Mundial | E92: {=_xlfn.XLOOKUP(F92, Filmes!$D$2:$D$344, Filmes!$A$2:$A$344, "")} -> 029 | F92: O(s) Assassino(s) | G92: Cinesystem Belas Artes Botafogo | H92: Praia de Botafogo, 316 | I92: 6
A93: 46300 | B93: Seg | C93: 0.89583333 | D93: Panorama Mundial | E93: {=_xlfn.XLOOKUP(F93, Filmes!$D$2:$D$344, Filmes!$A$2:$A$344, "")} -> 029 | F93: O(s) Assassino(s) | G93: Kinoplex São Luiz | H93: Rua do Catete, 311 - Catete | I93: 2
A94: 46304 | B94: Sex | C94: 0.82291667 | D94: Panorama Mundial | E94: {=_xlfn.XLOOKUP(F94, Filmes!$D$2:$D$344, Filmes!$A$2:$A$344, "")} -> 029 | F94: O(s) Assassino(s) | G94: CineCarioca José Wilker | H94: Rua Leite Leal, 45 | I94: 2
A95: 46301 | B95: Ter | C95: 0.80208333 | D95: Panorama Mundial | E95: {=_xlfn.XLOOKUP(F95, Filmes!$D$2:$D$344, Filmes!$A$2:$A$344, "")} -> 030 | F95: O Último Resort | G95: Estação Claro Rio | H95: Rua Voluntários da Pátria, 35 | I95: 3 | L95: Sim
A96: 46304 | B96: Sex | C96: 0.89583333 | D96: Panorama Mundial | E96: {=_xlfn.XLOOKUP(F96, Filmes!$D$2:$D$344, Filmes!$A$2:$A$344, "")} -> 030 | F96: O Último Resort | G96: Cinesystem Belas Artes Botafogo | H96: Praia de Botafogo, 316 | I96: 1
A97: 46306 | B97: Dom | C97: 0.57291667 | D97: Panorama Mundial | E97: {=_xlfn.XLOOKUP(F97, Filmes!$D$2:$D$344, Filmes!$A$2:$A$344, "")} -> 030 | F97: O Último Resort | G97: Cine Santa Teresa | H97: Rua Paschoal Carlos Magno, 136
A98: 46296 | B98: Qui | C98: 0.78125 | D98: Panorama Mundial | E98: {=_xlfn.XLOOKUP(F98, Filmes!$D$2:$D$344, Filmes!$A$2:$A$344, "")} -> 031 | F98: Oito Pontes | G98: Cinesystem Belas Artes Botafogo | H98: Praia de Botafogo, 316 | I98: 5
A99: 46300 | B99: Seg | C99: 0.6875 | D99: Panorama Mundial | E99: {=_xlfn.XLOOKUP(F99, Filmes!$D$2:$D$344, Filmes!$A$2:$A$344, "")} -> 031 | F99: Oito Pontes | G99: Estação Claro Rio | H99: Rua Voluntários da Pátria, 35 | I99: 3
A100: 46305 | B100: Sáb | C100: 0.84375 | D100: Panorama Mundial | E100: {=_xlfn.XLOOKUP(F100, Filmes!$D$2:$D$344, Filmes!$A$2:$A$344, "")} -> 031 | F100: Oito Pontes | G100: CineCarioca José Wilker | H100: Rua Leite Leal, 45 | I100: 1
A101: 46296 | B101: Qui | C101: 0.5625 | D101: Panorama Mundial | E101: {=_xlfn.XLOOKUP(F101, Filmes!$D$2:$D$344, Filmes!$A$2:$A$344, "")} -> 032 | F101: Os Frutos da Terra | G101: CineCarioca José Wilker | H101: Rua Leite Leal, 45 | I101: 2
...
